Workbook

Sheet consolidado
A1: codigoOC | B1: FechaEnvioOC | C1: NombreOC | D1: DescripcionOC | E1: MontoNetoOC | F1: DescuentosOC | G1: CargosOC | H1: ImpuestosOC | I1: MontoTotalOC | J1: UnidadCompra | K1: Proveedor | L1: ProveedorRUT | M1: ActividadProveedor | N1: TamanoProveedor | O1: RegionProveedor | P1: CodigoProductoONU | Q1: DescripcionItem | R1: CantidadItem | S1: UnidadMedida | T1: MontoNetoItem | U1: MontoTotalItem | V1: CodigoCotizacion | W1: DescripcionCotizacion | X1: CodigoProductoCotizadoONU | Y1: RUTProveedorCotizacion | Z1: DetalleCotizacion
A2: 1058012-6724-AG25 | B2: 45934 | C2: URGENTE FARMACIA DOSIS UNITARIA ABRIL / BENRALIZUMAB 30 MG JGA | D2: PEDIDO URGENTE FARMACIA DOSIS UNITARIA ABRIL. COMPRA AGIL DESPACHO AEREO CARGO DEL PROVEEDOR. 1058012-191-COT25 | E2: 3189516 | F2: 0 | G2: 0 | H2: 606008.04 | I2: 3795524 | J2: Fármarcos | K2: ASTRAZENECA SA | L2: 76.447.530-5 | M2: VENTA AL POR MAYOR DE PRODUCTOS FARMACEUTICOS | N2: Grande | O2: Región Metropolitana de Santiago | P2: 85121902 | Q2: BENRALIZUMAB 30 MG JERINGA PRELLENADA | R2: 2 | S2: Unidad | T2: 1594758 | U2: 3189516 | V2: 1058012-191-COT25 | W2: EL HOSPITAL CLÍNICO DE MAGALLANES REQUIERE BENRALIZUMAB 30 MG JGA. INDICAR AL COTIZAR: VALOR UNITARIO TOTAL, PRESENTACIÓN (UD), FECHA VCTO, ADJUNTAR FICHA TÉCNICA Y/O REGISTRO ISP, TIPO DE TRASLADO (ESPECIFICAR, PARA ACORDAR RETIRO CARGO HOSPITAL DE SER NECESARIO), E INDICAR SI CUENTA CON STOCK PARA DESPACHO INMEDIATO. SE DECLARARÁ INADMISIBLE OFERTA QUE INDIQUE VALOR REFERENCIAL $0 o $1, U OMITAN CUALQUIER INFORMACIÓN SOLICITADA PARA ESTA COTIZACIÓN. | X2: 85121902 | Y2: 76.447.530-5 | Z2: Fármaco innovador y/o referente. Venc > 1 año, despacho 2-3 días hábiles desde aceptación de orden de compra. Flete incluido. Cuando genere su OC, el rut de compra y dirección de despacho deben poseer autorización sanitaria vigente.
A3: 1058012-1778-AG24 | B3: 45495 | C3: (FAR) COMITÉ FARMACIA JULIO / RILPIVIRINA - CABOTEGRAVIR 900-600 MG FA | D3: PEDIDO COMITÉ FARMACIA JULIO. ADQUISICIÓN VÍA COMPRA ÁGIL. FLETE 72 HORAS HÁBILES SEGÚN COTIZACIÓN. REF 1058012-497-COT24. | E3: 1518000 | F3: 0 | G3: 0 | H3: 288420 | I3: 1806420 | J3: Fármarcos | K3: GLAXOSMITHKLINE CHILE FARMACEUTICA LIMITADA | L3: 85.025.700-0 | M3: FABRICACION DE PRODUCTOS FARMACEUTICOS, SUSTANCIAS QUIMICAS MEDICINALE | N3: Grande | O3: Región Metropolitana de Santiago | P3: 85121902 | Q3: RILPIRIVINA - CABOTEGRAVIR 900-600 MG FA | R3: 3 | S3: Frasco Ampolla | T3: 506000 | U3: 1518000 | V3: 1058012-497-COT24 | W3: EL HOSPITAL CLÍNICO DE MAGALLANES REQUIERE RILPIRIVINA - CABOTEGRAVIR 900-600 MG FA. INDICAR AL COTIZAR: VALOR UNITARIO TOTAL, PRESENTACIÓN (FA), FECHA VCTO, ADJUNTAR FICHA TÉCNICA Y/O REGISTRO ISP, TIPO DE TRASLADO CARGO PROVEEDOR (ESPECIFICAR, PARA ACORDAR RETIRO CARGO HOSPITAL DE SER NECESARIO), E INDICAR SI CUENTA CON STOCK PARA DESPACHO INMEDIATO. SE DESESTIMARÁ OFERTA QUE INDIQUE VALOR REFERENCIAL $0 o $1, U OMITAN INFORMACIÓN. | X3: 85121902 | Y3: 85.025.700-0 | Z3: Validez de la oferta 90 días. Facturación mínima $250.000.- neto. Vencimiento superior a doce meses, ENTREGA: 72Horas hábiles una vez aceptada la orden de compra. Condiciones Comerciales, Flete incluido. contacto gsk.ordenesdecompra@gsk.com
A4: 1058012-61-AG24 | B4: 45627 | C4: COMITÉ FARMACIA N°10 AÑO 2023/ RILPIRIVINA - CABOTEGRAVIR 900-600 MG FA | D4: PEDIDO COMITÉ FARMACIA N°10 AÑO 2023. COMPRA AGIL. FLETE AEREO CARGO DEL PROVEEDOR 1058012-15-COT24 | E4: 1518000 | F4: 0 | G4: 0 | H4: 288420 | I4: 1806420 | J4: Fármarcos | K4: GLAXOSMITHKLINE CHILE FARMACEUTICA LIMITADA | L4: 85.025.700-0 | M4: FABRICACION DE PRODUCTOS FARMACEUTICOS, SUSTANCIAS QUIMICAS MEDICINALE | N4: Grande | O4: Región Metropolitana de Santiago | P4: 51191905 | Q4: RILPIRIVINA - CABOTEGRAVIR 900-600 MG FA | R4: 3 | S4: Frasco Ampolla | T4: 506000 | U4: 1518000 | V4: 1058012-15-COT24 | W4: EL HOSPITAL CLÍNICO DE MAGALLANES REQUIERE CABOTEGRAVIR/RILPIVIRINA 600/900 MF FA. INDICAR AL COTIZAR: VALOR UNITARIO TOTAL, PRESENTACIÓN (ML), FECHA VCTO, ADJUNTAR FICHA TÉCNICA Y/O REGISTRO ISP, TIPO DE TRASLADO (ESPECIFICAR, PARA ACORDAR RETIRO CARGO HOSPITAL DE SER NECESARIO), E INDICAR SI CUENTA CON STOCK PARA DESPACHO INMEDIATO. SE DESESTIMARÁ OFERTA QUE INDIQUE VALOR REFERENCIAL $0 o $1, U OMITAN INFORMACIÓN. | X4: 51191905 | Y4: 85.025.700-0 | Z4: Validez de la oferta 90 días. Facturación mínima $250.000.- neto. Vencimiento superior a doce meses, ENTREGA: 48 Horas hábiles una vez aceptada la orden de compra. Políticas de Devolución punto d), Flete incluido. contacto gsk.ordenesdecompra@gsk.com
A5: 1058012-7475-AG25 | B5: 45825 | C5: FALTA CENABAST FARMACIA AMBULATORIA JUNIO / DENOSUMAB 60 MG ML SOL INY | D5: PEDIDO FALTA CENABAST FARMACIA AMBULATORIA JUNIO. ADQUISICIÓN VÍA COMPRA ÁGIL. DESPACHO 7 DÍAS CARGO DEL PROVEEDOR SEGÚN COTIZACIÓN. ZGEN 100004663. REF 1058012-408-COT25. | E5: 564448 | F5: 0 | G5: 0 | H5: 107245.12 | I5: 671693.12 | J5: Fármarcos | K5: SCM PHARMA SPA | L5: 77.337.544-5 | M5: VENTA AL POR MAYOR DE PRODUCTOS FARMACEUTICOS Y MEDICINALES | N5: Mediana | O5: Región Metropolitana de Santiago | P5: 85121902 | Q5: DENOSUMAB 60 MG ML SOLUCIÓN INYECTABLE | R5: 2 | S5: Frasco Ampolla | T5: 282224 | U5: 564448 | V5: 1058012-408-COT25 | W5: EL HOSPITAL CLÍNICO DE MAGALLANES REQUIERE DENOSUMAB 60 MG ML SOL INY. INDICAR AL COTIZAR: VALOR UNITARIO TOTAL, PRESENTACIÓN (UD), FECHA VCTO, ADJUNTAR FICHA TÉCNICA Y/O REGISTRO ISP, TIPO DE TRASLADO Y FECHA ESPECIFICA DE ENTREGA (ESPECIFICAR, PARA ACORDAR RETIRO CARGO HOSPITAL DE SER NECESARIO), E INDICAR SI CUENTA CON STOCK PARA DESPACHO INMEDIATO. SE DECLARARÁ INADMISIBLE OFERTA QUE INDIQUE VALOR REFERENCIAL $0 o $1, U OMITAN INFORMACIÓN Y DOCUMENTOS SOLICITADOS. | X5: 85121902 | Y5: 77.337.544-5 | Z5: Se adjunta cotización detallada, Contacto F. 225104550, contacto@scmpharma.cl, Despacho sin costo, Envio 7 dias- monto mínimo de despacho $ 100.000.- Cotización valida por 15 días.
A6: 1058012-7755-AG25 | B6: 45859 | C6: FALTA CENABAST (SUSPENDIDO) JULIO / DENOSUMAB 60 MG ML SOL INY | D6: PEDIDO FALTA CENABAST (SUSPENDIDO) JULIO. ADQUISICIÓN VÍA COMPRA ÁGIL. DESPACHO 7 DÍAS CARGO DEL PROVEEDOR SEGÚN COTIZACIÓN. ZGEN 100004663. REF 1058012-465-COT25. | E6: 1128896 | F6: 0 | G6: 0 | H6: 214490.24 | I6: 1343386.2 | J6: Fármarcos | K6: SCM PHARMA SPA | L6: 77.337.544-5 | M6: VENTA AL POR MAYOR DE PRODUCTOS FARMACEUTICOS Y MEDICINALES | N6: Mediana | O6: Región Metropolitana de Santiago | P6: 85121902 | Q6: DENOSUMAB 60 MG ML SOLUCIÓN INYECTABLE | R6: 4 | S6: Unidad | T6: 282224 | U6: 1128896 | V6: 1058012-465-COT25 | W6: EL HOSPITAL CLÍNICO DE MAGALLANES REQUIERE DENOSUMAB 60 MG ML SOL INY. INDICAR AL COTIZAR: VALOR UNITARIO TOTAL, PRESENTACIÓN (UD), FECHA VCTO, ADJUNTAR FICHA TÉCNICA Y/O REGISTRO ISP, TIPO DE TRASLADO (ESPECIFICAR, PARA ACORDAR RETIRO CARGO HOSPITAL DE SER NECESARIO), E INDICAR SI CUENTA CON STOCK PARA DESPACHO INMEDIATO. SE DECLARARÁ INADMISIBLE OFERTA QUE INDIQUE VALOR REFERENCIAL $1, U OMITAN INFORMACIÓN Y DOCUMENTOS SOLICITADOS. | X6: 85121902 | Y6: 77.337.544-5 | Z6: Se adjunta cotización detallada, Contacto F. 225104550, contacto@scmpharma.cl, Despacho sin costo, Envio 7 dias- monto mínimo de despacho $ 100.000.- Cotización valida por 15 días.
A7: 1058012-1513-AG24 | B7: 45462 | C7: FARMACIA DOSIS UNITARIA/ IBUPROFENO 10 MG/2 ML AMP | D7: PEDIDO FARMACIA DOSIS UNITARIA.COMPRA AGIL DESPACHO AÉREO, CARGO DEL PROVEEDOR. 1058012-420-COT24 | E7: 1580000 | F7: 0 | G7: 0 | H7: 300200 | I7: 1880200 | J7: Fármarcos | K7: innovative medicines s.a . agencia en chile | L7: 59.144.890-0 | M7: venta al por menor de productos medicinales | N7: Mediana | O7: Región Metropolitana de Santiago | P7: 51142106 | Q7: IBUPROFENO 10 MG/2 ML AMP | R7: 8 | S7: Ampolla | T7: 197500 | U7: 1580000 | V7: 1058012-420-COT24 | W7: EL HOSPITAL CLÍNICO DE MAGALLANES REQUIERE IBUPROFENO 10 MG/2 ML AMP . INDICAR AL COTIZAR: VALOR UNITARIO TOTAL, PRESENTACIÓN (ML), FECHA VCTO, ADJUNTAR FICHA TÉCNICA Y/O REGISTRO ISP, TIPO DE TRASLADO y ESPECIFICAR FECHA DE ENTREGA, INDICAR SI CUENTA CON STOCK PARA DESPACHO INMEDIATO. SE DESESTIMARÁ OFERTA QUE INDIQUE VALOR REFERENCIAL $0 o $1, U OMITAN INFORMACIÓN. | X7: 51142106 | Y7: 59.144.890-0 | Z7: PRODUCTO PEDEA, autorizado en Chile bajo Resolución Exenta N° 33509 (adjunta), unidades en Chile disponibles para despacho inmediato, vencimiento 31.12.2025.
A8: 1058012-862-AG24 | B8: 45600 | C8: COMITÉ FARMACIA / CARBOXIMALTOSA DE HIERRO SOLUCIÓN INYECTABLE 500 MG/10 ML, AMP | D8: PEDIDO COMITÉ FARMACIA. COMPRA ÁGIL DESPACHO AÉREO CARGO DEL PROVEEDOR. 1058012-269-COT24 | E8: 141500 | F8: 0 | G8: 0 | H8: 26885 | I8: 168385 | J8: Fármarcos | K8: LABORATORIOS ANDROMACO S.A. | L8: 76.237.266-5 | M8: FARMACEUTICO | N8: Grande | O8: Región Metropolitana de Santiago | P8: 51131514 | Q8: CARBOXIMALTOSA DE HIERRO SOLUCIÓN INYECTABLE 500 MG/10 ML, AMP | R8: 1 | S8: Unidad | T8: 141500 | U8: 141500 | V8: 1058012-269-COT24 | W8: EL HOSPITAL CLÍNICO DE MAGALLANES REQUIERE CARBOXIMALTOSA DE HIERRO SOLUCIÓN INYECTABLE 500 MG/10 ML, AMP. INDICAR AL COTIZAR: VALOR UNITARIO TOTAL, PRESENTACIÓN (ML), FECHA VCTO, ADJUNTAR FICHA TÉCNICA Y/O REGISTRO ISP, TIPO DE TRASLADO (ESPECIFICAR, PARA ACORDAR RETIRO CARGO HOSPITAL DE SER NECESARIO), E INDICAR SI CUENTA CON STOCK PARA DESPACHO INMEDIATO. SE DESESTIMARÁ OFERTA QUE INDIQUE VALOR REFERENCIAL $0 o $1, U OMITAN INFORMACIÓN. | X8: 51131514 | Y8: 76.237.266-5 | Z8: 22100383 FERINJECT SOLUCION INYECTABLE 500/10 ML - 500MG DE HIERRO COMO CARBOXIMALTOSA DE HIERRO - FRASCO DE SOLUCION INYECTABLE REG. ISP F-20175/23, FECHA DE VCTO 30-06-2026, DESPACHO EN 02 D?AS MONTO M?NIMO DE DESPACHO $300.000 NETO
A9: 1058012-7375-AG25 | B9: 45936 | C9: COMPRA ALTERNATIVA (7225) FALTA CENABAST/ RISPERIDONA 37,5 MG FA POLVO LIOFILIZADO | D9: PEDIDO COMPRA ALTERNATIVA(7225). COMPRA AGIL. DESPACHO A CARGO DEL PROVEEDOR. 1058012-380-COT25 | E9: 1300000 | F9: 0 | G9: 0 | H9: 247000 | I9: 1547000 | J9: Fármarcos | K9: LABORATORIO C&D PHARMA LIMITADA | L9: 76.394.174-4 | M9: VENTA AL POR MAYOR DE PRODUCTOS FARMACEUTICOS | N9: Mediana | O9: Región Metropolitana de Santiago | P9: 51141704 | Q9: RISPERIDONA 37,5 MG FA POLVO LIOFILIZADO | R9: 10 | S9: Frasco Ampolla | T9: 130000 | U9: 1300000 | V9: 1058012-380-COT25 | W9: EL HCM REQUIERE RISPERIDONA 37,5 MG FA POLVO LIOFILIZADO. INDICAR FECHA DE ENTREGA EN BODEGA HCM, FACTOR EMPAQUE, FECHA VCTO, ADJUNTAR FICHA TÉCNICA Y/O REGISTRO ISP, TIPO DE TRASLADO. POSTULAR SOLO SI CUENTA CON STOCK PARA DESPACHO INMEDIATO. COMPRA SUJETA A MULTA DE NO RESPETAR FECHA ESTIMADA DE ENTREGA. SE DESESTIMARÁ OFERTA QUE INDIQUE VALOR REFERENCIAL $1, O QUE SOBREPASE EL VALOR DEL MONTO ESTIMADO O NO CUMPLA CON LOS DIAS Y DOC. SOLICITADOS. | X9: 51141704 | Y9: 76.394.174-4 | Z9: RISTRIONA RISPERIDONA POLVO PARA SUSPENSIÓN INYECTABLE DE LIBERACIÓN PROLONGADA 37,5 mg CON SOLVENTE REG ISP F-27100/22 FABRICANTE: LABORATORIO PHARMATHEN S.A., GRECIA PERIODO DE EFICACIA, 24 MESES
A10: 1058012-4803-AG25 | B10: 45747 | C10: FARMACIA AMBULATORIA MARZO / FLUTICASONA 50 MCG INH | D10: PEDIDO FARMACIA AMBULATORIA MARZO. ADQUISICIÓN VÍA COMPRA ÁGIL. DESPACHO 48 HRS. SEGÚN COTIZACIÓN. REF 1058012-161-COT25. | E10: 2100030 | F10: 0 | G10: 0 | H10: 399005.7 | I10: 2499035.7 | J10: Fármarcos | K10: FARMACIAS PEDRO ITURRIETA MELENDEZ E.I.R.L. | L10: 76.764.759-K | N10: Pequeña | O10: Región Metropolitana de Santiago | P10: 51181722 | Q10: FLUTICASONA 50 MCG INHALADOR BUCAL (ASMA BRONQUIAL) | R10: 30 | S10: Unidad | T10: 70001 | U10: 2100030 | V10: 1058012-161-COT25 | W10: EL HOSPITAL CLÍNICO DE MAGALLANES REQUIERE FLUTICASONA 50 MCG INHALADOR BUCAL (ASMA BRONQUIAL). INDICAR AL COTIZAR: VALOR UNITARIO TOTAL, PRESENTACIÓN (UD), FECHA VCTO, ADJUNTAR FICHA TÉCNICA Y/O REGISTRO ISP, TIPO DE TRASLADO CARGO PROVEEDOR (ESPECIFICAR, PARA ACORDAR RETIRO CARGO HOSPITAL DE SER NECESARIO), E INDICAR SI CUENTA CON STOCK PARA DESPACHO INMEDIATO. SE DECLARARÁ INADMISIBLE OFERTA QUE INDIQUE VALOR REFERENCIAL $0 o $1, U OMITAN INFORMACIÓN Y DOCUMENTOS SOLICITADOS. | X10: 51181722 | Y10: 76.764.759-K | Z10: BREXOVENT LF INHBUC 50 MCG X 120 DSS vence 4/26 despacho GRATIS 48 horas una vez aceptada al OC se adjunta ficha fono: 992657125
A11: 1058012-67-AG24 | B11: 45627 | C11: COMITÉ FARMACIA/ RILUZOL 5 MG/ML JBE | D11: PEDIDO COMITÉ FARMACIA. COMPRA AGIL. FLETE CARGO DEL PROVEEDOR. COORDINAR CON RODRIGO BARRIA AL 61-2293466 1058012-20-COT24 | E11: 271060 | F11: 0 | G11: 0 | H11: 51501.4 | I11: 322561.4 | J11: Fármarcos | K11: LABORATORIO CELNOVA CHILE SPA | L11: 76.926.592-9 | M11: Farmacéutico | N11: Pequeña | O11: Región Metropolitana de Santiago | P11: 51142801 | Q11: RILUZOL 5 MG/ML JBE | R11: 4 | S11: Frasco | T11: 67765 | U11: 271060 | V11: 1058012-20-COT24 | W11: EL HOSPITAL CLÍNICO DE MAGALLANES REQUIERE RILUZOL 5 MG/ML JBE. INDICAR AL COTIZAR: VALOR UNITARIO TOTAL, PRESENTACIÓN (ML), FECHA VCTO, ADJUNTAR FICHA TÉCNICA Y/O REGISTRO ISP, TIPO DE TRASLADO (ESPECIFICAR, PARA ACORDAR RETIRO CARGO HOSPITAL DE SER NECESARIO), E INDICAR SI CUENTA CON STOCK PARA DESPACHO INMEDIATO. SE DESESTIMARÁ OFERTA QUE INDIQUE VALOR REFERENCIAL $0 o $1, U OMITAN INFORMACIÓN. | X11: 51142801 | Y11: 76.926.592-9 | Z11: TEGLUTIK SUSPENSIÓN ORAL 5 mg/mL (RILUZOL). Presentación: solución oral 5 mg/ml, frasco 300 ml. Vencimiento: 31-07-2025. Tipo de traslado: Aéreo, temperatura ambiente, despacho en 48 horas habiles. Contamos con Stock inmediato.
A12: 1058012-7371-AG25 | B12: 45906 | C12: FALTA CENABAST / GLUCAGON 1MG LIOF SOL INYECT FAM | D12: PEDIDO FALTA CENABAST. COMPRA AGIL. DESPACHO A CARGO DEL PROVEEDOR. 1058012-372-COT25 | E12: 526900 | F12: 0 | G12: 0 | H12: 100111 | I12: 627011 | J12: Fármarcos | K12: LABORATORIO ACONFAR CHILE LIMITADA | L12: 76.125.564-9 | M12: SERVICIOS DE ENVASADO Y EMPAQUE| OTROS PROFESIONALES DE LA SALUD| OTRAS ACTIVIDADES EMPRESARIALES RELACIONADAS CON LA SALUD HUMANA | N12: Pequeña | O12: Región Metropolitana de Santiago | P12: 51181508 | Q12: GLUCAGON 1MG LIOF SOL INYECT FAM | R12: 10 | S12: Frasco Ampolla | T12: 52690 | U12: 526900 | V12: 1058012-372-COT25 | W12: EL HCM REQUIERE GLUCAGON 1MG LIOF SOL INYECT FAM. INDICAR FECHA DE ENTREGA EN BODEGA HCM, FACTOR EMPAQUE, FECHA VCTO, ADJUNTAR FICHA TÉCNICA Y/O REGISTRO ISP, TIPO DE TRASLADO. POSTULAR SOLO SI CUENTA CON STOCK PARA DESPACHO INMEDIATO. COMPRA SUJETA A MULTA DE NO RESPETAR FECHA ESTIMADA DE ENTREGA. SE DESESTIMARÁ OFERTA QUE INDIQUE VALOR REFERENCIAL $1, O QUE SOBREPASE EL VALOR DEL MONTO ESTIMADO O NO CUMPLA CON LOS DIAS Y DOC. SOLICITADOS. | X12: 51181508 | Y12: 76.125.564-9 | Z12: JOR. FACTURACION MINIMA $50.000+IVA PARA SANTIAGO Y $75.000+IVA PARA REGIONES, DESPACHO: STGO 24-48 HR Y REGIONES 72 HR, UNIDAD MIN. COTIZADA, SE AJUSTARÁ A FACTOR DE EMPAQUE, REG.ISP, FACT.ELECTRONICA. STOCK DISPONIBLE PARA ENTREGA INMEDIATA.
A13: 1058012-2929-AG24 | B13: 45577 | C13: FARMACIA AMBULATORIA DICIEMBRE / SOFOSBUVIR-VELPATASVIR 400-100 MG CM | D13: PEDIDO FARMACIA AMBULATORIA DICIEMBRE. ADQUISICIÓN VÍA COMPRA ÁGIL. FLETE 3 DÍAS HÁBILES CARGO DEL PROVEEDOR. REF 1058012-671-COT24. | E13: 1428000 | F13: 0 | G13: 0 | H13: 271320 | I13: 1699320 | J13: Fármarcos | K13: GADOR LIMITADA | L13: 76.084.945-6 | M13: FABRICACION DE PRODUCTOS FARMACEUTICOS, SUSTANCIAS QUIMICAS MEDICINALE| FABRICACION DE OTROS PRODUCTOS QUIMICOS N.C.P.| FABRICACION DE EQUIPO MEDICO Y QUIRURGICO, Y DE APARATOS ORTOPEDICOS| VENTA AL POR MAYOR DE OTROS PRODUCTOS N.C.P. | N13: Grande | O13: Región Metropolitana de Santiago | P13: 85121902 | Q13: SOFOSBUVIR-VELPATASVIR 400-100 MG CM | R13: 28 | S13: Comprimido | T13: 51000 | U13: 1428000 | V13: 1058012-671-COT24 | W13: EL HOSPITAL CLÍNICO DE MAGALLANES REQUIERE SOFOSBUVIR-VELPATASVIR 400-100 MG CM. INDICAR AL COTIZAR: VALOR UNITARIO TOTAL, PRESENTACIÓN (CM), FECHA VCTO, ADJUNTAR FICHA TÉCNICA Y/O REGISTRO ISP, TIPO DE TRASLADO CARGO PROVEEDOR (ESPECIFICAR, PARA ACORDAR RETIRO CARGO HOSPITAL DE SER NECESARIO), E INDICAR SI CUENTA CON STOCK PARA DESPACHO INMEDIATO. SE DESESTIMARÁ OFERTA QUE INDIQUE VALOR REFERENCIAL $0 o $1, U OMITAN INFORMACIÓN Y DOCUMENTOS SOLICITADOS. | X13: 85121902 | Y13: 76.084.945-6 | Z13: EPCLUSA 400/100 COMPRIMIDOS RECUBIERTOS SOFOSBUVIR 400 mg - VELPATASVIR 100mg, REFERENTE Estuche contiene 28 comprimidos recubiertos, Reg. ISP.- F-23583-22, Vcto: 30-04-2027, Plazo Entrega: 3 días hábiles, PRECIO ESTUCHE:$1.428.000
A14: 1058012-3013-AG24 | B14: 45645 | C14: FARMACIA AMBULATORIA URGENTE DICIEMBRE / SOFOSBUVIR-VELPATASVIR 400-100 MG CM | D14: PEDIDO FARMACIA AMBULATORIA URGENTE DICIEMBRE . COMPRA AGIL DESPACHO AÉREO CARGO DEL PROVEEDOR. 1058012-684-COT24 | E14: 2856000 | F14: 0 | G14: 0 | H14: 542640 | I14: 3398640 | J14: Fármarcos | K14: GADOR LIMITADA | L14: 76.084.945-6 | M14: FABRICACION DE PRODUCTOS FARMACEUTICOS, SUSTANCIAS QUIMICAS MEDICINALE| FABRICACION DE OTROS PRODUCTOS QUIMICOS N.C.P.| FABRICACION DE EQUIPO MEDICO Y QUIRURGICO, Y DE APARATOS ORTOPEDICOS| VENTA AL POR MAYOR DE OTROS PRODUCTOS N.C.P. | N14: Grande | O14: Región Metropolitana de Santiago | P14: 85121902 | Q14: SOFOSBUVIR-VELPATASVIR 400-100 MG CM | R14: 56 | S14: Comprimido | T14: 51000 | U14: 2856000 | V14: 1058012-684-COT24 | W14: EL HOSPITAL CLÍNICO DE MAGALLANES REQUIERE SOFOSBUVIR-VELPATASVIR 400-100 MG CM. INDICAR AL COTIZAR: VALOR UNITARIO TOTAL, PRESENTACIÓN (CM), FECHA VCTO, ADJUNTAR FICHA TÉCNICA Y/O REGISTRO ISP, TIPO DE TRASLADO CARGO PROVEEDOR (ESPECIFICAR, PARA ACORDAR RETIRO CARGO HOSPITAL DE SER NECESARIO), E INDICAR SI CUENTA CON STOCK PARA DESPACHO INMEDIATO. SE DESESTIMARÁ OFERTA QUE INDIQUE VALOR REFERENCIAL $0 o $1, U OMITAN INFORMACIÓN Y DOCUMENTOS SOLICITADOS. | X14: 85121902 | Y14: 76.084.945-6 | Z14: EPCLUSA 400/100 COMPRIMIDOS RECUBIERTOS SOFOSBUVIR 400 mg - VELPATASVIR 100mg, REFERENTE Estuche contiene 28 comprimidos recubiertos, Reg. ISP.- F-23583/22, Vcto: 30-04-2027, Plazo Ent: 3 dias hábiles, Valor ofertado x Unidad. STOCK DESPACHO INMEDIATO
A15: 1058012-7820-AG25 | B15: 45862 | C15: FARMACIA DU JULIO / METILPREDNISOLONA ACETATO 80 MG | D15: FARMACIA DU JULIO ADQUISICION A TRAVES DE COMPRA AGIL DESPACHO 24 A 48 HORAS CARGO DEL PROVEEDOR 100001027 REF: 1058012-459-COT25 | E15: 1303820 | F15: 0 | G15: 0 | H15: 247725.8 | I15: 1551545.8 | J15: Fármarcos | K15: PFIZER CHILE S.A. | L15: 96.981.250-9 | M15: FABRICACION DE PRODUCTOS DE CONFITERIA| FABRICACION DE PRODUCTOS FARMACEUTICOS, SUSTANCIAS QUIMICAS MEDICINALE| FABRICACIONES DE JABONES Y DETERGENTES, PREPARADOS PARA LIMPIAR, PERFU | N15: Grande | O15: Región Metropolitana de Santiago | P15: 51181707 | Q15: METILPREDNISOLONA ACETATO 80 MG. | R15: 35 | S15: Ampolla | T15: 37252 | U15: 1303820 | V15: 1058012-459-COT25 | W15: EL HCM REQUIERE METILPREDNISOLONA ACETATO 80 MG. INDICAR FECHA DE ENTREGA EN BODEGA HCM, FACTOR EMPAQUE, FECHA VCTO, ADJUNTAR FICHA TÉCNICA Y/O REGISTRO ISP, TIPO DE TRASLADO. POSTULAR SOLO SI CUENTA CON STOCK PARA DESPACHO INMEDIATO. COMPRA SUJETA A MULTA DE NO RESPETAR FECHA ESTIMADA DE ENTREGA. SE DESESTIMARÁ OFERTA QUE INDIQUE VALOR REFERENCIAL $1, O QUE SOBREPASE EL VALOR DEL MONTO ESTIMADO O NO CUMPLA CON LOS DIAS Y DOC. SOLICITADOS. | X15: 51181707 | Y15: 96.981.250-9 | Z15: DEPOMEDROL 80MG - ML - METILPREDNISOLONA. de PFIZER. Precio corresponde a 1 frasco ampolla. Envase de venta caja x 1 Frasco Ampolla. REGISTRO ISP N° F-1276-23 Vencimiento 31-05-2026. Con carta de canje.
A16: 1058012-845-AG24 | B16: 45539 | C16: PEDIDO FARMACIA DOSIS UNITARIA/ METILPREDNISOLONA ACETATO 80 MG | D16: PEDIDO F. DOSIS UNITARIA. COMPRA AGIL DESPACHO AÉREO CARGO DEL PROVEEDOR. 1058012-262-COT24 100001027 | E16: 1419120 | F16: 0 | G16: 0 | H16: 269632.8 | I16: 1688752.8 | J16: Fármarcos | K16: PFIZER CHILE S.A. | L16: 96.981.250-9 | M16: FABRICACION DE PRODUCTOS DE CONFITERIA| FABRICACION DE PRODUCTOS FARMACEUTICOS, SUSTANCIAS QUIMICAS MEDICINALE| FABRICACIONES DE JABONES Y DETERGENTES, PREPARADOS PARA LIMPIAR, PERFU | N16: Grande | O16: Región Metropolitana de Santiago | P16: 51181707 | Q16: METILPREDNISOLONA ACETATO 80 MG | R16: 40 | S16: Unidad | T16: 35478 | U16: 1419120 | V16: 1058012-262-COT24 | W16: EL HOSPITAL CLÍNICO DE MAGALLANES REQUIERE METILPREDNISOLONA ACETATO 80 MG. INDICAR AL COTIZAR: VALOR UNITARIO TOTAL, PRESENTACIÓN (ML), FECHA VCTO, ADJUNTAR FICHA TÉCNICA Y/O REGISTRO ISP, TIPO DE TRASLADO (ESPECIFICAR, PARA ACORDAR RETIRO CARGO HOSPITAL DE SER NECESARIO), E INDICAR SI CUENTA CON STOCK PARA DESPACHO INMEDIATO. SE DESESTIMARÁ OFERTA QUE INDIQUE VALOR REFERENCIAL $0 o $1, U OMITAN INFORMACIÓN. | X16: 51181707 | Y16: 96.981.250-9 | Z16: DEPOMEDROL 80MG - ML - METILPREDNISOLONA. de PFIZER. Precio corresponde a 1 frasco ampolla. Envase de venta caja x 1 F A. REG ISP N° F-1276-23. Vencimiento 31-07-2025. Flete incluido en el precio.
A17: 1058012-7670-AG25 | B17: 45845 | C17: FARMACIA AMBULATORIA JULIO / PANCREOLIPASA 5.000 UI GRANULOS | D17: PEDIDO FARMACIA AMBULATORIA JULIO. ADQUISICIÓN VÍA COMPRA ÁGIL. DESPACHO 3 DÍAS CARGO DEL PROVEEDOR SEGÚN COTIZACIÓN. REF 1058012-447-COT25. | E17: 1044150 | F17: 0 | G17: 0 | H17: 198388.5 | I17: 1242538.5 | J17: Fármarcos | K17: LABORATORIOS RECALCINE SA | L17: 91.637.000-8 | M17: FABRICACION DE PRODUCTOS FARMACEUTICOS, SUSTANCIAS QUIMICAS MEDICINALE| VENTA AL POR MAYOR DE OTROS PRODUCTOS N.C.P.| OTRAS ACTIVIDADES EMPRESARIALES N.C.P. | N17: Grande | O17: Región Metropolitana de Santiago | P17: 51171910 | Q17: PANCREOLIPASA 5.000 UI GRANULOS FRASCO 20 GR. | R17: 30 | S17: Frasco | T17: 34805 | U17: 1044150 | V17: 1058012-447-COT25 | W17: EL HOSPITAL CLÍNICO DE MAGALLANES REQUIERE PANCREOLIPASA 5.000 UI GRANULOS FRASCO 20 GR. INDICAR AL COTIZAR: VALOR UNITARIO TOTAL, PRESENTACIÓN (FCO), FECHA VCTO, ADJUNTAR FICHA TÉCNICA Y/O REGISTRO ISP, TIPO DE TRASLADO Y FECHA ESPECIFICA DE ENTREGA (ESPECIFICAR, PARA ACORDAR RETIRO CARGO HOSPITAL DE SER NECESARIO), E INDICAR SI CUENTA CON STOCK PARA DESPACHO INMEDIATO. SE DECLARARÁ INADMISIBLE OFERTA QUE INDIQUE VALOR REFERENCIAL $0 o $1, U OMITAN INFORMACIÓN Y DOCUMENTOS SOLICITADOS. | X17: 51171910 | Y17: 91.637.000-8 | Z17: 882352 CREON 5.000 FRASCO 20 MG PA PANCREATINA REG ISP B-2707/23 VENCE 30-04-2027 STOCK DESPACHO INMEDIATO COTIZACIÓN LABORATORIOS RECALCINE FLETE INCLUIDO DESPACHO EN 2 DÍAS/48 HORAS MÍN DE FACTURACIÓN 100.000 SE COTIZAN VALORES NETOS
A18: 1058012-1806-AG24 | B18: 45499 | C18: (FAR) COMPRA ALTERNATIVA STOCK CRÍTICO FARMACIA AMBULATORIA JUNIO / FLUTICASONA PROPIONATO MICRONIZADO 50 MCG INH ORAL | D18: COMPRA ALTERNATIVA POR FALTA DE STOCK EN PROVEEDOR OC N° 1058012-1651-AG24. FLETE 3 DÍAS SEGÚN COTIZACIÓN. REF 1058012-506-COT24. | E18: 1339650 | F18: 0 | G18: 0 | H18: 254533.5 | I18: 1594183.5 | J18: Fármarcos | K18: DROGUERÍA ACONCAGUA SPA | L18: 76.985.933-0 | M18: VENTA AL POR MAYOR DE PRODUCTOS FARMACEUTICOS Y MEDICINALES | N18: Micro | O18: Región Metropolitana de Santiago | P18: 51181722 | Q18: FLUTICASONA PROPIONATO MICRONIZADO 50 MCG AEROSOL PARA INHALACION ORAL (SIN ALCOHOL) | R18: 39 | S18: Unidad | T18: 34350 | U18: 1339650 | V18: 1058012-506-COT24 | W18: EL HOSPITAL CLÍNICO DE MAGALLANES REQUIERE FLUTICASONA PROPIONATO MICRONIZADO 50 MCG INH ORAL. INDICAR AL COTIZAR: VALOR UNITARIO TOTAL, PRESENTACIÓN (ML), FECHA VCTO, ADJUNTAR FICHA TÉCNICA Y/O REGISTRO ISP, TIPO DE TRASLADO CARGO PROVEEDOR (ESPECIFICAR, PARA ACORDAR RETIRO CARGO HOSPITAL DE SER NECESARIO), E INDICAR SI CUENTA CON STOCK PARA DESPACHO INMEDIATO. SE DESESTIMARÁ OFERTA QUE INDIQUE VALOR REFERENCIAL $0 o $1, U OMITAN INFORMACIÓN Y DOCUMENTOS SOLICITADOS. | X18: 51181722 | Y18: 76.985.933-0 | Z18: SE ADJUNTA COTIZACIÓN FORMAL Y FICHA DE PRODUCTO CON VENCE MAYOR A 12 MESES. PLAZO DE ENTREGA 2 A 3 DÍAS LUEGO DE EMITIDA LA ÓRDEN DE COMPRA. MÍNIMO DE DESPACHO 180.000 PESOS. REPRESENTANTE DE VENTA MARCEL ACUÑA. 9 75770902 VENTAS2@DROGUERIAACONCAGUA.CL
A19: 1058012-1651-AG24 | B19: 45298 | C19: STOCK CRÍTICO FARMACIA AMBULATORIA JUNIO / FLUTICASONA PROPIONATO MICRONIZADO 50 MCG INH ORAL | D19: PEDIDO STOCK CRÍTICO FARMACIA AMBULATORIA JUNIO. ADQUISICIÓN VÍA COMPRA ÁGIL. FLETE 48 HRS. SEGÚN COTIZACIÓN. REF 1058012-457-COT24 | E19: 1363520 | F19: 0 | G19: 0 | H19: 259068.8 | I19: 1622588.8 | J19: Fármarcos | K19: ADN FARMACEUTICA SPA | L19: 76.786.297-0 | M19: DROGUERIA | N19: Micro | O19: Región Metropolitana de Santiago | P19: 51181722 | Q19: FLUTICASONA PROPIONATO MICRONIZADO 50 MCG AEROSOL PARA INHALACION ORAL (SIN ALCOHOL) | R19: 40 | S19: Unidad | T19: 34088 | U19: 1363520 | V19: 1058012-457-COT24 | W19: EL HOSPITAL CLÍNICO DE MAGALLANES REQUIERE FLUTICASONA PROPIONATO MICRONIZADO 50 MCG AEROSOL PARA INHALACION ORAL (SIN ALCOHOL). INDICAR AL COTIZAR: VALOR UNITARIO TOTAL, PRESENTACIÓN (UD), FECHA VCTO, ADJUNTAR FICHA TÉCNICA Y/O REGISTRO ISP, TIPO DE TRASLADO CARGO PROVEEDOR (ESPECIFICAR, PARA ACORDAR RETIRO CARGO HOSPITAL DE SER NECESARIO), E INDICAR SI CUENTA CON STOCK PARA DESPACHO INMEDIATO. SE DESESTIMARÁ OFERTA QUE INDIQUE VALOR REFERENCIAL $0 o $1, U OMITAN INFORMACIÓN. | X19: 51181722 | Y19: 76.786.297-0 | Z19: FLIXOTIDE LF INH 50 MCG X 120 DS*ENTREGA DE 24 A 48 HORAS, VENCE SUPERIOR A 12 MESES, DESPACHO INCLUIDO EN EL PRECIO, SIN MINIMO DE COMPRA, OFERENTE Ximena Silva/9-57438894/xsilva@adnfarmaceutica.cl
A20: 1058012-7391-AG25 | B20: 45936 | C20: FALTA CENABAST JUNIO/METILPREDNISOLONA 1 G LIOF IV-IM FAM | D20: PEDIDO FALTA CENABAST JUNIO. COMPRA ÁGIL. DESPACHO A CARGO DEL PROVEEDOR. 1058012-374-COT25 | E20: 646627 | F20: 0 | G20: 0 | H20: 122859.13 | I20: 769486.13 | J20: Fármarcos | K20: PFIZER CHILE S.A. | L20: 96.981.250-9 | M20: FABRICACION DE PRODUCTOS DE CONFITERIA| FABRICACION DE PRODUCTOS FARMACEUTICOS, SUSTANCIAS QUIMICAS MEDICINALE| FABRICACIONES DE JABONES Y DETERGENTES, PREPARADOS PARA LIMPIAR, PERFU | N20: Grande | O20: Región Metropolitana de Santiago | P20: 51181707 | Q20: METILPREDNISOLONA 1G LIOF IV-IM FAN | R20: 19 | S20: Frasco Ampolla | T20: 34033 | U20: 646627 | V20: 1058012-374-COT25 | W20: EL HCM REQUIERE METILPREDNISOLONA 1G LIOF IV-IM FAN. INDICAR FECHA DE ENTREGA EN BODEGA HCM, FACTOR EMPAQUE, FECHA VCTO, ADJUNTAR FICHA TÉCNICA Y/O REGISTRO ISP, TIPO DE TRASLADO. POSTULAR SOLO SI CUENTA CON STOCK PARA DESPACHO INMEDIATO. COMPRA SUJETA A MULTA DE NO RESPETAR FECHA ESTIMADA DE ENTREGA. SE DESESTIMARÁ OFERTA QUE INDIQUE VALOR REFERENCIAL $1, O QUE SOBREPASE EL VALOR DEL MONTO ESTIMADO O NO CUMPLA CON LOS DIAS Y DOC. SOLICITADOS. | X20: 51181707 | Y20: 96.981.250-9 | Z20: SOLU MEDROL 1 GR ACT-O-VIAL METILPREDNISOLONA HEMISUCCINATO DE PFIZER. Precio corresponde a 1 frasco ampolla. Envase de venta caja x 1 frasco Ampolla. REGISTRO ISP N° F-2816-24. Vencimiento: 30-09-2026. MONTO MINIMO PARA DESPACHO 100.000
A21: 1058012-7390-AG25 | B21: 45936 | C21: FALTA CENABAST/DESMOPRESINA 100 MCG/1ML FRA 5 A 6 ML | D21: PEDIDO FALTA CENABAST. COMPRA ÁGIL. DESPACHO A CARGO DEL PROVEEDOR. 1058012-370-COT25 | E21: 168750 | F21: 0 | G21: 0 | H21: 32062.5 | I21: 200812.5 | J21: Fármarcos | K21: BPH S.A. | L21: 96.519.830-k | M21: VENTA AL POR MAYOR DE PRODUCTOS QUIMICOS | N21: Grande | O21: Región Metropolitana de Santiago | P21: 51182101 | Q21: DESMOPRESINA 100 MCG/1ML FRA 5 A 6 ML | R21: 5 | S21: Frasco | T21: 33750 | U21: 168750 | V21: 1058012-370-COT25 | W21: EL HCM REQUIERE DESMOPRESINA 100 MCG/1ML FRA 5 A 6 ML. INDICAR FECHA DE ENTREGA EN BODEGA HCM, FACTOR EMPAQUE, FECHA VCTO, ADJUNTAR FICHA TÉCNICA Y/O REGISTRO ISP, TIPO DE TRASLADO. POSTULAR SOLO SI CUENTA CON STOCK PARA DESPACHO INMEDIATO. COMPRA SUJETA A MULTA DE NO RESPETAR FECHA ESTIMADA DE ENTREGA. SE DESESTIMARÁ OFERTA QUE INDIQUE VALOR REFERENCIAL $1, O QUE SOBREPASE EL VALOR DEL MONTO ESTIMADO O NO CUMPLA CON LOS DIAS Y DOC. SOLICITADOS. | X21: 51182101 | Y21: 96.519.830-k | Z21: DESMOPRESINA ACET. SLN NASAL 10 MCG/D FC 5 ML EAN:7800086789003 VC:31-12-2026 REG:F-26040 EX1.SE COTIZA PRECIO NETO POR FC PARA DESPACHO 2 DIAS, MONTO MINIMO A FACTURAR Y DESPACHAR $120.000 NETO. PIA MARTINICH VENTAS6@BPH.CL
A22: 1058012-1512-AG24 | B22: 45461 | C22: COMITÉ FARMACIA MAYO / AMBRISENTÁN 10 MG CM | D22: PEDIDO COMITÉ FARMACIA MAYO. ADQUISICIÓN VÍA COMPRA ÁGIL. FLETE 3 DÍA HÁBILES SEGÚN COTIZACIÓN. REF 1058012-370-COT24. COMITÉ FARMACIA N°4 DEL 29-04-2024. | E22: 994440 | F22: 0 | G22: 0 | H22: 188943.6 | I22: 1183383.6 | J22: Fármarcos | K22: GLAXOSMITHKLINE CHILE FARMACEUTICA LIMITADA | L22: 85.025.700-0 | M22: FABRICACION DE PRODUCTOS FARMACEUTICOS, SUSTANCIAS QUIMICAS MEDICINALE | N22: Grande | O22: Región Metropolitana de Santiago | P22: 85121902 | Q22: AMBRISENTAM 10 MG CM | R22: 30 | S22: Comprimido | T22: 33148 | U22: 994440 | V22: 1058012-370-COT24 | W22: EL HOSPITAL CLÍNICO DE MAGALLANES REQUIERE AMBRISENTAM 10 MG CM. INDICAR AL COTIZAR: VALOR UNITARIO TOTAL, PRESENTACIÓN (CM), FECHA VCTO, ADJUNTAR FICHA TÉCNICA Y/O REGISTRO ISP, TIPO DE TRASLADO CARGO PROVEEDOR. (ESPECIFICAR, PARA ACORDAR RETIRO CARGO HOSPITAL DE SER NECESARIO), E INDICAR SI CUENTA CON STOCK PARA DESPACHO INMEDIATO. SE DESESTIMARÁ OFERTA QUE INDIQUE VALOR REFERENCIAL $0 o $1, U OMITAN INFORMACIÓN Y NO ADJUNTEN DOCUMENTOS. | X22: 85121902 | Y22: 85.025.700-0 | Z22: 60000000109532 VOLIBRIS 10mg x 30 Comprimidos recubiertos (I) AMBRISENTÁN VENCIMIENTO:Mayor a 12 Meses - ISP: F-22308/20. Despacho 3 días hábiles. Monto mínimo $250.000 Netos.
... A26: 1058012-3977-AG23 | B26: 45323 | C26: FARMACIA PROG. VIH / LECHE SUSTITUTA DE LECHE MATERNA | D26: PEDIDO FARMACIA [PROGR. VIH]. ADQUISIÓN VÍA COMPRA ÁGIL. FLETE CARGO DEL PROVEEDOR. REF 1058012-766-COT23 | E26: 1238400 | F26: 0 | G26: 0 | H26: 235296 | I26: 1473696 | J26: Fármarcos | K26: ACQUA INVERSIONES SPA | L26: 77.423.498-5 | M26: VENTA AL POR MAYOR NO ESPECIALIZADA | N26: N/A | O26: Región Metropolitana de Santiago | P26: 51191603 | Q26: LECHE SUSTITUTA DELECHE MATERNA NAN 1 800 GR. | R26: 48 | S26: Tarro | T26: 25800 | U26: 1238400 | V26: 1058012-766-COT23 | W26: EL HOSPITAL CLÍNICO DE MAGALLANES REQUIERE LECHE SUSTITUTA DELECHE MATERNA NAN 1 900 GR.. INDICAR AL COTIZAR: VALOR UNITARIO TOTAL, PRESENTACIÓN (GR), FECHA VCTO, ADJUNTAR FICHA TÉCNICA Y/O REGISTRO ISP, TIPO DE TRASLADO (ESPECIFICAR, PARA ACORDAR RETIRO CARGO HOSPITAL DE SER NECESARIO), E INDICAR SI CUENTA CON STOCK PARA DESPACHO INMEDIATO. SE DESESTIMARÁ OFERTA QUE INDIQUE VALOR REFERENCIAL $0 o $1, U OMITAN INFORMACIÓN. | X26: 51191603 | Y26: 77.423.498-5 | Z26: COSTO FLETE INCLUIDO, DESPACHO DE 24 A 48 HORAS, UNA VEZ ACEPTADA LA ORDEN DE COMPRA, SIN MÍNIMO DE FACTURACIÓN, VENCE SUPERIOR A 12 MESES (DSR) dsanchezr@acquainversiones.cl contacto +569 3582 9651
A27: 1058012-7412-AG25 | B27: 45967 | C27: COMITÉ FARMACIA JUNIO / DEUCRAVACITINIB 6 MG CM | D27: PEDIDO COMITÉ FARMACIA JUNIO. ADQUISICIÓN VÍA COMPRA ÁGIL. DESPACHO 3 DÍAS CARGO DEL PROVEEDOR SEGÚN COTIZACIÓN. REF 1058012-398-COT25. | E27: 5626560 | F27: 0 | G27: 0 | H27: 1069046.4 | I27: 6695606.4 | J27: Fármarcos | K27: FARMACIAS PEDRO ITURRIETA MELENDEZ E.I.R.L. | L27: 76.764.759-K | N27: Pequeña | O27: Región Metropolitana de Santiago | P27: 85121902 | Q27: DEUCRAVACITINIB 6 MG CM | R27: 240 | S27: Comprimido | T27: 23444 | U27: 5626560 | V27: 1058012-398-COT25 | W27: EL HOSPITAL CLÍNICO DE MAGALLANES REQUIERE DEUCRAVACITINIB 6 MG CM. INDICAR AL COTIZAR: VALOR UNITARIO TOTAL, PRESENTACIÓN (CM), FECHA VCTO, ADJUNTAR FICHA TÉCNICA Y/O REGISTRO ISP, TIPO DE TRASLADO Y FECHA ESPECIFICA DE ENTREGA (ESPECIFICAR, PARA ACORDAR RETIRO CARGO HOSPITAL DE SER NECESARIO), E INDICAR SI CUENTA CON STOCK PARA DESPACHO INMEDIATO. SE DECLARARÁ INADMISIBLE OFERTA QUE INDIQUE VALOR REFERENCIAL $0 o $1, U OMITAN INFORMACIÓN Y DOCUMENTOS SOLICITADOS. | X27: 85121902 | Y27: 76.764.759-K | Z27: SOTYKTU 6 MG X 30 COMP. vence 10/26 despacho GRATIS 48 horas una vez aceptada al OC se adjunta ficha fono: 992657125
A28: 1058012-6888-AG25 | B28: 45777 | C28: FALTA CENABAST MARZO / CICLOFOSFAMIDA 1G FA POLVO LIOFILIZADO | D28: PEDIDO FALTA CENABAST MARZO SIN RECEPCION. COMPRA AGIL DESPACHO 2 DIAS CARGO DEL PROVEEDOR. (DE ACUERDO A LO OFERTADO) 1058012-235-COT25 | E28: 637140 | F28: 0 | G28: 0 | H28: 121056.6 | I28: 758196.6 | J28: Fármarcos | K28: ADN FARMACEUTICA SPA | L28: 76.786.297-0 | M28: DROGUERIA | N28: Mediana | O28: Región Metropolitana de Santiago | P28: 51111507 | Q28: CICLOFOSFAMIDA 1G FA POLVO LIOFILIZADO | R28: 30 | S28: Frasco Ampolla | T28: 21238 | U28: 637140 | V28: 1058012-235-COT25 | W28: EL HCM REQUIERE CICLOFOSFAMIDA 1G FA POLVO LIOFILIZADO. INDICAR FECHA DE ENTREGA EN BODEGA HCM, FACTOR EMPAQUE, FECHA VCTO, ADJUNTAR FICHA TÉCNICA Y/O REGISTRO ISP, TIPO DE TRASLADO. POSTULAR SOLO SI CUENTA CON STOCK PARA DESPACHO INMEDIATO. COMPRA SUJETA A MULTA DE NO RESPETAR FECHA ESTIMADA DE ENTREGA. SE DESESTIMARÁ OFERTA QUE INDIQUE VALOR REFERENCIAL $0 o $1. SE DEJARA INADMISIBLE LA OFERTA QUE SOBREPASE EL VALOR DEL MONTO ESTIMADO O NO CUMPLA CON LOS DIAS Y DOC. SOLICITADOS. | X28: 51111507 | Y28: 76.786.297-0 | Z28: ENDOXAN AMP. 1GR. CX1 CICLOFOSFAMIDA ENTREGA DE 24 A 48 HRS, VENCE MAS DE 12 MESES, DESPACHO C/FACTURA INCLUIDO EN EL PRECIO, SIN MINIMO DE COMPRA,CON POLITICA DE CANJE, OFERENTE Ximena Silva/9-57438894/xsilva@adnfarmaceutica.cl
A29: 1058012-7861-AG25 | B29: 45755 | C29: FARMACIA AMBULATORIA JULIO-DICIEMBRE / LEVETIRACETAM 100 MG ML | D29: PEDIDO FARMACIA AMBULATORIA JULIO-DICIEMBRE. ADQUISICIÓN VÍA COMPRA ÁGIL. DESPACHO 72 HORAS HÁBILES CARGO DEL PROVEEDOR SEGÚN COTIZACIÓN. REF 1058012-494-COT25. | E29: 540000 | F29: 0 | G29: 0 | H29: 102600 | I29: 642600 | J29: Fármarcos | K29: GLAXOSMITHKLINE CHILE FARMACEUTICA LIMITADA | L29: 85.025.700-0 | M29: FABRICACION DE PRODUCTOS FARMACEUTICOS, SUSTANCIAS QUIMICAS MEDICINALE | N29: Grande | O29: Región Metropolitana de Santiago | P29: 51141518 | Q29: LEVETIRACETAM 100 MG ML TIPO KEPPRA | R29: 30 | S29: Frasco | T29: 18000 | U29: 540000 | V29: 1058012-494-COT25 | W29: EL HOSPITAL CLÍNICO DE MAGALLANES REQUIERE LEVETIRACETAM 100 MG ML TIPO KEPPRA. INDICAR AL COTIZAR: VALOR UNITARIO TOTAL, PRESENTACIÓN (FC), FECHA VCTO, ADJUNTAR FICHA TÉCNICA Y/O REGISTRO ISP, TIPO DE TRASLADO (ESPECIFICAR, PARA ACORDAR RETIRO CARGO HOSPITAL DE SER NECESARIO), E INDICAR SI CUENTA CON STOCK PARA DESPACHO INMEDIATO. SE DECLARARÁ INADMISIBLE OFERTA QUE INDIQUE VALOR REFERENCIAL $0 o $1, U OMITAN INFORMACIÓN Y/O DOCUMENTOS SOLICITADOS. | X29: 51141518 | Y29: 85.025.700-0 | Z29: Validez de la oferta 90 días. Facturación mínima $500.000.- neto. Vencimiento superior a doce meses, ENTREGA: 72 Horas hábiles una vez aceptada la orden de compra. Condiciones Comerciales punto 10, Flete incluido. contacto gsk.ordenesdecompra@gsk.com
A30: 1058012-8222-AG25 | B30: 45697 | C30: FARMACIA AMBULATORIA AGOSTO / CARBAMAZEPINA 100 MG 5 ML SO JBE | D30: PEDIDO FARMACIA AMBULATORIA AGOSTO. REF 1058012-533-COT25. DESPACHO 72 HORAS CARGO DEL PROVEEDOR SEGÚN COTIZACIÓN. ZGEN 100005816. | E30: 338000 | F30: 0 | G30: 0 | H30: 64220 | I30: 402220 | J30: Fármarcos | K30: LABORATORIO ACONFAR CHILE LIMITADA | L30: 76.125.564-9 | M30: SERVICIOS DE ENVASADO Y EMPAQUE| OTROS PROFESIONALES DE LA SALUD| OTRAS ACTIVIDADES EMPRESARIALES RELACIONADAS CON LA SALUD HUMANA | N30: Pequeña | O30: Región Metropolitana de Santiago | P30: 85121902 | Q30: CARBAMAZEPINA 100 MG 5 ML SO JBE | R30: 20 | S30: Frasco | T30: 16900 | U30: 338000 | V30: 1058012-533-COT25 | W30: EL HOSPITAL CLÍNICO DE MAGALLANES REQUIERE CARBAMAZEPINA 100 MG 5 ML SO JBE (TIPO TEGRETAL). INDICAR AL COTIZAR: VALOR UNITARIO TOTAL, PRESENTACIÓN (FCO), FECHA VCTO, ADJUNTAR FICHA TÉCNICA Y/O REGISTRO ISP, TIPO DE TRASLADO Y FECHA ESPECIFICA DE ENTREGA (ESPECIFICAR, PARA ACORDAR RETIRO CARGO HOSPITAL DE SER NECESARIO), E INDICAR SI CUENTA CON STOCK PARA DESPACHO INMEDIATO. SE DECLARARÁ INADMISIBLE OFERTA QUE INDIQUE VALOR REFERENCIAL $0 o $1, U OMITAN INFORMACIÓN Y DOCUMENTOS SOLICITADOS. | X30: 85121902 | Y30: 76.125.564-9 | Z30: JT FACTURAC. MÍN. $ 50.000+IVA STGO $ 75.000+IVA REGIONES. SI MONTO SUPERA 100 UTM, SE SUBIRÁN A $ 1 PARA OFERTAR.PLAZO ENTREGA STGO.24-48 hrs. REGIONES 48-72 hrs. (según cobertura O.L) FAVOR RESPETAR FACTOR EMPAQUE (para comp. inyectables y sueros).
A31: 1058012-6779-AG25 | B31: 45763 | C31: FARMACIA AMBULATORIA ABRIL / BIFIDOBACTERIUM BB-12 PROBIOTICOS EN GOTAS | D31: PEDIDO FARMACIA AMBULATORIA ABRIL. ADQUISICIÓN VÍA COMPRA ÁGIL. DESPACHO 72 HRS CARGO DEL PROVEEDOR SEGÚN COTIZACIÓN. REF 1058012-220-COT25. | E31: 1000620 | F31: 0 | G31: 0 | H31: 190117.8 | I31: 1190737.8 | J31: Fármarcos | K31: LABORATORIO ACONFAR CHILE LIMITADA | L31: 76.125.564-9 | M31: SERVICIOS DE ENVASADO Y EMPAQUE| OTROS PROFESIONALES DE LA SALUD| OTRAS ACTIVIDADES EMPRESARIALES RELACIONADAS CON LA SALUD HUMANA | N31: Pequeña | O31: Región Metropolitana de Santiago | P31: 51191905 | Q31: BIFIDOBACTERIUM BB-12 PROBIOTICOS EN GOTAS | R31: 60 | S31: Frasco | T31: 16677 | U31: 1000620 | V31: 1058012-220-COT25 | W31: EL HOSPITAL CLÍNICO DE MAGALLANES REQUIERE BIFIDOBACTERIUM BB-12 PROBIOTICOS EN GOTAS. INDICAR AL COTIZAR: VALOR UNITARIO TOTAL, PRESENTACIÓN (ML), FECHA VCTO, ADJUNTAR FICHA TÉCNICA Y/O REGISTRO ISP, TIPO DE TRASLADO (ESPECIFICAR, PARA ACORDAR RETIRO CARGO HOSPITAL DE SER NECESARIO), E INDICAR SI CUENTA CON STOCK PARA DESPACHO INMEDIATO. SE DECLARARÁ INADMISIBLE OFERTA QUE INDIQUE VALOR REFERENCIAL $0 o $1, U OMITAN CUALQUIER INFORMACIÓN SOLICITADA PARA ESTA COTIZACIÓN. | X31: 51191905 | Y31: 76.125.564-9 | Z31: JOR. FACTURACION MINIMA $50.000+IVA PARA SANTIAGO Y $75.000+IVA PARA REGIONES, DESPACHO: STGO 24-48 HR Y REGIONES 72 HR, UNIDAD MIN. COTIZADA, SE AJUSTARÁ A FACTOR DE EMPAQUE, REG.ISP, FACT.ELECTRONICA. STOCK DISPONIBLE PARA ENTREGA INMEDIATA.
A32: 1058012-7012-AG25 | B32: 45996 | C32: DERMATOLOGÍA COMITÉ FARMACIA MAYO / IMIQUIMOD 5% CREMA | D32: PEDIDO DERMATOLOGÍA COMITÉ FARMACIA MAYO. ADQUISICIÓN VÍA COMPRA ÁGIL. DESPACHO 7 DÍAS CARGO DEL PROVEEDOR SEGÚN COTIZACIÓN. REF 1058012-296-COT25. | E32: 325440 | F32: 0 | G32: 0 | H32: 61833.6 | I32: 387273.6 | J32: Fármarcos | K32: SCM PHARMA SPA | L32: 77.337.544-5 | M32: VENTA AL POR MAYOR DE PRODUCTOS FARMACEUTICOS Y MEDICINALES | N32: Mediana | O32: Región Metropolitana de Santiago | P32: 51201510 | Q32: IMIQUIMOD 5% CREMA | R32: 20 | S32: Unidad | T32: 16272 | U32: 325440 | V32: 1058012-296-COT25 | W32: EL HOSPITAL CLÍNICO DE MAGALLANES REQUIERE IMIQUIMOD 5% CREMA. INDICAR AL COTIZAR: VALOR UNITARIO TOTAL, PRESENTACIÓN (UD), FECHA VCTO, ADJUNTAR FICHA TÉCNICA Y/O REGISTRO ISP, TIPO DE TRASLADO (ESPECIFICAR, PARA ACORDAR RETIRO CARGO HOSPITAL DE SER NECESARIO), E INDICAR SI CUENTA CON STOCK PARA DESPACHO INMEDIATO. SE DECLARARÁ INADMISIBLE OFERTA QUE INDIQUE VALOR REFERENCIAL $0 o $1, U OMITAN INFORMACIÓN SOLICITADA. | X32: 51201510 | Y32: 77.337.544-5 | Z32: Se adjunta cotización detallada, Contacto F. 225104550, contacto@scmpharma.cl, Despacho sin costo, Envio 7 dias- monto mínimo de despacho $ 100.000.- Cotización valida por 15 días.
A33: 1058012-4493-AG25 | B33: 45750 | C33: COMPRA ALTERNATIVA FALTA CENABAST FEBRERO / AZITROMICINA 500 MG IV | D33: COMPRA ALTERNATIVA POR FALTA DE STOCK EN OC N° 1058012-4414-SE25. ADQUISICIÓN VÍA COMPRA ÁGIL. DESPACHO 3 DÍAS SEGÚN COTIZACIÓN. ZGEN 100004661. REF 1058012-119-COT25. | E33: 796250 | F33: 0 | G33: 0 | H33: 151287.5 | I33: 947537.5 | J33: Fármarcos | K33: EMCURE PHARMA CHILE SPA | L33: 77.240.238-4 | M33: FABRICACION DE PRODUCTOS FARMACEUTICOS, SUSTANCIAS QUIMICAS MEDICINALE | N33: Mediana | O33: Región Metropolitana de Santiago | P33: 51101572 | Q33: AZITROMICINA 500 MG IV | R33: 50 | S33: Unidad | T33: 15925 | U33: 796250 | V33: 1058012-119-COT25 | W33: EL HOSPITAL CLÍNICO DE MAGALLANES REQUIERE AZITROMICINA 500 MG IV. INDICAR AL COTIZAR: VALOR UNITARIO TOTAL, PRESENTACIÓN (UD), FECHA VCTO, ADJUNTAR FICHA TÉCNICA Y/O REGISTRO ISP, TIPO DE TRASLADO CARGO PROVEEDOR (ESPECIFICAR, PARA ACORDAR RETIRO CARGO HOSPITAL DE SER NECESARIO), E INDICAR SI CUENTA CON STOCK PARA DESPACHO INMEDIATO. SE DESESTIMARÁ OFERTA QUE INDIQUE VALOR REFERENCIAL $0 o $1, U OMITAN INFORMACIÓN Y DOCUMENTOS SOLICITADOS. | X33: 51101572 | Y33: 77.240.238-4 | Z33: AZITROMICINA LIOFILIZADO PARA SOLUCIÓN INYECTABLE 500MG FAM, FACTOR EMPAQUE X 10 FAM. EQUIVALENTE TERAPÉUTICO, Registro ISP F-27542/23, Vencimiento 07-2026 Stock disponible, entrega en 3 días - flete incluido. Datos de contacto en cotización adjunta.
A34: 1058012-4622-AG25 | B34: 45964 | C34: FARMACIA DOSIS UNITARIA NEONATOLOGIA/ BIFIDOBACTERIUM, BB-12 PROBIOTICOS EN GOTAS | D34: PEDIDO FARMACIA DOSIS UNITARIA NEONATOLOGIA. COMPRA AGIL DESPACHO, CARGO DEL PROVEEDOR. 1058012-135-COT25 | E34: 303220 | F34: 0 | G34: 0 | H34: 57611.8 | I34: 360831.8 | J34: Fármarcos | K34: FARMACEUTICA CARIBEAN LTDA | L34: 76.830.090-9 | M34: VENTA AL POR MAYOR DE ARTICULOS DE PERFUMERIA, COSMETICOS, JABONES Y P| VENTA AL POR MAYOR DE PRODUCTOS FARMACEUTICOS| ALMACENES MEDIANOS (VENTA DE ALIMENTOS) SUPERMERCADOS, MINIMARKETS| VENTA AL POR MENOR DE PRODUCTOS MEDICINALES| VENTA AL POR MENOR DE | N34: Grande | O34: Región Metropolitana de Santiago | P34: 51191905 | Q34: BIFIDOBACTERIUM, BB-12 PROBIOTICOS EN GOTAS | R34: 20 | S34: Frasco | T34: 15161 | U34: 303220 | V34: 1058012-135-COT25 | W34: EL HOSPITAL CLÍNICO DE MAGALLANES REQUIERE BIFIDOBACTERIUM, BB-12 PROBIOTICOS EN GOTAS. INDICAR AL COTIZAR: VALOR UNITARIO TOTAL, PRESENTACIÓN (ML), FECHA VCTO, ADJUNTAR FICHA TÉCNICA Y/O REGISTRO ISP, TIPO DE TRASLADO (ESPECIFICAR, PARA ACORDAR RETIRO CARGO HOSPITAL DE SER NECESARIO), E INDICAR SI CUENTA CON STOCK PARA DESPACHO INMEDIATO. SE DESESTIMARÁ OFERTA QUE INDIQUE VALOR REFERENCIAL $0 o $1, U OMITAN INFORMACIÓN. | X34: 51191905 | Y34: 76.830.090-9 | Z34: FACTURACION MINIMA $50.000+IVA PARA SANTIAGO Y $75.000+IVA PARA REGIONES, DESPACHO: STGO 24-48 HR Y REGIONES 48-72 HRS, FLETE ADICIONALSOLO SUEROS X VOLUMEN, UNIDAD MIN. COTIZADA, SE AJUSTARÁ A FACTOR DE EMPAQUE, REG.ISP, FACT.ELECTRONICA.
A35: 1058012-4686-AG25 | B35: 45736 | C35: FALTA CENABAST MARZO / CICLOFOSFAMIDA 1G FA POLVO LIOFILIZADO | D35: PEDIDO FALTA DISTRIBUCIÓN CENABAST MARZO. ADQUISICIÓN VÍA COMPRA ÁGIL. DESPACH0O 24 A 48 HRS. SEGÚN COTIZACIÓN. ZGEN 100000371. REF 1058012-146-COT25. | E35: 990080 | F35: 0 | G35: 0 | H35: 188115.2 | I35: 1178195.2 | J35: Fármarcos | K35: ADN FARMACEUTICA SPA | L35: 76.786.297-0 | M35: DROGUERIA | N35: Mediana | O35: Región Metropolitana de Santiago | P35: 51111507 | Q35: CICLOFOSFAMIDA 1G FA POLVO LIOFILIZADO | R35: 70 | S35: Frasco Ampolla | T35: 14144 | U35: 990080 | V35: 1058012-146-COT25 | W35: EL HOSPITAL CLÍNICO DE MAGALLANES REQUIERE CICLOFOSFAMIDA 1G FA POLVO LIOFILIZADO. INDICAR AL COTIZAR: VALOR UNITARIO TOTAL, PRESENTACIÓN (ML), FECHA VCTO, ADJUNTAR FICHA TÉCNICA Y/O REGISTRO ISP, TIPO DE TRASLADO (ESPECIFICAR, PARA ACORDAR RETIRO CARGO HOSPITAL DE SER NECESARIO), E INDICAR SI CUENTA CON STOCK PARA DESPACHO INMEDIATO. SE DECLARARA INADMISIBLE OFERTA QUE INDIQUE VALOR REFERENCIAL $0 o $1, NO ENTREGUEN DOCUMENTACIÓN TÉCNICA U OMITAN INFORMACIÓN. | X35: 51111507 | Y35: 76.786.297-0 | Z35: ENDOXAN 1 G SOL. INY. X 50 ML, COSTO FLETE INCLUIDO, DESPACHO DE 24 A 48 HORAS, UNA VEZ ACEPTADA LA ORDEN DE COMPRA, SIN MÍNIMO DE FACTURACIÓN, VENCE SUPERIOR A 12 MESES (PV) pvalencia@adnfarmaceutica.cl
A36: 1058012-7676-AG25 | B36: 45907 | C36: FALTA CENABAST JULIO (FALTANTE) / CICLOFOSFAMIDA 1G FA POLVO LIOFILIZADO | D36: PEDIDO FALTA CENABAST JULIO (FALTANTE). ADQUISICIÓN VÍA COMPRA ÁGIL. DESPACHO 3 DÍAS CARGO DEL PROVEEDOR SEGÚN COTIZACIÓN. ZGEN 100000371. REF 1058012-437-COT25. | E36: 424320 | F36: 0 | G36: 0 | H36: 80620.8 | I36: 504940.8 | J36: Fármarcos | K36: ADN FARMACEUTICA SPA | L36: 76.786.297-0 | M36: DROGUERIA | N36: Mediana | O36: Región Metropolitana de Santiago | P36: 51111507 | Q36: CICLOFOSFAMIDA 1G FA POLVO LIOFILIZADO | R36: 30 | S36: Frasco Ampolla | T36: 14144 | U36: 424320 | V36: 1058012-437-COT25 | W36: EL HCM REQUIERE CICLOFOSFAMIDA 1G FA POLVO LIOFILIZADO. INDICAR FECHA DE ENTREGA EN BODEGA HCM, FACTOR EMPAQUE, FECHA VCTO, ADJUNTAR FICHA TÉCNICA Y/O REGISTRO ISP, TIPO DE TRASLADO. POSTULAR SOLO SI CUENTA CON STOCK PARA DESPACHO INMEDIATO. COMPRA SUJETA A MULTA DE NO RESPETAR FECHA ESTIMADA DE ENTREGA. SE DESESTIMARÁ OFERTA QUE INDIQUE VALOR REFERENCIAL $1, O QUE SOBREPASE EL VALOR DEL MONTO ESTIMADO O NO CUMPLA CON LOS DIAS Y DOC. SOLICITADOS. | X36: 51111507 | Y36: 76.786.297-0 | Z36: ENDOXAN 1 G SOL. INY. X 50 ML*ENTREGA DE 24 A 48 HRS, VENCE MAS DE 12 MESES, DESPACHO C/FACTURA, DESPACHO INCLUIDO EN EL PRECIO, SIN MINIMO DE COMPRA,CON POLITICA DE CANJE, OFERENTE Ximena Silva/9-57438894/xsilva@adnfarmaceutica.cl
A37: 1058012-7672-AG25 | B37: 45876 | C37: COMPRA ALTERNATIVA FALTA CENABAST MAYO Y JUNIO / LACTULOSA 65-66 1000 ML | D37: COMPRA ALTERNATIVA POR FALTA DE STOCK EN PROVEEDOR OC N° 1058012-7047-SE25 Y OC N° 1058012-7423-SE25. ADQUISICIÓN VÍA COMPRA ÁGIL. DESPACHO 7 DÍAS CARGO DEL PROVEEDOR SEGÚN COTIZACIÓN. ZGEN 100000893. REF 1058012-452-COT25. | E37: 2898000 | F37: 0 | G37: 0 | H37: 550620 | I37: 3448620 | J37: Fármarcos | K37: SCM PHARMA SPA | L37: 77.337.544-5 | M37: VENTA AL POR MAYOR DE PRODUCTOS FARMACEUTICOS Y MEDICINALES | N37: Mediana | O37: Región Metropolitana de Santiago | P37: 51171605 | Q37: LACTULOSA 65-66 1000 ML | R37: 210 | S37: Litro | T37: 13800 | U37: 2898000 | V37: 1058012-452-COT25 | W37: EL HOSPITAL CLÍNICO DE MAGALLANES REQUIERE LACTULOSA 65-66 1000 ML. INDICAR AL COTIZAR: VALOR UNITARIO TOTAL, PRESENTACIÓN (LT), FECHA VCTO, ADJUNTAR FICHA TÉCNICA Y/O REGISTRO ISP, TIPO DE TRASLADO Y FECHA ESPECIFICA DE ENTREGA (ESPECIFICAR, PARA ACORDAR RETIRO CARGO HOSPITAL DE SER NECESARIO), E INDICAR SI CUENTA CON STOCK PARA DESPACHO INMEDIATO. SE DECLARARÁ INADMISIBLE OFERTA QUE INDIQUE VALOR REFERENCIAL $0 o $1, U OMITAN INFORMACIÓN Y DOCUMENTOS SOLICITADOS. | X37: 51171605 | Y37: 77.337.544-5 | Z37: Se adjunta cotización detallada, Contacto F. 225104550, contacto@scmpharma.cl, Despacho sin costo, Envio 7 dias- monto mínimo de despacho $ 100.000.- Cotización valida por 15 días.
A38: 1058012-1372-AG24 | B38: 45571 | C38: FARMACIA AMBULATORIA JUNIO / CARBAMAZEPINA 100 MG 5ML SO | D38: PEDIDO FARMACIA AMBULATORIA JUNIO. ADQUISICIÓN VÍA COMPRA ÁGIL. FLETE CARGO DEL PROVEEDOR. ZGEN 100005816. REF 1058012-402-COT24. | E38: 619200 | F38: 0 | G38: 0 | H38: 117648 | I38: 736848 | J38: Fármarcos | K38: NOVOFARMA SERVICE S A | L38: 96.945.670-2 | M38: SERVICIOS DE ALMACENAMIENTO Y DEPOSITO| OTRAS ACTIVIDADES EMPRESARIALES N.C.P. | N38: Grande | O38: Región Metropolitana de Santiago | P38: 51141513 | Q38: CARBAMAZEPINA 100 MG 5ML SOLUCIÓN ORAL | R38: 48 | S38: Frasco | T38: 12900 | U38: 619200 | V38: 1058012-402-COT24 | W38: EL HOSPITAL CLÍNICO DE MAGALLANES REQUIERE CARBAMAZEPINA 100 MG 5ML SO. INDICAR AL COTIZAR: VALOR UNITARIO TOTAL, PRESENTACIÓN (ML), FECHA VCTO, ADJUNTAR FICHA TÉCNICA Y/O REGISTRO ISP, TIPO DE TRASLADO CARGO PROVEEDOR CON DESPACHOS PARCIALIZADOS (ESPECIFICAR, PARA ACORDAR RETIRO CARGO HOSPITAL DE SER NECESARIO), E INDICAR SI CUENTA CON STOCK PARA DESPACHO INMEDIATO. SE DESESTIMARÁ OFERTA QUE INDIQUE VALOR REFERENCIAL $0 o $1, U OMITAN INFORMACIÓN. | X38: 51141513 | Y38: 96.945.670-2 | Z38: AX3003800 - TEGRETAL JARABE 2% 100ML - F-4378/20 - CARBAMAZEPINA - - FRASCO 100 ML - EFICACIA DE 36 MESES ALMACENADO A NO MÁS DE 25ºC - LOTE ACTUAL VENCE 31/08/2026 DESPACHO INMEDIATO- SIN REGARGO POR FLETE- MINIMO DE DESPACHO 7 UF + IVA.
A39: 1058012-6777-AG25 | B39: 45763 | C39: COMPRA ALTERNATIVA STOCK CRÍTICO FARMACIA DOSIS UNITARIA / AMINOACIDOS 10% PARA ADMINISTRACION I.V. | D39: COMPRA ALTERNATIVA STOCK CRÍTICO FARMACIA DOSIS UNITARIA EN PROVEEDOR DE N° ORDEN 1058012-6645-SE25. ADQUISICIÓN VÍA COMPRA ÁGIL. TRASLADO AEREO CARGO DEL PROVEEDOR ZGEN 100000114 REF 1058012-204-COT25 | E39: 1278800 | F39: 0 | G39: 0 | H39: 242972 | I39: 1521772 | J39: Fármarcos | K39: FRESENIUS KABI CHILE LIMITADA | L39: 77.478.120-k | M39: VENTA AL POR MAYOR DE PRODUCTOS FARMACEUTICOS| TRANSPORTE DE CARGA POR CARRETERA| EMPRESAS DE ASESORIA, CONSULTORIA FINANCIERA Y DE APOYO AL GIRO | N39: Grande | O39: Región Metropolitana de Santiago | P39: 51191902 | Q39: AMINOACIDOS 10% PARA ADMINISTRACION I.V. | R39: 100 | S39: Unidad | T39: 12788 | U39: 1278800 | V39: 1058012-204-COT25 | W39: EL HOSPITAL CLÍNICO DE MAGALLANES REQUIERE AMINOACIDOS 10% PARA ADMINISTRACION I.V. INDICAR AL COTIZAR: VALOR UNITARIO TOTAL, PRESENTACIÓN (UD), FECHA VCTO, ADJUNTAR FICHA TÉCNICA Y/O REGISTRO ISP, TIPO DE TRASLADO (ESPECIFICAR, PARA ACORDAR RETIRO CARGO HOSPITAL DE SER NECESARIO), E INDICAR SI CUENTA CON STOCK PARA DESPACHO INMEDIATO. SE DECLARARÁ INADMISIBLE OFERTA QUE INDIQUE VALOR REFERENCIAL $0 o $1, U OMITAN CUALQUIER INFORMACIÓN SOLICITADA PARA ESTA COTIZACIÓN. | X39: 51191902 | Y39: 77.478.120-k | Z39: Cotización_0020178566. Despacho en caja según factor de empaque. Vencimiento de material 04.07.2026.
... A47: 1058012-2089-AG24 | B47: 45533 | C47: STOCK CRÍTICO FARMACIA AMBULATORIA AGOSTO / BUDESONIDA FORMOTEROL FUMARATO 160/4,5 MCG BUCAL | D47: PEDIDO STOCK CRÍTICO FARMACIA AMBULATORIA AGOSTO. ADQUISICIÓN VÍA COMPRA ÁGIL. FLETE 2 A 3 DÍAS HÁBILES CARGO DEL PROVEEDOR SEGÚN COTIZACIÓN. REF 1058012-543-COT24. | E47: 1087300 | F47: 0 | G47: 0 | H47: 206587 | I47: 1293887 | J47: Fármarcos | K47: ASTRAZENECA SA | L47: 76.447.530-5 | M47: VENTA AL POR MAYOR DE PRODUCTOS FARMACEUTICOS | N47: Grande | O47: Región Metropolitana de Santiago | P47: 51161703 | Q47: BUDESONIDA FORMOTEROL FUMARATO 160/4,5 MCG BUCAL | R47: 100 | S47: Unidad | T47: 10873 | U47: 1087300 | V47: 1058012-543-COT24 | W47: EL HOSPITAL CLÍNICO DE MAGALLANES REQUIERE BUDESONIDA FORMOTEROL FUMARATO 160/4,5 MCG BUCAL. INDICAR AL COTIZAR: VALOR UNITARIO TOTAL, PRESENTACIÓN (UD), FECHA VCTO, ADJUNTAR FICHA TÉCNICA Y/O REGISTRO ISP, TIPO DE TRASLADO CARGO PROVEEDOR (ESPECIFICAR, PARA ACORDAR RETIRO CARGO HOSPITAL DE SER NECESARIO), E INDICAR SI CUENTA CON STOCK PARA DESPACHO INMEDIATO. SE DESESTIMARÁ OFERTA QUE INDIQUE VALOR REFERENCIAL $0 o $1, U OMITAN INFORMACIÓN Y DOCUMENTOS SOLICITADOS. | X47: 51161703 | Y47: 76.447.530-5 | Z47: Fármaco innovador y/o referente. Venc > 1 año, despacho 2-3 días hábiles desde aceptación de orden de compra. Flete incluido. Cuando genere su OC, el rut de compra y dirección de despacho deben poseer autorización sanitaria vigente.
A48: 1058012-2875-AG24 | B48: 45547 | C48: FARMACIA DOSIS UNITARIA DICIEMBRE / KETAMINA 500 MG 10 ML SOL INY FA | D48: PEDIDO FARMACIA DOSIS UNITARIA DICIEMBRE. ADQUISICIÓN VÍA COMPRA ÁGIL. FLETE CARGO DEL PROVEEDOR. ZGEN 100000865. REF 1058012-662-COT24. | E48: 257500 | F48: 0 | G48: 0 | H48: 48925 | I48: 306425 | J48: Fármarcos | K48: CRISTALIA CHILE SPA | L48: 77.542.429-K | N48: N/A | O48: Región Metropolitana de Santiago | P48: 51142934 | Q48: KETAMINA SOL INY 500 MG/10 ML | R48: 25 | S48: Frasco Ampolla | T48: 10300 | U48: 257500 | V48: 1058012-662-COT24 | W48: EL HOSPITAL CLÍNICO DE MAGALLANES REQUIERE KETAMINA SOL INY 500 MG/10 ML. INDICAR AL COTIZAR: VALOR UNITARIO TOTAL, PRESENTACIÓN (ML), FECHA VCTO, ADJUNTAR FICHA TÉCNICA Y/O REGISTRO ISP, TIPO DE TRASLADO y ESPECIFICAR FECHA DE ENTREGA, INDICAR SI CUENTA CON STOCK PARA DESPACHO INMEDIATO. SE DESESTIMARÁ OFERTA QUE INDIQUE VALOR REFERENCIAL $0 o $1, U OMITAN INFORMACIÓN. | X48: 51142934 | Y48: 77.542.429-K | Z48: -ESKETAMINA MARCA KETA-S 50MG/ML 25FA 10 ML POR LABORATORIO CRISTALIA (PRESENTACION 25 FRASCO AMPOLLA POR CAJA) VENCIMIENTO SUPERIOR A 12 MESES DISTRIBUCION DESDE 23-12-2024
A49: 1057402-6386-AG24 | B49: 45464 | C49: (FAR) ANTISEPTICOS Y DESINFECTANTES JUNIO / CLORHEXIDINA 5% TINTURA 125 ML | D49: PEDIDO ANTISEPTICOS Y DESINFECTANTES JUNIO. ADQUISICIÓN VÍA COMPRA ÁGIL. FLETE 3 A 5 DÍAS HÁBILES SEGÚN COTIZACIÓN. REF 1057402-936-COT24 | E49: 720000 | F49: 0 | G49: 0 | H49: 136800 | I49: 856800 | J49: Bienes y Servicios | K49: EQUIPOS MÉDICOS CHILE SPA | L49: 77.354.084-5 | N49: Pequeña | O49: Región Metropolitana de Santiago | P49: 42281601 | Q49: CLORHEXIDINA 5% TINTURA 125 ML | R49: 72 | S49: Unidad | T49: 10000 | U49: 720000 | V49: 1057402-936-COT24 | W49: SE REQUIERE PARA EL HOSPITAL CLÍNICO DE MAGALLANES CLORHEXIDINA 5% TINTURA 125 ML. INDICAR: VALOR UNITARIO, PRESENTACIÓN Y EMPAQUE (ML), FECHA VCTO, ADJUNTAR FICHA TÉCNICA Y/O REGISTRO ISP, IMAGEN DEL PRODUCTO, TIEMPO DE ENTREGA (ESPECIFICAR, PARA COORDINAR RETIRO CARGO HOSPITAL DE SER NECESARIO), E INDICAR SI CUENTA CON STOCK PARA DESPACHO INMEDIATO. NO SE CONSIDERARÁN OFERTAS QUE INDIQUEN VALOR REFERENCIAL $0 Ó $1 U OMITAN INFORMACIÓN. | X49: 42281601 | Y49: 77.354.084-5 | Z49: SE ADJUNTA FICHA TÉCNICA DE LA OFERTA, INCLUYE LA TOTALIDAD DE LA SOLICITUD. ENTREGA 3 A 5 DÍAS HÁBILES. ANTE DUDAS FAVOR CONTACTARME c.calderon@equiposmedicoschile.cl +56937621017 CATALINA CALDERÓ
A50: 1058012-1537-AG24 | B50: 45468 | C50: COMPRA ALTERNATIVA FALTA CENABAST JUNIO / LEVETIRACETAM 100 MG ML SO | D50: COMPRA ALTERNATIVA POR FALTA DE STOCK EN PROVEEDOR OC N° 1058012-1384-SE24. ADQUISICIÓN VÍA COMPRA ÁGIL. FLETE 2 DÍAS HÁBILES SEGÚN COTIZACIÓN. ZGEN 100002573. REF 1058012-428-COT24. | E50: 600000 | F50: 0 | G50: 0 | H50: 114000 | I50: 714000 | J50: Fármarcos | K50: LABORATORIOS RECALCINE SA | L50: 91.637.000-8 | M50: FABRICACION DE PRODUCTOS FARMACEUTICOS, SUSTANCIAS QUIMICAS MEDICINALE| VENTA AL POR MAYOR DE OTROS PRODUCTOS N.C.P.| OTRAS ACTIVIDADES EMPRESARIALES N.C.P. | N50: Grande | O50: Región Metropolitana de Santiago | P50: 51141518 | Q50: LEVETIRACETAM 100 MG ML SOLUCIÓN ORAL | R50: 60 | S50: Frasco | T50: 10000 | U50: 600000 | V50: 1058012-428-COT24 | W50: EL HOSPITAL CLÍNICO DE MAGALLANES REQUIERE LEVETIRACETAM 100 MG ML SO. INDICAR AL COTIZAR: VALOR UNITARIO TOTAL, PRESENTACIÓN (ML), FECHA VCTO, ADJUNTAR FICHA TÉCNICA Y/O REGISTRO ISP, TIPO DE TRASLADO CARGO PROVEEDOR (ESPECIFICAR, PARA ACORDAR RETIRO CARGO HOSPITAL DE SER NECESARIO), E INDICAR SI CUENTA CON STOCK PARA DESPACHO INMEDIATO. SE DESESTIMARÁ OFERTA QUE INDIQUE VALOR REFERENCIAL $0 o $1, U OMITAN INFORMACIÓN. | X50: 51141518 | Y50: 91.637.000-8 | Z50: 881526 KOPODEX 100MG SOL ORAL X 120 ML PA LEVETIRACETAM 100 MG REG ISP F-16138/22 VENCE 15-05-2027. PRECIO INCL. FLETE, ENTREGA 48 HRS HAB., MIN. FACT. $100.000.- STOCK DISPONIBLE, CONTACTO: SHIRLEY.BELMAR@ABBOTT.COM
A51: 1058012-2828-AG24 | B51: 45625 | C51: FARMACIA DOSIS UNITARIA/ FENOTERTOL BROMI}HIDRATO 0,5 MG + IPATROPIO BROMURO 0,25 MG/ML 1058012-655-COT24 | D51: PEDIDO FARMACIA DOSIS UNITARIA. COMPRA AGIL (SIN OFERTAS) DESPACHO CARGO DEL PROVEEDOR. 100000627 | E51: 950000 | F51: 0 | G51: 0 | H51: 180500 | I51: 1130500 | J51: Fármarcos | K51: DROGUERÍA ACONCAGUA SPA | L51: 76.985.933-0 | M51: VENTA AL POR MAYOR DE PRODUCTOS FARMACEUTICOS Y MEDICINALES | N51: Micro | O51: Región Metropolitana de Santiago | P51: 51151738 | Q51: FENOTEROL BROMHIDRATO 0,5 MG + IPATROPIO BROMURO 0,25 MG / ML | R51: 100 | S51: Unidad | T51: 9500 | U51: 950000 | V51: 1058012-655-COT24 | W51: EL HOSPITAL CLÍNICO DE MAGALLANES REQUIERE FENOTEROL BROMHIDRATO 0,5 MG + IPATROPIO BROMURO 0,25 MG / ML INDICAR AL COTIZAR: VALOR UNITARIO TOTAL, PRESENTACIÓN (ML), FECHA VCTO, ADJUNTAR FICHA TÉCNICA Y/O REGISTRO ISP, TIPO DE TRASLADO (ESPECIFICAR, PARA ACORDAR RETIRO CARGO HOSPITAL DE SER NECESARIO), E INDICAR SI CUENTA CON STOCK PARA DESPACHO INMEDIATO. SE DESESTIMARÁ OFERTA QUE INDIQUE VALOR REFERENCIAL $0 o $1, U OMITAN INFORMACIÓN. | X51: 51151738 | Y51: 76.985.933-0 | Z51: ADJUNTO COTIZACIÓN FORMAL, FICHA DE PRODUCTOS Y REGISTRO DE ISP. VENCIMIENTO MAYOR A 12 MESES. ENTREGA Y DISPONIBILIDAD INMEDIATA LUEGO DE EMITIDA LA OC. MÍNIMO DE DESPACHO $180.000. CONTACTO DE VENTAS JONATHAN GRANIFO. VENTAS3@ACGRUPOACONCAGUA.CL
A52: 1058012-96-AG25 | B52: 45901 | C52: COMITÉ FARMACIA/ AMBRISENTÁN 10 MG CM | D52: PEDIDO COMITÉ FARMACIA. COMPRA AGIL DESPACHO CARGO DEL PROVEEDOR. 1058012-11-COT25 | E52: 762750 | F52: 0 | G52: 0 | H52: 144922.5 | I52: 907672.5 | J52: Fármarcos | K52: EMCURE PHARMA CHILE SPA | L52: 77.240.238-4 | M52: FABRICACION DE PRODUCTOS FARMACEUTICOS, SUSTANCIAS QUIMICAS MEDICINALE | N52: Mediana | O52: Región Metropolitana de Santiago | P52: 51161626 | Q52: AMBRISENTAM 10 MG CM | R52: 90 | S52: Comprimido | T52: 8475 | U52: 762750 | V52: 1058012-11-COT25 | W52: EL HOSPITAL CLÍNICO DE MAGALLANES REQUIERE AMBRISENTAM 10 MG CM. INDICAR AL COTIZAR: VALOR UNITARIO TOTAL, PRESENTACIÓN (ML), FECHA VCTO, ADJUNTAR FICHA TÉCNICA Y/O REGISTRO ISP, TIPO DE TRASLADO (ESPECIFICAR, PARA ACORDAR RETIRO CARGO HOSPITAL DE SER NECESARIO), E INDICAR SI CUENTA CON STOCK PARA DESPACHO INMEDIATO. SE DESESTIMARÁ OFERTA QUE INDIQUE VALOR REFERENCIAL $0 o $1, U OMITAN INFORMACIÓN. | X52: 51161626 | Y52: 77.240.238-4 | Z52: ARISEON COMPRIMIDOS RECUBIERTOS 10 mg (AMBRISENTÁN), caja x 30, Registro ISP: F-27488, vencimiento 30-09-2027 Stock disponible, entrega en 3 días. Flete Incluido. Datos de contacto en cotización adjunta.
A53: 1058012-1243-AG24 | B53: 45440 | C53: COMITÉ FARMACIA MAYO / CIANOCOBALAMINA 50 MCG 5 ML JBE | D53: PEDIDO COMITÉ FARMACIA MAYO. ADQUISICIÓN VÍA COMPRA ÁGIL. FLETE CARGO DEL PROVEEDOR. DESPACHO PARCIALIZADO, 30 FRASCOS AL ACEPTAR OC, 30 FRASCOS RESTANTES SERAN COORDINADAS POR D. RODRIGO BARRIA (CORREO rodrigo.barria.hcm@gmail.com - FONO 61-2293466.) REF 1058012-368-COT24. COMITÉ FARMACIA N°4 DEL 29-04-2024. | E53: 465960 | F53: 0 | G53: 0 | H53: 88532.4 | I53: 554492.4 | J53: Fármarcos | K53: DROGUERIA GLOBAL PHARMA SPA | L53: 76.389.383-9 | M53: FARMACIA Y PERFUMERIA | N53: Grande | O53: Región Metropolitana de Santiago | P53: 85121902 | Q53: CIANOCOBALAMINA 50 MCG 5 ML JBE | R53: 60 | S53: Frasco | T53: 7766 | U53: 465960 | V53: 1058012-368-COT24 | W53: EL HOSPITAL CLÍNICO DE MAGALLANES REQUIERE CIANOCOBALAMINA 50 MCG 5 ML JBE. INDICAR AL COTIZAR: VALOR UNITARIO TOTAL, PRESENTACIÓN (ML), FECHA VCTO, ADJUNTAR FICHA TÉCNICA Y/O REGISTRO ISP, TIPO DE TRASLADO CARGO PROVEEDOR, SE SOLICITARAN DESPACHOS PARCIALIZADOS SEGÚN SOLICITUDES DEL HOSPITAL. (ESPECIFICAR, PARA ACORDAR RETIRO CARGO HOSPITAL DE SER NECESARIO), E INDICAR SI CUENTA CON STOCK PARA DESPACHO INMEDIATO. SE DESESTIMARÁ OFERTA QUE INDIQUE VALOR REFERENCIAL $0 o $1, U OMITAN INFORMACIÓ | X53: 85121902 | Y53: 76.389.383-9 | Z53: 66661104 TOL-12 ORAL SOLUCION ORAL 250 ML (CIANOCOBALAMINA+PIRIDOXINA+TIAMINA) LAB SAVAL ABR-2027 DROGUERÍA GLOBAL PHARMA SPA POSEE TRANSPORTE FDEX/TNT/STARKEN ENTREGA EN 12 DÍAS HÁBILES, MÍNIMO DE COMPRA $30.000 MÁS IVA. INFO AESCOBEDO@GLOBAL-PHARMA.CL
A54: 1057402-5711-AG24 | B54: 45479 | C54: (FAR) SUEROS Y ALCOHOLES JUNIO / ALCOHOL ETILICO 99° ML | D54: PEDIDO SUEROS Y ALCOHOLES JUNIO. ADQUISICIÓN VÍA COMPRA ÁGIL. FLETE CARGO DEL PROVEEDOR. REF 1057402-857-COT24. | E54: 1327500 | F54: 0 | G54: 0 | H54: 252225 | I54: 1579725 | J54: Bienes y Servicios | K54: VERDEJO Y VERDEJO LIMITADA | L54: 79.591.440-4 | M54: VENTAS AL POR MENOR DE OTROS PRODUCTOS EN ALMACENES ESPECIALIZADOS N.C | N54: Pequeña | O54: Región Metropolitana de Santiago | P54: 42281711 | Q54: ALCOHOL ABSOLUTO = 99° PA, BIDON 2,5 LITROS. | R54: 180 | S54: Bidón | T54: 7375 | U54: 1327500 | V54: 1057402-857-COT24 | W54: SE REQUIERE PARA EL HOSPITAL CLÍNICO DE MAGALLANES ALCOHOL ETILICO 99° 2,5 LT. INDICAR: VALOR UNITARIO, PRESENTACIÓN Y EMPAQUE (ML), FECHA VCTO, ADJUNTAR FICHA TÉCNICA Y/O REGISTRO ISP, IMAGEN DEL PRODUCTO, TIEMPO DE ENTREGA (ESPECIFICAR, PARA COORDINAR RETIRO CARGO HOSPITAL DE SER NECESARIO), E INDICAR SI CUENTA CON STOCK PARA DESPACHO INMEDIATO. NO SE CONSIDERARÁN OFERTAS QUE INDIQUEN VALOR REFERENCIAL $0 Ó $1 U OMITAN INFORMACIÓN. | X54: 42281711 | Y54: 79.591.440-4 | Z54: Alcohol Etílico Anhidro 99,5º
A55: 1058012-7821-AG25 | B55: 45862 | C55: FARMACIA DU JULIO / MIVACUORIO 10MG/5ML AM | D55: FARMACIA DU JULIO ADQUISICION A TRAVES DE COMPRA AGIL DESPACHO 24 A 48 HORAS CARGO DEL PROVEEDOR REF: 1058012-460-COT25 | E55: 423540 | F55: 0 | G55: 0 | H55: 80472.6 | I55: 504012.6 | J55: Fármarcos | K55: ASPEN CHILE S.A. | L55: 76.328.242-2 | M55: Venta de Productos y Subproductos Farmacéuticos, medicinales y nutricionales | N55: Grande | O55: Región Metropolitana de Santiago | P55: 51152002 | Q55: MIVACUORIO 10MG/5ML AM | R55: 60 | S55: Ampolla | T55: 7059 | U55: 423540 | V55: 1058012-460-COT25 | W55: EL HCM REQUIERE MIVACUORIO 10ML/5ML AM. INDICAR FECHA DE ENTREGA EN BODEGA HCM, FACTOR EMPAQUE, FECHA VCTO, ADJUNTAR FICHA TÉCNICA Y/O REGISTRO ISP, TIPO DE TRASLADO. POSTULAR SOLO SI CUENTA CON STOCK PARA DESPACHO INMEDIATO. COMPRA SUJETA A MULTA DE NO RESPETAR FECHA ESTIMADA DE ENTREGA. SE DESESTIMARÁ OFERTA QUE INDIQUE VALOR REFERENCIAL $1, O QUE SOBREPASE EL VALOR DEL MONTO ESTIMADO O NO CUMPLA CON LOS DIAS Y DOC. SOLICITADOS. | X55: 51152002 | Y55: 76.328.242-2 | Z55: MIVACRON SOL.INY.10 mg5 ml (Mivacurio Cloruro).Reg.ISP:F-2658722. PROVEEDOR UNICO.Fabricante:ASPEN SA STERILE OPERATIONS PTY LTD , Sudráfica. Presentación:Caja x 5 amp.Producto Refrigerado.VCTO:10.2027. M.mínimo$100.000+IVA.Entrega 48 hr hábiles
A56: 1058012-8344-AG25 | B56: 45917 | C56: FARMACIA AMBULATORIA SEPTIEMBRE / LUBRICANTE OCULAR QUE CONTENGA CARBOMERO | D56: PEDIDO FARMACIA AMBULATORIA SEPTIEMBRE. ADQUISICIÓN VÍA COMPRA ÁGIL. DESPACHO E DÍAS CARGO DEL PROVEEDOR. REF 1058012-553-COT25. | E56: 2429700 | F56: 0 | G56: 0 | H56: 461643 | I56: 2891343 | J56: Fármarcos | K56: THEA PHARMA SPA | L56: 76.692.953-2 | M56: Venta al por mayor de otros productos N.C.P. | N56: Grande | O56: Región Metropolitana de Santiago | P56: 51241120 | Q56: LUBRICANTE OCULAR QUE CONTENGA CARBOMERO (0,2-0,25,0,3 GR / 100 GR) GEL | R56: 350 | S56: Tubo | T56: 6942 | U56: 2429700 | V56: 1058012-553-COT25 | W56: EL HOSPITAL CLÍNICO DE MAGALLANES REQUIERE LUBRICANTE OCULAR QUE CONTENGA CARBOMERO. INDICAR AL COTIZAR: VALOR UNITARIO TOTAL, PRESENTACIÓN (TUBO), FECHA VCTO, ADJUNTAR FICHA TÉCNICA Y/O REGISTRO ISP, TIPO DE TRASLADO Y FECHA ESPECIFICA DE ENTREGA (ESPECIFICAR, PARA ACORDAR RETIRO CARGO HOSPITAL DE SER NECESARIO), E INDICAR SI CUENTA CON STOCK PARA DESPACHO INMEDIATO. SE DECLARARÁ INADMISIBLE OFERTA QUE INDIQUE VALOR REFERENCIAL $0 o $1, U OMITAN INFORMACIÓN Y DOCUMENTOS SOLICITADOS. | X56: 51241120 | Y56: 76.692.953-2 | Z56: Siccafluid gel en gotas lubricantes oculares Frasco gotario por 10 gr.
A57: 1058012-2996-AG24 | B57: 45717 | C57: COMITÉ FARMACIA/ OLANZAPINA 10 MG BUCODISPERSABLE | D57: PEDIDO COMITÉ FARMACIA. COMPRA AGIL DESPACHO CARGO DEL PROVEEDOR. 1058012-674-COT24 | E57: 3153500 | F57: 0 | G57: 0 | H57: 599165 | I57: 3752665 | J57: Fármarcos | K57: ADN FARMACEUTICA SPA | L57: 76.786.297-0 | M57: DROGUERIA | N57: Mediana | O57: Región Metropolitana de Santiago | P57: 51141703 | Q57: OLANZAPINA 10 MG BUCODISPERSABLE | R57: 500 | S57: Comprimido | T57: 6307 | U57: 3153500 | V57: 1058012-674-COT24 | W57: EL HOSPITAL CLÍNICO DE MAGALLANES REQUIERE OLANZAPINA 10 MG BUCODISPERSABLE. INDICAR AL COTIZAR: VALOR UNITARIO TOTAL, PRESENTACIÓN (ML), FECHA VCTO, ADJUNTAR FICHA TÉCNICA Y/O REGISTRO ISP, TIPO DE TRASLADO y ESPECIFICAR FECHA DE ENTREGA, INDICAR SI CUENTA CON STOCK PARA DESPACHO INMEDIATO. SE DESESTIMARÁ OFERTA QUE INDIQUE VALOR REFERENCIAL $0 o $1, U OMITAN INFORMACIÓN. | X57: 51141703 | Y57: 76.786.297-0 | Z57: ZYPREXA ZYDIS COM.10MG. CX14, COSTO FLETE INCLUIDO, DESPACHO DE 24 A 48 HORAS, UNA VEZ ACEPTADA LA ORDEN DE COMPRA, SIN MÍNIMO DE FACTURACIÓN, VENCE SUPERIOR A 12 MESES (PV) pvalencia@adnfarmaceutica.cl
A58: 1058012-2049-AG24 | B58: 45531 | C58: COMPRA ALTERNATIVA FALTA CENABAST/ REMIFENTANILO CLORHIDRATO 1 MG FA | D58: COMPRA ALTERNATIVA POR FALTA DE STOCK EN PROVEEDOR DE N° ORDEN 1058012-1955-SE24. ADQUISICIÓN VÍA COMPRA ÁGIL. TRASLADO CARGO AL PROVEEDOR ZGEN (100001243) REF 1058012-538-COT24 | E58: 123080 | F58: 0 | G58: 0 | H58: 23385.2 | I58: 146465.2 | J58: Fármarcos | K58: ASPEN CHILE S.A. | L58: 76.328.242-2 | M58: Venta de Productos y Subproductos Farmacéuticos, medicinales y nutricionales | N58: Grande | O58: Región Metropolitana de Santiago | P58: 51142232 | Q58: REMIFENTANILO CLORHIDRATO 1 MG FA | R58: 20 | S58: Frasco Ampolla | T58: 6154 | U58: 123080 | V58: 1058012-538-COT24 | W58: EL HOSPITAL CLÍNICO DE MAGALLANES REQUIERE REMIFENTANILO CLORHIDRATO 1 MG FA. INDICAR AL COTIZAR: VALOR UNITARIO TOTAL, PRESENTACIÓN (ML), FECHA VCTO, ADJUNTAR FICHA TÉCNICA Y/O REGISTRO ISP, TIPO DE TRASLADO y ESPECIFICAR FECHA DE ENTREGA, INDICAR SI CUENTA CON STOCK PARA DESPACHO INMEDIATO. SE DESESTIMARÁ OFERTA QUE INDIQUE VALOR REFERENCIAL $0 o $1, U OMITAN INFORMACIÓN. | X58: 51142232 | Y58: 76.328.242-2 | Z58: ULTIVA POLVO LIOFILIZADO PARA SOLUCIÓN INYECTABLE 1 mg. (remifentanilo). PRODUCTO ORIGINAL. REG ISP: F-309/23. Presentación: Caja x 5 amp. Procedencia: Glaxosmithkline Manufacturing S.P.A., Italia. Vcto.: 11.2024. M.mínimo $100.000+IVA entrega 48 hr hábil
A59: 1058012-881-AG24 | B59: 45399 | C59: FALTA CENABAST ABRIL / TIMOLOL MALEATO 0,5% SOLUC OFT | D59: PEDIDO FALTA DISTRIBUCIÓN CENABAST ABRIL. ADQUISICIÓN VÍA COMPRA ÁGIL. FLETE CARGO DEL PROVEEDOR. REF 1058012-278-COT24. | E59: 961600 | F59: 0 | G59: 0 | H59: 182704 | I59: 1144304 | J59: Fármarcos | K59: FARMACIAS PEDRO ITURRIETA MELENDEZ E.I.R.L. | L59: 76.764.759-K | N59: Pequeña | O59: Región Metropolitana de Santiago | P59: 51241115 | Q59: TIMOLOL MALEATO 0,5% SOL OFT | R59: 160 | S59: Frasco | T59: 6010 | U59: 961600 | V59: 1058012-278-COT24 | W59: EL HOSPITAL CLÍNICO DE MAGALLANES REQUIERE TIMOLOL MALEATO 0,5% SOL OFT. INDICAR AL COTIZAR: VALOR UNITARIO TOTAL, PRESENTACIÓN (FCO), FECHA VCTO, ADJUNTAR FICHA TÉCNICA Y/O REGISTRO ISP, TIPO DE TRASLADO CARGO PROVEEDOR (ESPECIFICAR, PARA ACORDAR RETIRO CARGO HOSPITAL DE SER NECESARIO), E INDICAR SI CUENTA CON STOCK PARA DESPACHO INMEDIATO. SE DESESTIMARÁ OFERTA QUE INDIQUE VALOR REFERENCIAL $0 o $1, U OMITAN INFORMACIÓN. | X59: 51241115 | Y59: 76.764.759-K | Z59: TIMOLOL COL 0,5% X 10 ML OPKO vence 7/24 despacho GRATIS 48 horas una vez aceptada la OC se adjunta ficha fono: 992657125
A60: 1058012-2219-AG24 | B60: 45548 | C60: COMITÉ FARMACIA N° 6/ BIFIDOBACTERIUM, BB-12 PROBIOTICOS EN GOTAS: 1058012-557-COT24 | D60: PEDIDO COMITE FARMACIA N° 6 F. DOSIS UNITARIA. COMPRA AGIL DESPACHO TERRESTRE, CARGO DEL PROVEEDOR. | E60: 120000 | F60: 0 | G60: 0 | H60: 22800 | I60: 142800 | J60: Fármarcos | K60: INSTITUTO SANITAS S A | L60: 90.073.000-4 | M60: FABRICACION DE PRODUCTOS FARMACEUTICOS, SUSTANCIAS QUIMICAS MEDICINALE | N60: Grande | O60: Región Metropolitana de Santiago | P60: 51191905 | Q60: BIFIDOBACTERIUM, BB-12 PROBIOTICOS EN GOTAS | R60: 20 | S60: Frasco | T60: 6000 | U60: 120000 | V60: 1058012-557-COT24 | W60: EL HOSPITAL CLÍNICO DE MAGALLANES REQUIERE BIFIDOBACTERIUM, BB-12 PROBIOTICOS EN GOTAS. INDICAR AL COTIZAR: VALOR UNITARIO TOTAL, PRESENTACIÓN (ML), FECHA VCTO, ADJUNTAR FICHA TÉCNICA Y/O REGISTRO ISP, TIPO DE TRASLADO (ESPECIFICAR, PARA ACORDAR RETIRO CARGO HOSPITAL DE SER NECESARIO), E INDICAR SI CUENTA CON STOCK PARA DESPACHO INMEDIATO. SE DESESTIMARÁ OFERTA QUE INDIQUE VALOR REFERENCIAL $0 o $1, U OMITAN INFORMACIÓN. | X60: 51191905 | Y60: 90.073.000-4 | Z60: S-PT4154.PROBACILUS.(Lactobacillus Reuteri)VENCE: 18-04-2026. Resolucio´n Sanitaria: 2113290870 del 26/07/20. VALIDEZ OFERTA:30 DÍAS. MONTO MÍNIMO:$120.000+IVA. ENVÍO TERRESTRE.PLAZO DE ENTREGA:15 DIAS.SE PUEDE ACORDAR RETIRO AL CORREO:squezada@sanitas.cl
A61: 1058012-7476-AG25 | B61: 45825 | C61: FARMACIA AMBULATORIA JUNIO / LACTOBACILLUS REUTERI PROTECTIS 5 ML | D61: PEDIDO FARMACIA AMBULATORIA JUNIO. ADQUISICIÓN VÍA COMPRA ÁGIL. DESPACHO 10 DÍAS CARGO DEL PROVEEDOR SEGÚN COTIZACIÓN. NOTA: SE PUEDE COORDINAR RETIRO DE LA CARGA. REF 1058012-390-COT25. | E61: 180000 | F61: 0 | G61: 0 | H61: 34200 | I61: 214200 | J61: Fármarcos | K61: INSTITUTO SANITAS S A | L61: 90.073.000-4 | M61: FABRICACION DE PRODUCTOS FARMACEUTICOS, SUSTANCIAS QUIMICAS MEDICINALE | N61: Grande | O61: Región Metropolitana de Santiago | P61: 51191905 | Q61: LACTOBACILLUS REUTERI PROTECTIS 5 ML GOTAS | R61: 30 | S61: Frasco | T61: 6000 | U61: 180000 | V61: 1058012-390-COT25 | W61: EL HOSPITAL CLÍNICO DE MAGALLANES REQUIERE LACTOBACILLUS REUTERI PROTECTIS 5 ML. INDICAR AL COTIZAR: VALOR UNITARIO TOTAL, PRESENTACIÓN (ML), FECHA VCTO, ADJUNTAR FICHA TÉCNICA Y/O REGISTRO ISP, TIPO DE TRASLADO Y FECHA ESPECIFICA DE ENTREGA (ESPECIFICAR, PARA ACORDAR RETIRO CARGO HOSPITAL DE SER NECESARIO), E INDICAR SI CUENTA CON STOCK PARA DESPACHO INMEDIATO. SE DECLARARÁ INADMISIBLE OFERTA QUE INDIQUE VALOR REFERENCIAL $0 o $1, U OMITAN INFORMACIÓN Y DOCUMENTOS SOLICITADOS. | X61: 51191905 | Y61: 90.073.000-4 | Z61: S-PT4154.PROBACILUS.POMO 5 ML.(Lactobacillus Reuteri)VENCE: 10-06-2026. Resolucio´n Sanitaria:2113290870 del 26/07/2021.VALIDEZ OFERTA:30 DÍAS.MONTO MÍNIMO:$120.000+IVA.PLAZO ENTREGA:10 DÍAS HÁBILES.PARA ACORDAR RETIRO CARGO HOSPITAL DE SER NECESESARIO
A62: 1057402-9103-AG24 | B62: 45605 | C62: (FAR) URGENTE ANTISEPTICOS Y DESINFENCTANTES SEPTIEMBRE / CLORHEXIDINA 2% ACUOSA TOPICA 500 ML | D62: PEDIDO URGENTE ANTISEPTICOS Y DESINFENCTANTES SEPTIEMBRE. ADQUISICIÓN VÍA COMPRA ÁGIL. FLETE 12 A 15 DÍAS SEGÚN COTIZACIÓN. REF 1057402-1234-COT24. | E62: 344160 | F62: 0 | G62: 0 | H62: 65390.4 | I62: 409550.4 | J62: Bienes y Servicios | K62: DIFEM LABORATORIOS S A | L62: 79.581.120-6 | M62: FABRICACION DE PRODUCTOS FARMACEUTICOS, SUSTANCIAS QUIMICAS MEDICINALE| FABRICACIONES DE JABONES Y DETERGENTES, PREPARADOS PARA LIMPIAR, PERFU | N62: Grande | O62: Región Metropolitana de Santiago | P62: 51102707 | Q62: CLORHEXIDINA 2% ACUOSA TOPICA 500 ML | R62: 60 | S62: Frasco | T62: 5736 | U62: 344160 | V62: 1057402-1234-COT24 | W62: SE REQUIERE PARA EL HOSPITAL CLÍNICO DE MAGALLANES CLORHEXIDINA 2% ACUOSA TOPICA 500 ML. INDICAR: VALOR UNITARIO, PRESENTACIÓN Y EMPAQUE (ML), FECHA VCTO, ADJUNTAR FICHA TÉCNICA Y/O REGISTRO ISP, IMAGEN DEL PRODUCTO, TIEMPO DE ENTREGA (ESPECIFICAR, PARA COORDINAR RETIRO CARGO HOSPITAL DE SER NECESARIO), E INDICAR SI CUENTA CON STOCK PARA DESPACHO INMEDIATO. NO SE CONSIDERARÁN OFERTAS QUE INDIQUEN VALOR REFERENCIAL $0 Ó $1 U OMITAN INFORMACIÓN Y DOCUMENTOS SOLICITADOS. | X62: 51102707 | Y62: 79.581.120-6 | Z62: Dichlorexan Solución Acuosa 2% 500cc. Marca DIFEM, procedencia nacional. Sin alcohol, para antisepsia de piel. Registro ISP. Estudio microb según resolución 89. Con inserto dosificador. Cajas x 20 unidades. Vencimiento 25-01-2026. Despacho 12-15 días.
A63: 1058012-1706-AG24 | B63: 45511 | C63: FARMACIA DOSIS UNITARIA/ VITAMINAS HIDROSUBLES USO IV INFANTIL - ADULTO (QUE CONTENGA 9 VITAMINAS HIDROSOLUBLES) | D63: PEDIDO FARMACIA DOSIS UNITARIA. COMPRA AGIL DESPACHO AÉREO CARGO DEL PROVEEDOR. 1058012-487-COT24 | E63: 1581440 | F63: 0 | G63: 0 | H63: 300473.6 | I63: 1881913.6 | J63: Fármarcos | K63: FRESENIUS KABI CHILE LIMITADA | L63: 77.478.120-k | M63: VENTA AL POR MAYOR DE PRODUCTOS FARMACEUTICOS| TRANSPORTE DE CARGA POR CARRETERA| EMPRESAS DE ASESORIA, CONSULTORIA FINANCIERA Y DE APOYO AL GIRO | N63: Grande | O63: Región Metropolitana de Santiago | P63: 51191905 | Q63: VITAMINAS HIDROSUBLES USO IV INFANTIL - ADULTO (QUE CONTENGA 9 VITAMINAS HIDROSOLUBLES) | R63: 280 | S63: Unidad | T63: 5648 | U63: 1581440 | V63: 1058012-487-COT24 | W63: EL HOSPITAL CLÍNICO DE MAGALLANES REQUIERE VITAMINAS HIDROSUBLES USO IV INFANTIL - ADULTO (QUE CONTENGA 9 VITAMINAS HIDROSOLUBLES). INDICAR AL COTIZAR: VALOR UNITARIO TOTAL, PRESENTACIÓN (ML), FECHA VCTO, ADJUNTAR FICHA TÉCNICA Y/O REGISTRO ISP, TIPO DE TRASLADO y ESPECIFICAR FECHA DE ENTREGA, INDICAR SI CUENTA CON STOCK PARA DESPACHO INMEDIATO. SE DESESTIMARÁ OFERTA QUE INDIQUE VALOR REFERENCIAL $0 o $1, U OMITAN INFORMACIÓN. | X63: 51191905 | Y63: 77.478.120-k | Z63: Cotización 20168464 , despacho en cajas cerradas, según factor de empaque. Despacho mínimo $200.000.- Oferta incluye despacho.
A64: 1058012-2581-AG24 | B64: 45423 | C64: FARMACIA DOSIS UNITARIA Y CENTRAL DE MEZCLAS/ VITAMINAS HIDROSUBLES USO IV INFANTIL - ADULTO (QUE CONTENGA 9 VITAMINAS HIDROSOLUBLES) | D64: PEDIDO FARMACIA DOSIS UNITARIA Y CENTRAL DE MEZCLAS. ID COMPRA AGIL DESPACHO AÉREO CARGO DEL PROVEEDOR. 1058012-613-COT24 | E64: 564700 | F64: 0 | G64: 0 | H64: 107293 | I64: 671993 | J64: Fármarcos | K64: FRESENIUS KABI CHILE LIMITADA | L64: 77.478.120-k | M64: VENTA AL POR MAYOR DE PRODUCTOS FARMACEUTICOS| TRANSPORTE DE CARGA POR CARRETERA| EMPRESAS DE ASESORIA, CONSULTORIA FINANCIERA Y DE APOYO AL GIRO | N64: Grande | O64: Región Metropolitana de Santiago | P64: 51191905 | Q64: VITAMINAS HIDROSUBLES USO IV INFANTIL - ADULTO (QUE CONTENGA 9 VITAMINAS HIDROSOLUBLES) | R64: 100 | S64: Unidad | T64: 5647 | U64: 564700 | V64: 1058012-613-COT24 | W64: EL HOSPITAL CLÍNICO DE MAGALLANES REQUIERE VITAMINAS HIDROSUBLES USO IV INFANTIL - ADULTO (QUE CONTENGA 9 VITAMINAS HIDROSOLUBLES). INDICAR AL COTIZAR: VALOR UNITARIO TOTAL, PRESENTACIÓN (ML), FECHA VCTO, ADJUNTAR FICHA TÉCNICA Y/O REGISTRO ISP, TIPO DE TRASLADO y ESPECIFICAR FECHA DE ENTREGA, INDICAR SI CUENTA CON STOCK PARA DESPACHO INMEDIATO. SE DESESTIMARÁ OFERTA QUE INDIQUE VALOR REFERENCIAL $0 o $1, U OMITAN INFORMACIÓN. | X64: 51191905 | Y64: 77.478.120-k | Z64: Cotización_0020172712, despacho en cajas cerradas, según factor de empaque. Despacho mínimo $200.000.-
A65: 1058012-423-AG24 | B65: 45342 | C65: FALTA CENABAST FEBRERO / FLUTICASONA 27,5 MCG/DO SUSP. NAS. | D65: PEDIDO FALTA DISTRIBUCIÓN CENABAST FEBRERO. ADQUISICIÓN VÍA COMPRA ÁGIL. FLETE EXPRESO CARGO DEL PROVEEDOR. ZGEN 100004353. REF 1058012-144-COT24. | E65: 970920 | F65: 0 | G65: 0 | H65: 184474.8 | I65: 1155394.8 | J65: Fármarcos | K65: ETEX FARMACEUTICA LIMITADA | L65: 78.026.330-K | M65: FABRICACION DE PRODUCTOS FARMACEUTICOS, SUSTANCIAS QUIMICAS MEDICINALE | N65: Grande | O65: Región Metropolitana de Santiago | P65: 51181722 | Q65: FLUTICASONA 27,5 MCG/DO SUSP. NAS. | R65: 180 | S65: Frasco | T65: 5394 | U65: 970920 | V65: 1058012-144-COT24 | W65: EL HOSPITAL CLÍNICO DE MAGALLANES REQUIERE FLUTICASONA 27,5 MCG/DO SUSP. NAS. INDICAR AL COTIZAR: VALOR UNITARIO TOTAL, PRESENTACIÓN (ML), FECHA VCTO, ADJUNTAR FICHA TÉCNICA Y/O REGISTRO ISP, TIPO DE TRASLADO CARGO PROVEEDOR (ESPECIFICAR, PARA ACORDAR RETIRO CARGO HOSPITAL DE SER NECESARIO), E INDICAR SI CUENTA CON STOCK PARA DESPACHO INMEDIATO. SE DESESTIMARÁ OFERTA QUE INDIQUE VALOR REFERENCIAL $0 o $1, U OMITAN INFORMACIÓN. | X65: 51181722 | Y65: 78.026.330-K | Z65: 10000000068114 ALENYS Susp Nebulización Nasal 27,5 mcg x 120 dosis Fluticasona Furoato VENCIMIENTO:Mayor a 12 Meses - ISP:F-16784/23 - Con cert. GMP. Despacho 3 dias habiles. Monto minimo de despacho $250.000 netos.
A66: 1058012-6753-AG25 | B66: 45761 | C66: FALTA CENABAST ABRIL/ ZIPRASIDONA 40 MG CP | D66: PEDIDO FALTA CENABAST ABRIL. COMPRA AGIL DESPACHO CARGO DEL PROVEEDOR. 100001579 1058012-203-COT25 | E66: 303540 | F66: 0 | G66: 0 | H66: 57672.6 | I66: 361212.6 | J66: Fármarcos | K66: SCM PHARMA SPA | L66: 77.337.544-5 | M66: VENTA AL POR MAYOR DE PRODUCTOS FARMACEUTICOS Y MEDICINALES | N66: Mediana | O66: Región Metropolitana de Santiago | P66: 51141725 | Q66: ZIPRASIDONA 40 MG CP | R66: 60 | S66: Cápsula | T66: 5059 | U66: 303540 | V66: 1058012-203-COT25 | W66: EL HOSPITAL CLÍNICO DE MAGALLANES REQUIERE ZIPRASIDONA 40 MG CP. INDICAR AL COTIZAR: FECHA DE ENTREGA EN BODEGA DEL HCM, PRESENTACIÓN (ML), FECHA VCTO, ADJUNTAR FICHA TÉCNICA Y/O REGISTRO ISP, TIPO DE TRASLADO. POSTULAR SOLO SI CUENTA CON STOCK PARA DESPACHO INMEDIATO. COMPRA SUJETA A MULTA POR NO RESPETAR FECHA ESTIMADA DE ENTREGA DE LA OC. SE DESESTIMARÁ OFERTA QUE INDIQUE VALOR REFERENCIAL $0 o $1, O NO CUMPLAN CON LO SOLICITADO. MOTIVO IPORTANTE PARA DEJAR FUERA UNA OFERTA ES S | X66: 51141725 | Y66: 77.337.544-5 | Z66: Se adjunta cotización detallada, Contacto F. 225104550, contacto@scmpharma.cl, Despacho sin costo, Envio 7 dias- monto mínimo de despacho $ 100.000.- Cotización valida por 15 días.
A67: 1057402-3005-AG24 | B67: 45376 | C67: (FAR) SUEROS Y ALCOHOLES MARZO / ALCOHOL ISOPROPILICO LT | D67: PEDIDO SUEROS Y ALCOHOLES MARZO. ADQUISICIÓN VÍA COMPRA ÁGIL. FLETE CARGO DEL PROVEEDOR. REF 1057402-462-COT24. | E67: 242500 | F67: 0 | G67: 55000 | H67: 56525 | I67: 354025 | J67: Bienes y Servicios | K67: WINKLER LIMITADA | L67: 79.722.860-5 | M67: ELABORACION DE OTROS PRODUCTOS ALIMENTICIOS NO CLASIFICADOS EN OTRA PA| VENTA AL POR MAYOR DE PRODUCTOS QUIMICOS| VENTA AL POR MAYOR DE OTROS PRODUCTOS N.C.P. | N67: Grande | O67: Región Metropolitana de Santiago | P67: 12191601 | Q67: ALCOHOL ISOPROPILICO LT. PUREZA x C.G 99.96% - HUMEDAD s/KF 0.019000% - P.ESPECIFICOS 20°C 0.7865 g/cc - ACIDEZ 0.0009% - COLOR APHA 3 - RANGO DESTILACION(°C) 81°-83°C - MAT.NO VOLATIL 0.4 m/g/100ml - ASPECTOS :LIQUIDO INCOLORO TRANSPARENTE. | R67: 50 | S67: Frasco | T67: 4850 | U67: 242500 | V67: 1057402-462-COT24 | W67: SE REQUIERE PARA EL HOSPITAL CLÍNICO DE MAGALLANES ALCOHOL ISOPROPILICO LT. INDICAR: VALOR UNITARIO, PRESENTACIÓN Y EMPAQUE (ML), FECHA VCTO (SUPERIOR 1 AÑO), ADJUNTAR FICHA TÉCNICA Y/O REGISTRO ISP, IMAGEN DEL PRODUCTO, TIEMPO DE ENTREGA (ESPECIFICAR, PARA COORDINAR RETIRO CARGO HOSPITAL DE SER NECESARIO), E INDICAR SI CUENTA CON STOCK PARA DESPACHO INMEDIATO. NO SE CONSIDERARÁN OFERTAS QUE INDIQUEN VALOR REFERENCIAL $0 Ó $1 U OMITAN INFORMACIÓN. | X67: 12191601 | Y67: 79.722.860-5 | Z67: SE ADJUNTA COTIZACIÓN 495755. PLAZO ENTREGA 5 DÍAS HÁBILES FECHA RECEPCIÓN OC.
A68: 1058012-4840-AG25 | B68: 45661 | C68: COMPRA FARMACIA DOSIS UNITARIA/ TETRABENAZINA 25 MG CM | D68: PEDIDO COMPRA FARMACIA DOSIS UNITARIA. COMPRA AGIL DESPACHO AEREO CARGO DEL PROVEEDOR. 1058012-166-COT25 100004940 | E68: 567600 | F68: 0 | G68: 0 | H68: 107844 | I68: 675444 | J68: Fármarcos | K68: NOVOFARMA SERVICE S A | L68: 96.945.670-2 | M68: SERVICIOS DE ALMACENAMIENTO Y DEPOSITO| OTRAS ACTIVIDADES EMPRESARIALES N.C.P. | N68: Grande | O68: Región Metropolitana de Santiago | P68: 51142601 | Q68: TETRABENAZINA 25 MG CM | R68: 120 | S68: Comprimido | T68: 4730 | U68: 567600 | V68: 1058012-166-COT25 | W68: EL HOSPITAL CLÍNICO DE MAGALLANES REQUIERE DE FORMA URGENTE TETRABENAZINA 25 MG CM. INDICAR AL COTIZAR: VALOR UNITARIO TOTAL, PRESENTACIÓN (ML), FECHA VCTO, ADJUNTAR FICHA TÉCNICA Y/O REGISTRO ISP, TIPO DE TRASLADO y ESPECIFICAR FECHA DE ENTREGA EN NUESTRAS BODEGAS, NO DE DESPACHO DEL PRODUCTO. POSTULAR SOLO SI CUENTA CON STOCK PARA DESPACHO INMEDIATO. SE DESESTIMARÁ OFERTA QUE INDIQUE VALOR REFERENCIAL $0 o $1, O QUE NO CUMPLAN CON LO SOLICITADO EN ESPECIAL LA FECHA DE ENTREGA Y NO DE DESP | X68: 51142601 | Y68: 96.945.670-2 | Z68: AX1013400-TETMODIS 25 MG-F-18504 / 21-TETRABENAZINA-FRASCO 112 COMPRIMIDOS-ALMACENADO A NO MÁS DE 25°C PROTEGIDO DE LA LUZ-SE ADJUNTA DOCUMENTACIÓN TÉCNICA, CERTIFICADO DE FARMACOVIGILANCIA Y CONDICIONES DE VENTA. VENCE:JUN 2026
A69: 1057402-14950-AG25 | B69: 45750 | C69: (FAR) ANTISEPTICOS Y DESINFENCTANTES FEBRERO / CLORHEXIDINA 2% TINTURA 125 ML | D69: PEDIDO (FAR) ANTISEPTICOS Y DESINFENCTANTES FEBRERO. ADQUISICIÓN VÍA COMPRA ÁGIL. DESPACHO 15 DÍAS SEGÚN COTIZACIÓN. REF 1057402-295-COT25. | E69: 681450 | F69: 0 | G69: 0 | H69: 129475.5 | I69: 810925.5 | J69: Bienes y Servicios | K69: HOSPITALIA PRODUCTOS MEDICOS LTDA | L69: 78.233.420-4 | M69: VENTA AL POR MAYOR DE OTROS PRODUCTOS N.C.P. | N69: Grande | O69: Región Metropolitana de Santiago | P69: 42281601 | Q69: CLORHEXIDINA 2% TINTURA ( BASE ALCOHOLICA ) 125 ML | R69: 150 | S69: Unidad | T69: 4543 | U69: 681450 | V69: 1057402-295-COT25 | W69: EL HOSPITAL CLÍNICO DE MAGALLANES REQUIERE CLORHEXIDINA 2% TINTURA ( BASE ALCOHOLICA ) 125 ML. INDICAR AL COTIZAR: VALOR UNITARIO TOTAL, PRESENTACIÓN (ML), FECHA VCTO, ADJUNTAR FICHA TÉCNICA Y/O REGISTRO ISP, TIPO DE TRASLADO y ESPECIFICAR FECHA DE ENTREGA, INDICAR SI CUENTA CON STOCK PARA DESPACHO INMEDIATO. SE DECLARARA INADMISIBLE OFERTA QUE INDIQUE VALOR REFERENCIAL $0 o $1, U OMITAN INFORMACIÓN Y DOCUMENTOS TÉCNICOS. | X69: 42281601 | Y69: 78.233.420-4 | Z69: Cotización Hospitalia. Factor de empaque cartón x 30 unidades. Código BRRI004 Se adjunta ficha técnica para su evaluación. Favor tomar en consideración factor de empaque y cotización adjunta. Despacho 15 días - solo mié - Favor considerar Venc: Sept/2026
A70: 1057402-26315-AG25 | B70: 45866 | C70: (FAR) PEDIATRIA HCM / GLICERINA LIQUIDA USP | D70: PEDIDO (FAR) PEDIATRIA HCM ADQUISICION A TRAVES DE COMPRA AGIL DESPACHO 24 A 48 HORAS CARGO DEL PROVEEDOR REF: 1057402-1107-COT25 | E70: 135000 | F70: 0 | G70: 0 | H70: 25650 | I70: 160650 | J70: Bienes y Servicios | K70: VERDEJO Y VERDEJO LIMITADA | L70: 79.591.440-4 | M70: VENTAS AL POR MENOR DE OTROS PRODUCTOS EN ALMACENES ESPECIALIZADOS N.C | N70: Pequeña | O70: Región Metropolitana de Santiago | P70: 51171608 | Q70: GLICERINA LIQUIDA USP LT. | R70: 30 | S70: Litro | T70: 4500 | U70: 135000 | V70: 1057402-1107-COT25 | W70: EL HCM REQUIERE GLICERINA LIQUIDA USP. INDICAR FECHA DE ENTREGA EN BODEGA HCM, FACTOR EMPAQUE, FECHA VCTO, ADJUNTAR FICHA TÉCNICA Y/O REGISTRO ISP, TIPO DE TRASLADO. POSTULAR SOLO SI CUENTA CON STOCK PARA DESPACHO INMEDIATO. COMPRA SUJETA A MULTA DE NO RESPETAR FECHA ESTIMADA DE ENTREGA. SE DESESTIMARÁ OFERTA QUE INDIQUE VALOR REFERENCIAL $1, O QUE SOBREPASE EL VALOR DEL MONTO ESTIMADO O NO CUMPLA CON LOS DIAS Y DOC. SOLICITADOS. | X70: 51171608 | Y70: 79.591.440-4 | Z70: GLICERINA LIQUIDA USP
A71: 1058012-7163-AG25 | B71: 45805 | C71: FARMACIA DOSIS UNITARIA MAYO/ FITOMENADIONA 10 MG ML ADMINISTRACIÓN vía EV | D71: PEDIDO FARMACIA DOSIS UNITARIA MAYO. COMPRA AGIL DESPACHO AEREO CARGO DEL PROVEEDOR. 1058012-326-COT25 | E71: 435900 | F71: 0 | G71: 0 | H71: 82821 | I71: 518721 | J71: Fármarcos | K71: SERVICIOS FARMACEUTICOS Y DE SALUD QAFARMA SPA | L71: 78.045.809-7 | N71: NoClasificado | O71: Región Metropolitana de Santiago | P71: 51191905 | Q71: FITOMENADIONA 10 MG ML ADMINISTRACIÓN vía EV (endovenoso) | R71: 100 | S71: Ampolla | T71: 4359 | U71: 435900 | V71: 1058012-326-COT25 | W71: EL HOSPITAL CLÍNICO DE MAGALLANES REQUIERE FITOMENADIONA 10 MG ML ADMINIS. INDICAR AL COTIZAR: VALOR UNITARIO TOTAL, PRESENTACIÓN (ML), FECHA VCTO, ADJUNTAR FICHA TÉCNICA Y/O REGISTRO ISP, TIPO DE TRASLADO y ESPECIFICAR FECHA DE ENTREGA EN NUESTRAS BODEGAS, NO DE DESPACHO DEL PRODUCTO. POSTULAR SOLO SI CUENTA CON STOCK PARA DESPACHO INMEDIATO. COMPRA SUJETA A MULTA POR NO RESPETAR FECHA ESTIMADA DE ENTREGA DE LA OC. SE DESESTIMARÁ OFERTA QUE INDIQUE VALOR $0 o $1, O NO CUMPLAN CON LO SOLICITADO | X71: 51191905 | Y71: 78.045.809-7 | Z71: Detalles en cotización adjunta, OC mínima $100.000, despacho sin costo extra en 48- 72 horas una vez aceptada la OC, correo qa.farmavidda@gmail.com CONSULTAS: +56946283996 Tamara Acuña
A72: 1058012-631-AG24 | B72: 45364 | C72: COMPRA ALTERNATIVA FALTA CENABAST FEBRERO / VITAMINAS A-C-D FRA GOTAS | D72: COMPRA ALTERNATIVA POR FALTA DE STOCK EN PROVEEDOR N° ORDEN 1058012-415-SE24. ADQUISICIÓN VÍA COMPRA ÁGIL. FLETE CARGO DEL PROVEEDOR. ZGEN 100001058. REF 1058012-196-COT24. | E72: 88200 | F72: 0 | G72: 0 | H72: 16758 | I72: 104958 | J72: Fármarcos | K72: ETHON PHARMACEUTICALS COMERCIALIZADORA IMP EXP Y DIST SPA | L72: 76.956.140-4 | M72: VENTA AL POR MAYOR DE ARTICULOS DE PERFUMERIA, COSMETICOS, JABONES Y P| VENTA AL POR MAYOR DE PRODUCTOS FARMACEUTICOS| VENTA AL POR MAYOR DE PRODUCTOS QUIMICOS | N72: Grande | O72: Región del Libertador General Bernardo O´Higgins | P72: 51191905 | Q72: VITAMINA A-C-D FRA GOTAS | R72: 21 | S72: Frasco | T72: 4200 | U72: 88200 | V72: 1058012-196-COT24 | W72: EL HOSPITAL CLÍNICO DE MAGALLANES REQUIERE VITAMINA A-C-D FRA GOTAS. INDICAR AL COTIZAR: VALOR UNITARIO TOTAL, PRESENTACIÓN (ML), FECHA VCTO, ADJUNTAR FICHA TÉCNICA Y/O REGISTRO ISP, TIPO DE TRASLADO CARGO PROVEEDOR (ESPECIFICAR, PARA ACORDAR RETIRO CARGO HOSPITAL DE SER NECESARIO), E INDICAR SI CUENTA CON STOCK PARA DESPACHO INMEDIATO. SE DESESTIMARÁ OFERTA QUE INDIQUE VALOR REFERENCIAL $0 o $1, U OMITAN INFORMACIÓN. | X72: 51191905 | Y72: 76.956.140-4 | Z72: VITAMINA ACD / 30ML SOLUCION ORAL. LABORATORIO CHILE. VITAMINA A-C-D. REG ISP F-21649. VCTO 11-2025 Entrega en 48 horas una vez aceptada la orden de compra. Monto mínimo de compra 50.000 neto Sin costo por despacho. Vigencia de cotización 60 días.
A73: 1058012-7700-AG25 | B73: 45907 | C73: MEDICAMENTO ONCOLOGÍA Y FARMACIA AMBULATORIA JULIO / GEL VISCOSO COADYUVANTE | D73: PEDIDO MEDICAMENTO ONCOLOGÍA Y FARMACIA AMBULATORIA JULIO. ADQUISICIÓN VÍA COMPRA ÁGIL. DESPACHO 3 DÍAS CARGO DEL PROVEEDOR SEGÚN COTIZACIÓN. REF 1058012-454-COT25. | E73: 824100 | F73: 0 | G73: 0 | H73: 156579 | I73: 980679 | J73: Fármarcos | K73: LABORATORIO C&D PHARMA LIMITADA | L73: 76.394.174-4 | M73: VENTA AL POR MAYOR DE PRODUCTOS FARMACEUTICOS | N73: Mediana | O73: Región Metropolitana de Santiago | P73: 51142148 | Q73: GEL VISCOSO COADYUVANTE EN TRATAMIENTO DE LESIONES DE LA MUCOSA BUCAL QUE CONTIENE: HIALURONATO DE SODIO, ÁCIDO GLICIRRETÍNICO, POLIVINILPIRROLIDON A (PVP), MALTODEXTRINA, PROPILENGLICOL | R73: 201 | S73: Sachet | T73: 4100 | U73: 824100 | V73: 1058012-454-COT25 | W73: EL HOSPITAL CLÍNICO DE MAGALLANES REQUIERE GEL VISCOSO COADYUVANTE. INDICAR AL COTIZAR: VALOR UNITARIO TOTAL, PRESENTACIÓN (UD), FECHA VCTO, ADJUNTAR FICHA TÉCNICA Y/O REGISTRO ISP, TIPO DE TRASLADO (ESPECIFICAR, PARA ACORDAR RETIRO CARGO HOSPITAL DE SER NECESARIO), E INDICAR SI CUENTA CON STOCK PARA DESPACHO INMEDIATO. SE DECLARARÁ INADMISIBLE OFERTA QUE INDIQUE VALOR REFERENCIAL $0 o $1, U OMITAN INFORMACIÓN SOLICITADA. | X73: 51142148 | Y73: 76.394.174-4 | Z73: GELCLAIR® GEL ORAL CONCENTRADO PARA LA RESTAURACIÓN DE MUCOSA ORAL. COMPOSICIÓN: HIALURONATO DE SODIO, ACIDO GLICIRETÍNICO, POLIVINIL PIRROLIDONA (PVP). CJ X 3 SACHET. CERTIFICACIÓN EMA, FABRICADO BAJO NORMA ISO 13485:2016. PERIODO DE EFICACIA 36 MESES.
A74: 1058012-4605-AG25 | B74: 45811 | C74: PEDIDO FARMACIA DOSIS UNITARIA/FITOMENADIONA 10 MG ML ADMINISTRACIÓN vía EV | D74: PEDIDO FARMACIA DOSIS UNITARIA. COMPRA AGIL DESPACHO CARGO DEL PROVEEDOR. 1058012-129-COT25 | E74: 1628000 | F74: 0 | G74: 0 | H74: 309320 | I74: 1937320 | J74: Fármarcos | K74: LABORATORIO ACONFAR CHILE LIMITADA | L74: 76.125.564-9 | M74: SERVICIOS DE ENVASADO Y EMPAQUE| OTROS PROFESIONALES DE LA SALUD| OTRAS ACTIVIDADES EMPRESARIALES RELACIONADAS CON LA SALUD HUMANA | N74: Pequeña | O74: Región Metropolitana de Santiago | P74: 85121902 | Q74: FITOMENADIONA 10 MG ML ADMINISTRACIÓN I.V. | R74: 400 | S74: Ampolla | T74: 4070 | U74: 1628000 | V74: 1058012-129-COT25 | W74: EL HOSPITAL CLÍNICO DE MAGALLANES REQUIERE FITOMENADIONA 10 MG ML ADMINISTRACIÓN I.V. INDICAR AL COTIZAR: VALOR UNITARIO TOTAL, PRESENTACIÓN (AM), FECHA VCTO, ADJUNTAR FICHA TÉCNICA Y/O REGISTRO ISP, TIPO DE TRASLADO CARGO PROVEEDOR (ESPECIFICAR, PARA ACORDAR RETIRO CARGO HOSPITAL DE SER NECESARIO), E INDICAR SI CUENTA CON STOCK PARA DESPACHO INMEDIATO. SE DESESTIMARÁ OFERTA QUE INDIQUE VALOR REFERENCIAL $0 o $1, U OMITAN INFORMACIÓN Y DOCUMENTOS SOLICITADOS. | X74: 85121902 | Y74: 76.125.564-9 | Z74: FACTURACIÓN MÍNIMA $50.000+IVA PARA SANTIAGO Y $75.000+IVA PARA REGIONES,DESPACHO:STGO 24-48 HR Y REGIONES 48-72 HR, FLETE ADICIONAL SOLO SUEROS X VOLUMEN,UNIDAD MIN. COTIZADA, SE AJUSTARÁ A FACTOR DE EMPAQUE, REG.ISP, FACTURA ELECTRÓNICA.
A75: 1057402-938-AG24 | B75: 45321 | C75: (FAR) ANTIS Y DESINF FEBRERO / CLORHEXIDINA 2% ACUOSA TOPICA 500 ML | D75: PEDIDO ANTIS Y DESINF FEBRERO. ADQUISICIÓN VÍA COMPRA ÁGIL. FLETE CARGO DEL PROVEEDOR. REF 1057402-144-COT24 | E75: 1124200 | F75: 0 | G75: 0 | H75: 213598 | I75: 1337798 | J75: Bienes y Servicios | K75: DIFEM LABORATORIOS S A | L75: 79.581.120-6 | M75: FABRICACION DE PRODUCTOS FARMACEUTICOS, SUSTANCIAS QUIMICAS MEDICINALE| FABRICACIONES DE JABONES Y DETERGENTES, PREPARADOS PARA LIMPIAR, PERFU | N75: Grande | O75: Región Metropolitana de Santiago | P75: 51102707 | Q75: CLORHEXIDINA 2% ACUOSA TOPICA 500 ML | R75: 280 | S75: Unidad | T75: 4015 | U75: 1124200 | V75: 1057402-144-COT24 | W75: SE REQUIERE PARA EL HOSPITAL CLÍNICO DE MAGALLANES CLORHEXIDINA 2% ACUOSA TOPICA 500 ML. INDICAR: VALOR UNITARIO, PRESENTACIÓN Y EMPAQUE (ML), FECHA VCTO (SUPERIOR 1 AÑO), ADJUNTAR FICHA TÉCNICA Y/O REGISTRO ISP, IMAGEN DEL PRODUCTO, TIEMPO DE ENTREGA (ESPECIFICAR, PARA COORDINAR RETIRO CARGO HOSPITAL DE SER NECESARIO), E INDICAR SI CUENTA CON STOCK PARA DESPACHO INMEDIATO. NO SE CONSIDERARÁN OFERTAS QUE INDIQUEN VALOR REFERENCIAL $0 Ó $1 U OMITAN INFORMACIÓN. | X75: 51102707 | Y75: 79.581.120-6 | Z75: Dichlorexan Solución Acuosa 2% 500cc. Marca DIFEM, procedencia nacional. Sin alcohol, para antisepsia de piel. Registro ISP. Estudio microb según resolución 89. Con inserto dosificador. Vig 18 meses. Cajas x 20 unidades. vencimiento 05/25.
A76: 1058012-7754-AG25 | B76: 45859 | C76: COMPRA ALTERNATIVA URGENTE STOCK CRÍTICO FARMACIA AMBULATORIA JULIO / ENOXAPARINA SODICA 80 MG 0,8 ML | D76: COMPRA ALTERNATIVA POR FALTA DE STOCK EN PROVEEDOR OC N° 1058012-7612-SE25. ADQUISICIÓN VÍA COMPRA ÁGIL. DESPACHO 5 A 7 DÍAS HÁBILES CARGO DEL PROVEEDOR SEGÚN COTIZACIÓN. ZGEN 100000553. REF 1058012-464-COT25. | E76: 600000 | F76: 0 | G76: 0 | H76: 114000 | I76: 714000 | J76: Fármarcos | K76: INVERSIONES PHARMAVISAN SOCIEDAD ANONIMA | L76: 76.055.804-4 | M76: VENTA AL POR MENOR DE PRODUCTOS MEDICINALES| VENTAS AL POR MENOR DE OTROS PRODUCTOS EN ALMACENES ESPECIALIZADOS N.C | N76: Grande | O76: Región Metropolitana de Santiago | P76: 51131607 | Q76: ENOXAPARINA SODICA 80 MG 0,8 ML | R76: 150 | S76: Unidad | T76: 4000 | U76: 600000 | V76: 1058012-464-COT25 | W76: EL HOSPITAL CLÍNICO DE MAGALLANES REQUIERE ENOXAPARINA SODICA 80 MG 0,8 ML. INDICAR AL COTIZAR: VALOR UNITARIO TOTAL, PRESENTACIÓN (UD), FECHA VCTO, ADJUNTAR FICHA TÉCNICA Y/O REGISTRO ISP, TIPO DE TRASLADO (ESPECIFICAR, PARA ACORDAR RETIRO CARGO HOSPITAL DE SER NECESARIO), E INDICAR SI CUENTA CON STOCK PARA DESPACHO INMEDIATO. SE DECLARARÁ INADMISIBLE OFERTA QUE INDIQUE VALOR REFERENCIAL $1, U OMITAN INFORMACIÓN Y DOCUMENTOS SOLICITADOS. | X76: 51131607 | Y76: 76.055.804-4 | Z76: Se adjunta cotización solicitada en base a stock disponible para despacho en 5-7 días hábiles, una vez aceptada la OC, monto mínimo de despacho $150.000 netos y servicio de post venta. Vanessa Sandoval Correo: licitaciones@pharmavisan.cl Fono:223039414.
A77: 1058012-7844-AG25 | B77: 45867 | C77: COMPRA ALTERNATIVA FARMACIA DU JULIO / ENOXAPARINA SODICA 80 MG 0,8 ML JGA | D77: COMPRA ALTERNATIVA POR FALTA DE STOCK EN PROVEEDOR OC N° 1058012-7698-SE25. ADQUISICIÓN VÍA COMPRA ÁGIL. DESPACHO 7 DÍAS HÁBILES CARGO DEL PROVEEDOR SEGÚN COTIZACIÓN. ZGEN 100000553. REF 1058012-490-COT25. | E77: 2399400 | F77: 0 | G77: 0 | H77: 455886 | I77: 2855286 | J77: Fármarcos | K77: INVERSIONES PHARMAVISAN SOCIEDAD ANONIMA | L77: 76.055.804-4 | M77: VENTA AL POR MENOR DE PRODUCTOS MEDICINALES| VENTAS AL POR MENOR DE OTROS PRODUCTOS EN ALMACENES ESPECIALIZADOS N.C | N77: Grande | O77: Región Metropolitana de Santiago | P77: 51131607 | Q77: ENOXAPARINA SODICA 80 MG 0,8 ML JGA | R77: 600 | S77: Unidad | T77: 3999 | U77: 2399400 | V77: 1058012-490-COT25 | W77: EL HOSPITAL CLÍNICO DE MAGALLANES REQUIERE ENOXAPARINA SODICA 80 MG. INDICAR AL COTIZAR: VALOR UNITARIO TOTAL, PRESENTACIÓN (UD), FECHA VCTO, ADJUNTAR FICHA TÉCNICA Y/O REGISTRO ISP, TIPO DE TRASLADO Y FECHA ESPECIFICA DE ENTREGA (ESPECIFICAR, PARA ACORDAR RETIRO CARGO HOSPITAL DE SER NECESARIO), E INDICAR SI CUENTA CON STOCK PARA DESPACHO INMEDIATO. SE DECLARARÁ INADMISIBLE OFERTA QUE INDIQUE VALOR REFERENCIAL $0 o $1, U OMITAN INFORMACIÓN Y DOCUMENTOS SOLICITADOS | X77: 51131607 | Y77: 76.055.804-4 | Z77: Se adjunta cotización solicitada en base a stock disponible para despacho en 5-7 días hábiles, una vez aceptada la OC, monto mínimo de despacho $150.000 netos y servicio de post venta. Claudia Pérez Correo: licitaciones@pharmavisan.cl Fono:223039416
A78: 1058012-1127-AG24 | B78: 45426 | C78: FARMACIA FALTA PROGRAMA VIH MAYO / BICTEGRAVIR/EMTRICITAVINA/TENOFOVIR ALAFEMNAMIDA 50/200/25 MG CM | D78: PEDIDO FARMACIA [FALTA PROGRAMA VIH] MAYO. ADQUISICIÓN VÍA COMPRA ÁGIL. FLETE CARGO DEL PROVEEDOR. REF 1058012-351-COT24. | E78: 1624140 | F78: 0 | G78: 0 | H78: 308586.6 | I78: 1932726.6 | J78: Fármarcos | K78: GADOR LIMITADA | L78: 76.084.945-6 | M78: FABRICACION DE PRODUCTOS FARMACEUTICOS, SUSTANCIAS QUIMICAS MEDICINALE| FABRICACION DE OTROS PRODUCTOS QUIMICOS N.C.P.| FABRICACION DE EQUIPO MEDICO Y QUIRURGICO, Y DE APARATOS ORTOPEDICOS| VENTA AL POR MAYOR DE OTROS PRODUCTOS N.C.P. | N78: Grande | O78: Región Metropolitana de Santiago | P78: 85121902 | Q78: BICTEGRAVIR /EMTRICITABINA /TENOFOVIR ALAFENAMIDA FUMARATO 50/200/25 MG CM | R78: 420 | S78: Comprimido | T78: 3867 | U78: 1624140 | V78: 1058012-351-COT24 | W78: EL HOSPITAL CLÍNICO DE MAGALLANES REQUIERE BICTEGRAVIR-EMTRICITA-VINATENOFOVIR-ALAFEMNAMIDA 50/200/25 MG CM. INDICAR AL COTIZAR: VALOR UNITARIO TOTAL, PRESENTACIÓN (CM), FECHA VCTO, ADJUNTAR FICHA TÉCNICA Y/O REGISTRO ISP, TIPO DE TRASLADO CARGO PROVEEDOR (ESPECIFICAR, PARA ACORDAR RETIRO CARGO HOSPITAL DE SER NECESARIO), E INDICAR SI CUENTA CON STOCK PARA DESPACHO INMEDIATO. SE DESESTIMARÁ OFERTA QUE INDIQUE VALOR REFERENCIAL $0 o $1, U OMITAN INFORMACIÓN. | X78: 85121902 | Y78: 76.084.945-6 | Z78: BIKTARVY, BICTEGRAVIR 50 mg-EMTRICITABINA 200mg-TENOFOVIR ALAFENAMIDA 25 mg contiene 30 comprimidos recubiertos. REG ISP: F-24969-19 Plazo entrega: 5 días hábiles desde aceptada la OC, sin canje, sin monto mínimo despacho. Vencimiento:30-12-2025.
A79: 1058012-6776-AG25 | B79: 45763 | C79: FARMACIA DOSIS UNITARIA ABRIL / FITOMENADIONA 10 MG ML ADMINISTRACIÓN vía EV | D79: PEDIDO STOCK CRÍTICO F. DOSIS UNITARIA. COMPRA AGIL DESPACHO CARGO DEL PROVEEDOR. 1058012-210-COT25 | E79: 1110000 | F79: 0 | G79: 0 | H79: 210900 | I79: 1320900 | J79: Fármarcos | K79: LABORATORIO ACONFAR CHILE LIMITADA | L79: 76.125.564-9 | M79: SERVICIOS DE ENVASADO Y EMPAQUE| OTROS PROFESIONALES DE LA SALUD| OTRAS ACTIVIDADES EMPRESARIALES RELACIONADAS CON LA SALUD HUMANA | N79: Pequeña | O79: Región Metropolitana de Santiago | P79: 51191905 | Q79: FITOMENADIONA 10 MG ML ADMINISTRACIÓN I.V. | R79: 300 | S79: Ampolla | T79: 3700 | U79: 1110000 | V79: 1058012-210-COT25 | W79: EL HOSPITAL CLÍNICO DE MAGALLANES REQUIERE FITOMENADIONA 10 MG ML ADMINIS. INDICAR AL COTIZAR: VALOR UNITARIO TOTAL, PRESENTACIÓN (ML), FECHA VCTO, ADJUNTAR FICHA TÉCNICA Y/O REGISTRO ISP, TIPO DE TRASLADO y ESPECIFICAR FECHA DE ENTREGA EN NUESTRAS BODEGAS, NO DE DESPACHO DEL PRODUCTO. POSTULAR SOLO SI CUENTA CON STOCK PARA DESPACHO INMEDIATO. COMPRA SUJETA A MULTA POR NO RESPETAR FECHA ESTIMADA DE ENTREGA DE LA OC. SE DESESTIMARÁ OFERTA QUE INDIQUE VALOR $0 o $1, O NO CUMPLAN CON LO SOLICITADO | X79: 51191905 | Y79: 76.125.564-9 | Z79: JT-FACTURACION MINIMA $50.000+IVA PARA SANTIAGO Y $75.000+IVA PARA REGIONES, DESPACHO: STGO 24-48 HR Y REGIONES 48-72 HRS, FLETE ADICIONALSOLO SUEROS X VOLUMEN, UNIDAD MIN. COTIZADA, SE AJUSTARÁ A FACTOR DE EMPAQUE, REG.ISP, FACT.ELECTRONICA.
A80: 1058012-7010-AG25 | B80: 45905 | C80: PEDIDO FARMACIA DOSIS UNITARIA/ MUPIROCINA 2% TOPICO | D80: PEDIDO STOCK CRÍTICO F. DOSIS UNITARIA. COMPRA AGIL DESPACHO CARGO DEL PROVEEDOR. 1058012-286-COT25 | E80: 72600 | F80: 0 | G80: 0 | H80: 13794 | I80: 86394 | J80: Fármarcos | K80: LABORATORIO ACONFAR CHILE LIMITADA | L80: 76.125.564-9 | M80: SERVICIOS DE ENVASADO Y EMPAQUE| OTROS PROFESIONALES DE LA SALUD| OTRAS ACTIVIDADES EMPRESARIALES RELACIONADAS CON LA SALUD HUMANA | N80: Pequeña | O80: Región Metropolitana de Santiago | P80: 51101597 | Q80: MUPIROCINA 2% TOPICO | R80: 20 | S80: Unidad | T80: 3630 | U80: 72600 | V80: 1058012-286-COT25 | W80: EL HCM REQUIERE MUPIROCINA 2% TOPICO. INDICAR FECHA DE ENTREGA EN BODEGA HCM, FACTOR EMPAQUE, FECHA VCTO, ADJUNTAR FICHA TÉCNICA Y/O REGISTRO ISP, TIPO DE TRASLADO. POSTULAR SOLO SI CUENTA CON STOCK PARA DESPACHO INMEDIATO. COMPRA SUJETA A MULTA DE NO RESPETAR FECHA ESTIMADA DE ENTREGA. SE DESESTIMARÁ OFERTA QUE INDIQUE VALOR REFERENCIAL $0 o $1. SE DEJARA INADMISIBLE LA OFERTA QUE SOBREPASE EL VALOR DEL MONTO ESTIMADO O NO CUMPLA CON LOS DIAS Y DOC. SOLICITADOS. | X80: 51101597 | Y80: 76.125.564-9 | Z80: MONTO MÍNIMO DE FACTURACION $50.000+IVA PARA SANTIAGO Y $ 75.000+IVA PARA REGIONES. DESPACHO: DE 24 HORAS, CONTAMOS CON FACTURA ELECTRÓNICA.TODOS NUESTROS PRODUCTOS CUENTAN CON REGISTRO ISP. FLETE SIN RECARGO.GARANTIZAMOS SERVICIO DE POST-VENTA.
A81: 1058012-1111-AG24 | B81: 45540 | C81: FARMACIA AMBULATORIA MAYO / FAMPRIDINA 10 MG CM | D81: PEDIDO FARMACIA AMBULATORIA MAYO. ADQUISICIÓN VÍA COMPRA ÁGIL. FLETE CARGO DEL PROVEEDOR. REF 1058012-324-COT24. | E81: 589176 | F81: 0 | G81: 0 | H81: 111943.44 | I81: 701119.44 | J81: Fármarcos | K81: BIOGEN CHILE SPA | L81: 76.099.774-9 | M81: VENTA AL POR MAYOR DE PRODUCTOS FARMACEUTICOS| SOCIEDADES DE INVERSION Y RENTISTAS DE CAPITALES MOBILIARIOS EN GENERA| ACTIVIDADES DE INVESTIGACION | N81: Grande | O81: Región Metropolitana de Santiago | P81: 85121902 | Q81: FAMPRIDINA 10 MG CM | R81: 168 | S81: Comprimido | T81: 3507 | U81: 589176 | V81: 1058012-324-COT24 | W81: EL HOSPITAL CLÍNICO DE MAGALLANES REQUIERE FAMPRIDINA 10 MG CM. INDICAR AL COTIZAR: VALOR UNITARIO TOTAL, PRESENTACIÓN (CM), FECHA VCTO, ADJUNTAR FICHA TÉCNICA Y/O REGISTRO ISP, TIPO DE TRASLADO CARGO PROVEEDOR (ESPECIFICAR, PARA ACORDAR RETIRO CARGO HOSPITAL DE SER NECESARIO), E INDICAR SI CUENTA CON STOCK PARA DESPACHO INMEDIATO. SE DESESTIMARÁ OFERTA QUE INDIQUE VALOR REFERENCIAL $0 o $1, U OMITAN INFORMACIÓN. | X81: 85121902 | Y81: 76.099.774-9 | Z81: Oferta de Biogen Chile SpA por Fampridina 10 mg. Precio neto por comprimido: 3.507 CLP Sin IVA. Unidad mínima de despacho corresponde a 1 caja con 56 comprimidos. Incluye despacho. Registro ISP F-19932/23 Vencimiento 31-03-2026
A82: 1058012-6769-AG25 | B82: 45762 | C82: COMPRA ALTERNATIVA FARMACIA AMBULATORIA ABRIL / LEVOCETIRIZINA 5 MG ML GTS | D82: COMPRA ALTERNATIVA POR FALTA DE STOCK EN PROVEEDOR OC N° 1058012-6697-SE25. ADQUISICIÓN VÍA COMPRA ÁGIL. DESPACHO 7 DÍAS CARGO DEL PROVEEDOR SEGÚN COTIZACIÓN. ZGEN 100005295. REF 1058012-216-COT25 | E82: 350400 | F82: 0 | G82: 0 | H82: 66576 | I82: 416976 | J82: Fármarcos | K82: SCM PHARMA SPA | L82: 77.337.544-5 | M82: VENTA AL POR MAYOR DE PRODUCTOS FARMACEUTICOS Y MEDICINALES | N82: Mediana | O82: Región Metropolitana de Santiago | P82: 51161615 | Q82: LEVOCETIRIZINA 5 MG ML GTS | R82: 100 | S82: Frasco | T82: 3504 | U82: 350400 | V82: 1058012-216-COT25 | W82: EL HOSPITAL CLÍNICO DE MAGALLANES REQUIERE LEVOCETIRIZINA 5 MG ML GTS. INDICAR AL COTIZAR: VALOR UNITARIO TOTAL, PRESENTACIÓN (ML), FECHA VCTO, ADJUNTAR FICHA TÉCNICA Y/O REGISTRO ISP, TIPO DE TRASLADO (ESPECIFICAR, PARA ACORDAR RETIRO CARGO HOSPITAL DE SER NECESARIO), E INDICAR SI CUENTA CON STOCK PARA DESPACHO INMEDIATO. SE DECLARARÁ INADMISIBLE OFERTA QUE INDIQUE VALOR REFERENCIAL $0 o $1, U OMITAN CUALQUIER INFORMACIÓN SOLICITADA PARA ESTA COTIZACIÓN. | X82: 51161615 | Y82: 77.337.544-5 | Z82: Se adjunta cotización detallada, Contacto F. 225104550, contacto@scmpharma.cl, Despacho sin costo, Envio 7 dias- monto mínimo de despacho $ 100.000.- Cotización valida por 15 días.
A83: 1058012-7372-AG25 | B83: 45906 | C83: FALTA CENABAST/NITROGLICERINA 50MG/10ML SOL. INY. AM/FAM | D83: PEDIDO FRALTA CENABAST. COMPRA AGIL. DESPACHO A CARGO DEL PROVEEDOR. 1058012-375-COT25 | E83: 161100 | F83: 0 | G83: 0 | H83: 30609 | I83: 191709 | J83: Fármarcos | K83: LABORATORIO ACONFAR CHILE LIMITADA | L83: 76.125.564-9 | M83: SERVICIOS DE ENVASADO Y EMPAQUE| OTROS PROFESIONALES DE LA SALUD| OTRAS ACTIVIDADES EMPRESARIALES RELACIONADAS CON LA SALUD HUMANA | N83: Pequeña | O83: Región Metropolitana de Santiago | P83: 51121603 | Q83: NITROGLICERINA 50MG/10ML SOL. INY. AM/FAM | R83: 50 | S83: Frasco Ampolla | T83: 3222 | U83: 161100 | V83: 1058012-375-COT25 | W83: EL HCM REQUIERE NITROGLICERINA 50MG/10ML SOL. INY. AM/FAM. INDICAR FECHA DE ENTREGA EN BODEGA HCM, FACTOR EMPAQUE, FECHA VCTO, ADJUNTAR FICHA TÉCNICA Y/O REGISTRO ISP, TIPO DE TRASLADO. POSTULAR SOLO SI CUENTA CON STOCK PARA DESPACHO INMEDIATO. COMPRA SUJETA A MULTA DE NO RESPETAR FECHA ESTIMADA DE ENTREGA. SE DESESTIMARÁ OFERTA QUE INDIQUE VALOR REFERENCIAL $1, O QUE SOBREPASE EL VALOR DEL MONTO ESTIMADO O NO CUMPLA CON LOS DIAS Y DOC. SOLICITADOS. | X83: 51121603 | Y83: 76.125.564-9 | Z83: JOR. FACTURACION MINIMA $50.000+IVA PARA SANTIAGO Y $75.000+IVA PARA REGIONES, DESPACHO: STGO 24-48 HR Y REGIONES 72 HR, UNIDAD MIN. COTIZADA, SE AJUSTARÁ A FACTOR DE EMPAQUE, REG.ISP, FACT.ELECTRONICA. STOCK DISPONIBLE PARA ENTREGA INMEDIATA.
... A101: 1058012-6768-AG25 | B101: 45761 | C101: FALTA CENABAST ABRIL/ TENOFOVIR/LAMIVUDINA/DOLUTEGRAVIR300/300/50 MG CM | D101: PEDIDO FALTA CENABAST ABRIL. COMPRA AGIL DESPACHO AEREO CARGO DEL PROVEEDOR. 100005050 1058012-202-COT25 | E101: 480000 | F101: 0 | G101: 0 | H101: 91200 | I101: 571200 | J101: Fármarcos | K101: PHARMARIS CHILE SPA | L101: 76.418.921-3 | M101: Imp. y Comercializacion Productos Farmaceuticos | N101: Grande | O101: Región Metropolitana de Santiago | P101: 51102332 | Q101: TENOFOVIR/LAMIVUDINA/DOLUTEGRAVIR 300/300/50 MG CM | R101: 300 | S101: Comprimido | T101: 1600 | U101: 480000 | V101: 1058012-202-COT25 | W101: EL HOSPITAL CLÍNICO DE MAGALLANES REQUIERE TENOFOVIR/LAMIVUDINA/DOLUTEGRAV. INDICAR AL COTIZAR: FECHA DE ENTREGA EN BODEGA DEL HCM, PRESENTACIÓN (ML), FECHA VCTO, ADJUNTAR FICHA TÉCNICA Y/O REGISTRO ISP, TIPO DE TRASLADO. POSTULAR SOLO SI CUENTA CON STOCK PARA DESPACHO INMEDIATO. COMPRA SUJETA A MULTA POR NO RESPETAR FECHA ESTIMADA DE ENTREGA DE LA OC. SE DESESTIMARÁ OFERTA QUE INDIQUE VALOR REFERENCIAL $0 o $1, O NO CUMPLAN CON LO SOLICITADO. MOTIVO IPORTANTE PARA DEJAR FUERA UNA OFERTA ES S | X101: 51102332 | Y101: 76.418.921-3 | Z101: ACRIPTEGA: TENOFOVIR/LAMIVUDINA/DOLUTEGRAVIR 300/300/50 MG CM - Envase x 30 CMP Stock disponible - vencimiento mayo 2026 Despacho incluído - 3 días hábiles despues de recibida la OC
A102: 1058012-1949-AG24 | B102: 45543 | C102: PEDIDO FARMACIA DOSIS UNITARIA/CLONIDINA CLORHIDRATO 100 MCG CM | D102: PEDIDO FARMACIA DOSIS UNITARIA. COMPRA AGIL DESPACHO CARGO DEL PROVEEDOR. 1058012-525-COT24 100000394 | E102: 628000 | F102: 0 | G102: 20000 | H102: 123120 | I102: 771120 | J102: Fármarcos | K102: EUROLABS CHILE SPA | L102: 77.528.837-K | N102: Pequeña | O102: Región Metropolitana de Santiago | P102: 51121718 | Q102: CLONIDINA CLORHIDRATO 100 MCG CM | R102: 400 | S102: Comprimido | T102: 1570 | U102: 628000 | V102: 1058012-525-COT24 | W102: EL HOSPITAL CLÍNICO DE MAGALLANES REQUIERE CLONIDINA CLORHIDRATO 100 MCG CM. INDICAR AL COTIZAR: VALOR UNITARIO TOTAL, PRESENTACIÓN (ML), FECHA VCTO, ADJUNTAR FICHA TÉCNICA Y/O REGISTRO ISP, TIPO DE TRASLADO y ESPECIFICAR FECHA DE ENTREGA, INDICAR SI CUENTA CON STOCK PARA DESPACHO INMEDIATO. SE DESESTIMARÁ OFERTA QUE INDIQUE VALOR REFERENCIAL $0 o $1, U OMITAN INFORMACIÓN. | X102: 51121718 | Y102: 77.528.837-K | Z102: Clonidina laboratorio TEVA USA caja por 100 tabletas vencimiento Junio 2026( articulo 21)
A103: 1058012-1781-AG24 | B103: 45495 | C103: (FAR) COMPRA ALTERNATIVA FARMACIA AMBULATORIA JULIO / ÁCIDO TRANEXAMICO 500 MG CM | D103: COMPRA ALTERNATIVA POR FALTA DE STOCK EN PROVEEDOR OC N° 1058012-1575-SE24. ADQUISICIÓN VÍA COMPRA ÁGIL. FLETE 3 DÍAS SEGÚN COTIZACIÓN. ZGEN 100000028. REF 1058012-489-COT24 | E103: 299000 | F103: 0 | G103: 0 | H103: 56810 | I103: 355810 | J103: Fármarcos | K103: EMCURE PHARMA CHILE SPA | L103: 77.240.238-4 | M103: FABRICACION DE PRODUCTOS FARMACEUTICOS, SUSTANCIAS QUIMICAS MEDICINALE | N103: Micro | O103: Región Metropolitana de Santiago | P103: 51131808 | Q103: ÁCIDO TRANEXAMICO 500 MG CM | R103: 200 | S103: Comprimido | T103: 1495 | U103: 299000 | V103: 1058012-489-COT24 | W103: EL HOSPITAL CLÍNICO DE MAGALLANES REQUIERE ÁCIDO TRANEXAMICO 500 MG CM. INDICAR AL COTIZAR: VALOR UNITARIO TOTAL, PRESENTACIÓN (CM), FECHA VCTO, ADJUNTAR FICHA TÉCNICA Y/O REGISTRO ISP, TIPO DE TRASLADO CARGO PROVEEDOR (ESPECIFICAR, PARA ACORDAR RETIRO CARGO HOSPITAL DE SER NECESARIO), E INDICAR SI CUENTA CON STOCK PARA DESPACHO INMEDIATO. SE DESESTIMARÁ OFERTA QUE INDIQUE VALOR REFERENCIAL $0 o $1, U OMITAN INFORMACIÓN. | X103: 51131808 | Y103: 77.240.238-4 | Z103: PAUSE-500 COMPRIMIDOS RECUBIERTOS 500 mg (ÁCIDO TRANEXÁMICO), caja x20, Bioequivalente, Registro ISP: F-26519/21. Incluye despacho en Institución. Stock disponible, entrega en 3 días. Datos de contacto en cotización adjunta.
A104: 1058012-4696-AG25 | B104: 45740 | C104: COMPRA ALTERNATIVA STOCK CRÍTICO FARMACIA AMBULATORIA MARZO / VITAMINA B1/B6/B12 AMP | D104: COMPRA ALTERNATIVA POR FALTA DE STOCK EN OC N° 1058012-4636-SE25. ADQUISICIÓN VÍA COMPRA ÁGIL. DESPACHO 7 DÍAS SEGÚN COTIZACIÓN. REF 1058012-152-COT25. | E104: 292400 | F104: 0 | G104: 0 | H104: 55556 | I104: 347956 | J104: Fármarcos | K104: SCM PHARMA SPA | L104: 77.337.544-5 | M104: VENTA AL POR MAYOR DE PRODUCTOS FARMACEUTICOS Y MEDICINALES | N104: Mediana | O104: Región Metropolitana de Santiago | P104: 51191905 | Q104: VITAMINA B1/B6/B12 AMP | R104: 200 | S104: Ampolla | T104: 1462 | U104: 292400 | V104: 1058012-152-COT25 | W104: EL HOSPITAL CLÍNICO DE MAGALLANES REQUIERE VITAMINA B1/B6/B12 AMP. INDICAR AL COTIZAR: VALOR UNITARIO TOTAL, PRESENTACIÓN (AMP), FECHA VCTO, ADJUNTAR FICHA TÉCNICA Y/O REGISTRO ISP, TIPO DE TRASLADO (ESPECIFICAR, PARA ACORDAR RETIRO CARGO HOSPITAL DE SER NECESARIO), E INDICAR SI CUENTA CON STOCK PARA DESPACHO INMEDIATO. SE DECLARARÁ INADMISIBLE OFERTA QUE INDIQUE VALOR REFERENCIAL $0 o $1, U OMITAN INFORMACIÓN. | X104: 51191905 | Y104: 77.337.544-5 | Z104: Se adjunta cotización detallada, Contacto F. 225104550, contacto@scmpharma.cl, Despacho sin costo, Envio 7 dias- monto mínimo de despacho $ 100.000.- Cotización valida por 15 días.
A105: 1058012-1162-AG24 | B105: 45432 | C105: COMPRA ALTERNATIVA URGENTE COMITÉ FARMACIA MAYO / ÁCIDO TRANEXÁMICO 500 MG CM | D105: COMPRA ALTERNATIVA POR FALTA DE STOCK EN PROVEDOR OC N° 1058012-1153-SE24. ADQUISICIÓN VÍA COMPRA ÁGIL. COMITÉ FARMACIA N°4 AÑO 2024. FLETE CARGO DEL PROVEEDOR. REF 1058012-360-COT24. ZGEN 100000028. | E105: 870000 | F105: 0 | G105: 0 | H105: 165300 | I105: 1035300 | J105: Fármarcos | K105: EMCURE PHARMA CHILE SPA | L105: 77.240.238-4 | M105: FABRICACION DE PRODUCTOS FARMACEUTICOS, SUSTANCIAS QUIMICAS MEDICINALE | N105: Pequeña | O105: Región Metropolitana de Santiago | P105: 51131808 | Q105: ÁCIDO TRANEXÁMICO 500 MG CM | R105: 600 | S105: Comprimido | T105: 1450 | U105: 870000 | V105: 1058012-360-COT24 | W105: EL HOSPITAL CLÍNICO DE MAGALLANES REQUIERE ÁCIDO TRANEXÁMICO 500 MG CM. INDICAR AL COTIZAR: VALOR UNITARIO TOTAL, PRESENTACIÓN (CM), FECHA VCTO, ADJUNTAR FICHA TÉCNICA Y/O REGISTRO ISP, FACILITAR TIPO DE TRASLADO CARGO HOSPITAL, E INDICAR SI CUENTA CON STOCK PARA DESPACHO INMEDIATO. SE DESESTIMARÁ OFERTA QUE INDIQUE VALOR REFERENCIAL $0 o $1, U OMITAN INFORMACIÓN | X105: 51131808 | Y105: 77.240.238-4 | Z105: PAUSE-500 COMPRIMIDOS RECUBIERTOS 500 mg (ÁCIDO TRANEXÁMICO), caja x20, Bioequivalente, Registro ISP: F-26519/21. Vencimiento: 30-04-2025. Stock disponible, entrega en 3 días, datos de contacto en cotizacion adjunta.
A106: 1057402-4352-AG24 | B106: 45411 | C106: (FAR) STOCK CRÍTICO SUEROS Y ALCOHOLES ABRIL / ALCOHOL ETILICO 70° FCO 250 ML | D106: PEDIDO STOCK CRÍTICO SUEROS Y ALCOHOLES ABRIL. ADQUISICIÓN VÍA COMPRA ÁGIL. FLETE CARGO DEL PROVEEDOR. REF 1057402-663-COT24. ZGEN 100000087. | E106: 1280124 | F106: 0 | G106: 0 | H106: 243223.56 | I106: 1523347.6 | J106: Bienes y Servicios | K106: DIFEM LABORATORIOS S A | L106: 79.581.120-6 | M106: FABRICACION DE PRODUCTOS FARMACEUTICOS, SUSTANCIAS QUIMICAS MEDICINALE| FABRICACIONES DE JABONES Y DETERGENTES, PREPARADOS PARA LIMPIAR, PERFU | N106: Grande | O106: Región Metropolitana de Santiago | P106: 51102710 | Q106: ALCOHOL ETILICO 70° FCO 250 ML | R106: 972 | S106: Frasco | T106: 1317 | U106: 1280124 | V106: 1057402-663-COT24 | W106: SE REQUIERE PARA EL HOSPITAL CLÍNICO DE MAGALLANES ALCOHOL ETILICO 70° FCO 250 ML. INDICAR: VALOR UNITARIO, PRESENTACIÓN Y EMPAQUE (ML), FECHA VCTO, ADJUNTAR FICHA TÉCNICA Y/O REGISTRO ISP, IMAGEN DEL PRODUCTO, TIEMPO DE ENTREGA (ESPECIFICAR, PARA COORDINAR RETIRO CARGO HOSPITAL DE SER NECESARIO), E INDICAR SI CUENTA CON STOCK PARA DESPACHO INMEDIATO. NO SE CONSIDERARÁN OFERTAS QUE INDIQUEN VALOR REFERENCIAL $0 Ó $1 U OMITAN INFORMACIÓN. | X106: 51102710 | Y106: 79.581.120-6 | Z106: 2402073 ALCOHOL 70% SOLUCIÓN TÓPICA DifemPharma 250mL, 36 unidades por caja. Vencimiento 24 meses Despacho 10-15 días. Contacto Daniella Riffo driffo@difem.cl 968447779
A107: 1057402-1213-AG24 | B107: 45385 | C107: (FAR) COMITÉ FARMACIA/ CINTA DE CETONEMIA | D107: PEDIDO COMITÉ FARMACIA. COMPRA AGIL DESPACHO AÉREO CARGO DEL PROVEEDOR. 1057402-175-COT24 | E107: 453600 | F107: 0 | G107: 0 | H107: 86184 | I107: 539784 | J107: Bienes y Servicios | K107: ABBOTT LABORATORIES DE CHILE LTDA | L107: 81.378.300-2 | M107: VENTA AL POR MAYOR DE OTROS PRODUCTOS N.C.P. | N107: Grande | O107: Región Metropolitana de Santiago | P107: 42294705 | Q107: CINTA (TIRA) DE CETONEMIA A_BGM09 FREESTYLE OPTIUM NEOKETONES | R107: 360 | S107: Tira | T107: 1260 | U107: 453600 | V107: 1057402-175-COT24 | W107: EL HOSPITAL CLÍNICO DE MAGALLANES REQUIERE CINTA DE CETONEMIA A_BGM09 FREESTYLE OPTIUM NEO KETONES. INDICAR AL COTIZAR: VALOR UNITARIO TOTAL, PRESENTACIÓN (ML), FECHA VCTO, ADJUNTAR FICHA TÉCNICA Y/O REGISTRO ISP, TIPO DE TRASLADO (ESPECIFICAR, PARA ACORDAR RETIRO CARGO HOSPITAL DE SER NECESARIO), E INDICAR SI CUENTA CON STOCK PARA DESPACHO INMEDIATO. SE DESESTIMARÁ OFERTA QUE INDIQUE VALOR REFERENCIAL $0 o $1, U OMITAN INFORMACIÓN. | X107: 42294705 | Y107: 81.378.300-2 | Z107: A_BGM14 FREESTYLE OPTIUM B-KETONES NEO CAJA X 10 CINTAS, PRECIO OFERTADO X CINTA, PRECIO INCLUYE FLETE. DESPACHO 72 HORAS AEREO. DISPONIBILIDAD INMEDIATA. FECHA VENCIMIENTO MAYOR A 12 MESES.
A108: 1058012-4628-AG25 | B108: 45994 | C108: COMPRA ALTERNATIVA FARMACIA AMBULATORIA FEBRERO / TRAMADOL 100 MG ML GTS | D108: COMPRA ALTERNATIVA POR FALTA DE STOCK EN OC N° 1058012-4434-AG25. ADQUISICIÓN VÍA COMPRA ÁGIL. DESPACHO 48 HRS. SEGÚN COTIZACIÓN. ZGEN 100001463. REF 1058012-137-COT25. | E108: 1388400 | F108: 0 | G108: 0 | H108: 263796 | I108: 1652196 | J108: Fármarcos | K108: COMERCIALIZADORA E-COMCHILE SPA | L108: 77.027.029-4 | M108: VENTAS Y SERVICIOS | N108: Micro | O108: Región Metropolitana de Santiago | P108: 51142235 | Q108: TRAMADOL 100 MG / ML SOLUCION ORAL (1 ML = 40 GOTAS) | R108: 1200 | S108: Frasco | T108: 1157 | U108: 1388400 | V108: 1058012-137-COT25 | W108: EL HOSPITAL CLÍNICO DE MAGALLANES REQUIERE TRAMADOL 100 MG ML GTS. INDICAR AL COTIZAR: VALOR UNITARIO TOTAL, PRESENTACIÓN (FC), FECHA VCTO, ADJUNTAR FICHA TÉCNICA Y/O REGISTRO ISP, TIPO DE TRASLADO (ESPECIFICAR, PARA ACORDAR RETIRO CARGO HOSPITAL DE SER NECESARIO), E INDICAR SI CUENTA CON STOCK PARA DESPACHO INMEDIATO. SE DECLARARA INADMISIBLE OFERTA QUE INDIQUE VALOR REFERENCIAL $0 o $1, NO ENTREGUEN DOCUMENTACIÓN TÉCNICA U OMITAN INFORMACIÓN. | X108: 51142235 | Y108: 77.027.029-4 | Z108: TRAMADOL 100 MG/ML GOTAS FCO. 10 ML VCTO 06-2026 ENVIO INCLUIDO 48 HORAS/ 56989247629 VENTAS@ECOMCH.CL / MINIMO DE FACTURACION 100.000 NETO
A109: 1058012-6798-AG25 | B109: 45769 | C109: COMPRA ALTERNATIVA FALTA CENABAST MARZO / ISOTRETINOINA 20 MG CP | D109: COMPRA ALTERNATIVA POR FALTA DE STOCK EN PROVEEDOR OC N° 1058012-6716-AG25. ADQUSICIÓN VÍA COMPRA ÁGIL. DESPACHO 48 A 72 HRS. CARGO DEL PROVEEDOR SEGÚN COTIZACIÓN. REF 1058012-227-COT25. | E109: 921600 | F109: 0 | G109: 0 | H109: 175104 | I109: 1096704 | J109: Fármarcos | K109: SERVICIOS FARMACEUTICOS Y DE SALUD QAFARMA SPA | L109: 78.045.809-7 | N109: NoClasificado | O109: Región Metropolitana de Santiago | P109: 85121902 | Q109: ISOTRETINOINA 20 MG CP | R109: 900 | S109: Cápsula | T109: 1024 | U109: 921600 | V109: 1058012-227-COT25 | W109: EL HOSPITAL CLÍNICO DE MAGALLANES REQUIERE ISOTRETINOINA 20 MG CP. INDICAR AL COTIZAR: VALOR UNITARIO TOTAL, PRESENTACIÓN (CP), FECHA VCTO, ADJUNTAR FICHA TÉCNICA Y/O REGISTRO ISP, TIPO DE TRASLADO (ESPECIFICAR, PARA ACORDAR RETIRO CARGO HOSPITAL DE SER NECESARIO), E INDICAR SI CUENTA CON STOCK PARA DESPACHO INMEDIATO. SE DECLARARÁ INADMISIBLE OFERTA QUE INDIQUE VALOR REFERENCIAL $0 o $1, U OMITAN CUALQUIER INFORMACIÓN SOLICITADA PARA ESTA COTIZACIÓN. | X109: 85121902 | Y109: 78.045.809-7 | Z109: Despacho en 48-72 horas, Oc minima 100.000, despacho sin costo extra, contacto Qafarma.spa@gmail.com Datos de pago: Rut 78.045.809-7 cuenta corriente n° 96176791 Banco Santander, correo qa.farmavidda@gmail.com
A110: 1058012-8335-AG25 | B110: 45922 | C110: COMPRA ALTERNATIVA CONTROLADOS/ METILFENIDATO 36 MG CM | D110: COMPRA ALTERNATIVA POR FALTA DE STOCK EN PROVEEDOR DE N° ÓRDENES 1058012-7240-SE257711 Y 7860 ADQUISICIÓN VÍA COMPRA ÁGIL. TRASLADO CARGO A CONFIRMAR CON EL SR. RODRIGO BARRÍA AL CORREO rodrigo.barria.b@redsalud.gov.cl Ó AL FONO 61 -2293466. ZGEN (100006139) REF 1058012-546-COT25 | E110: 600000 | F110: 0 | G110: 0 | H110: 114000 | I110: 714000 | J110: Fármarcos | K110: Exeltis Chile SpA | L110: 76.383.221-K | M110: Farmaceutico | N110: Grande | O110: Región Metropolitana de Santiago | P110: 51142618 | Q110: METILFENIDATO 36 MG CM LP | R110: 600 | S110: Comprimido | T110: 1000 | U110: 600000 | V110: 1058012-546-COT25 | W110: EL HCM REQUIERE METILFENIDATO 36 MG CM LP. INDICAR FECHA DE ENTREGA EN BODEGA HCM, FACTOR EMPAQUE, FECHA VCTO, ADJUNTAR FICHA TÉCNICA Y/O REGISTRO ISP, TIPO DE TRASLADO. POSTULAR SOLO SI CUENTA CON STOCK PARA DESPACHO INMEDIATO. COMPRA SUJETA A MULTA DE NO RESPETAR FECHA ESTIMADA DE ENTREGA. SE DESESTIMARÁ OFERTA QUE INDIQUE VALOR REFERENCIAL $1, O QUE SOBREPASE EL VALOR DEL MONTO ESTIMADO O NO CUMPLA CON LOS DIAS Y DOC. SOLICITAD | X110: 51142618 | Y110: 76.383.221-K | Z110: 236795 OSMETIL 36 - METILFENIDATO 36 MG. CADA FRASCO CONTIENE 30 COMPRIMIDOS DE LIBERACION OSMOTICA PROLONGADAVENC 30-04-2027 MINMO FACT Y DESP $ 150.000 NETOENTREGA 3 DIAS HAB.
A111: 1058012-4756-AG25 | B111: 45742 | C111: COMPRA ALTERNATIVA FARMACIA AMBULATORIA MARZO / TRAMADOL 100 MG ML GTS | D111: COMPRA ALTERNATIVA POR FALTA DE STOCK EN OC N° 1058012-4675-SE25. ADQUISICIÓN VÍA COMPRA ÁGIL. DESPACHO 24 A 48 HRS. SEGÚN COTIZACIÓN. ZGEN 100001463. REF 1058012-157-COT25. | E111: 1755000 | F111: 0 | G111: 0 | H111: 333450 | I111: 2088450 | J111: Fármarcos | K111: ADN FARMACEUTICA SPA | L111: 76.786.297-0 | M111: DROGUERIA | N111: Mediana | O111: Región Metropolitana de Santiago | P111: 51142235 | Q111: TRAMADOL 100 MG ML GTS (1 ML = 40 GOTAS) | R111: 1800 | S111: Frasco | T111: 975 | U111: 1755000 | V111: 1058012-157-COT25 | W111: EL HOSPITAL CLÍNICO DE MAGALLANES REQUIERE TRAMADOL 100 MG ML GTS. INDICAR AL COTIZAR: VALOR UNITARIO TOTAL, PRESENTACIÓN (ML), FECHA VCTO, ADJUNTAR FICHA TÉCNICA Y/O REGISTRO ISP, TIPO DE TRASLADO CARGO PROVEEDOR (ESPECIFICAR, PARA ACORDAR RETIRO CARGO HOSPITAL DE SER NECESARIO), E INDICAR SI CUENTA CON STOCK PARA DESPACHO INMEDIATO. SE DECLARARÁ INADMISIBLE OFERTA QUE INDIQUE VALOR REFERENCIAL $0 o $1, U OMITAN INFORMACIÓN Y DOCUMENTOS SOLICITADOS. | X111: 51142235 | Y111: 76.786.297-0 | Z111: TRAMADOL GTS.100MG/ML.10M, COSTO FLETE INCLUIDO, DESPACHO DE 24 A 48 HORAS, UNA VEZ ACEPTADA LA ORDEN DE COMPRA, SIN MÍNIMO DE FACTURACIÓN, VENCE SUPERIOR A 12 MESES (PV) pvalencia@adnfarmaceutica.cl
A112: 1058012-8336-AG25 | B112: 45922 | C112: COMPRA ALTERNATIVA CONTROLADOS JULIO - AGOSTO / METILFENIDATO 27 MG CM LP | D112: COMPRA ALTERNATIVA POR FALTA DE STOCK EN PROVEEDOR DE N° ORDEN 1058012-7709-SE25 7859-SE25. ADQUISICIÓN VÍA COMPRA ÁGIL. TRASLADO CARGO A CONFIRMAR CON EL SR. RODRIGO BARRÍA AL CORREO rodrigo.barria.b@redsalud.gov.cl Ó AL FONO 61 -2293466. ZGEN 100006138 REF 1058012-535-COT25 | E112: 230400 | F112: 0 | G112: 0 | H112: 43776 | I112: 274176 | J112: Fármarcos | K112: Exeltis Chile SpA | L112: 76.383.221-K | M112: Farmaceutico | N112: Grande | O112: Región Metropolitana de Santiago | P112: 51142618 | Q112: METILFENIDATO 27 MG CM LIBERACIÓN PROLONGADA | R112: 240 | S112: Comprimido | T112: 960 | U112: 230400 | V112: 1058012-535-COT25 | W112: EL HCM REQUIERE METILFENIDATO 27 MG CM LP. INDICAR FECHA DE ENTREGA EN BODEGA HCM, FACTOR EMPAQUE, FECHA VCTO, ADJUNTAR FICHA TÉCNICA Y/O REGISTRO ISP, TIPO DE TRASLADO. POSTULAR SOLO SI CUENTA CON STOCK PARA DESPACHO INMEDIATO. COMPRA SUJETA A MULTA DE NO RESPETAR FECHA ESTIMADA DE ENTREGA. SE DESESTIMARÁ OFERTA QUE INDIQUE VALOR REFERENCIAL $1, O QUE SOBREPASE EL VALOR DEL MONTO ESTIMADO O NO CUMPLA CON LOS DIAS Y DOC. SOLICITADOS. | X112: 51142618 | Y112: 76.383.221-K | Z112: 236794 OSMETIL 27 - METILFENIDATO 27 MG. CADA FRASCO CONTIENE 30 COMPRIMIDOS DE LIBERACION OSMOTICA PROLONGADA VENC 31-MAR.-2027 ENTREGA 6 DIAS HAB MINIMO FACT Y DESP $ 150.000 NETO
A113: 1058012-6964-AG25 | B113: 45813 | C113: FALTA CENABAST ABRIL/ ISOTRETINOINA 20 MG CAP | D113: PEDIDO FALTA CENABAST ABRIL. COMPRA AGIL DESPACHO CARGO DEL PROVEEDOR. 1058012-212-COT25 | E113: 425700 | F113: 0 | G113: 0 | H113: 80883 | I113: 506583 | J113: Fármarcos | K113: ADN FARMACEUTICA SPA | L113: 76.786.297-0 | M113: DROGUERIA | N113: Mediana | O113: Región Metropolitana de Santiago | P113: 51241220 | Q113: ISOTRETINOINA 20 MG CAP | R113: 450 | S113: Unidad | T113: 946 | U113: 425700 | V113: 1058012-212-COT25 | W113: EL HOSPITAL CLÍNICO DE MAGALLANES REQUIERE ISOTRETINOINA 20 MG CAP. INDICAR AL COTIZAR: FECHA DE ENTREGA EN BODEGA DEL HCM, PRESENTACIÓN (ML), FECHA VCTO, ADJUNTAR FICHA TÉCNICA Y/O REGISTRO ISP, TIPO DE TRASLADO. POSTULAR SOLO SI CUENTA CON STOCK PARA DESPACHO INMEDIATO. COMPRA SUJETA A MULTA POR NO RESPETAR FECHA ESTIMADA DE ENTREGA DE LA OC. SE DESESTIMARÁ OFERTA QUE INDIQUE VALOR REFERENCIAL $0 o $1, O NO CUMPLAN CON LO SOLICITADO. MOTIVO IPORTANTE PARA DEJAR FUERA UNA OFERTA ES S | X113: 51241220 | Y113: 76.786.297-0 | Z113: INFLADER CAP.20MG.CX30*ENTREGA DE 24 A 48 HRS, VENCE MAS DE 12 MESES, DESPACHO C/FACTURA INCLUIDO EN EL PRECIO, SIN MINIMO DE COMPRA,CON POLITICA DE CANJE, OFERENTE Ximena Silva/9-57438894/xsilva@adnfarmaceutica.cl
A114: 1058012-1777-AG24 | B114: 45492 | C114: (FAR) FARMACIA DOSIS UNITARIA JULIO / GLUCOSA 50% 20 ML SOL INY AMP | D114: PEDIDO FARMACIA DOSIS UNITARIA JULIO. ADQUISICIÓN VÍA COMPRA ÁGIL. FLETE 30 A 45 DÍAS SEGÚN COTIZACIÓN. REF 1058012-496-COT24. | E114: 450000 | F114: 0 | G114: 0 | H114: 85500 | I114: 535500 | J114: Fármarcos | K114: FARMACIAS Y DROGUERÍAS DE CHILE SPA | L114: 76.032.335-7 | M114: VENTA AL POR MAYOR DE OTROS PRODUCTOS N.C.P.| VENTA AL POR MENOR DE PRODUCTOS MEDICINALES | N114: Mediana | O114: Región Metropolitana de Santiago | P114: 51142149 | Q114: GLUCOSA 50% 20 ML SOLUCIÓN INYECTABLE AMP | R114: 500 | S114: Ampolla | T114: 900 | U114: 450000 | V114: 1058012-496-COT24 | W114: EL HOSPITAL CLÍNICO DE MAGALLANES REQUIERE GLUCOSA 50% 20 ML SOL INY AMP. INDICAR AL COTIZAR: VALOR UNITARIO TOTAL, PRESENTACIÓN (ML), FECHA VCTO, ADJUNTAR FICHA TÉCNICA Y/O REGISTRO ISP, TIPO DE TRASLADO CARGO PROVEEDOR (ESPECIFICAR, PARA ACORDAR RETIRO CARGO HOSPITAL DE SER NECESARIO), E INDICAR SI CUENTA CON STOCK PARA DESPACHO INMEDIATO. SE DESESTIMARÁ OFERTA QUE INDIQUE VALOR REFERENCIAL $0 o $1, U OMITAN INFORMACIÓN. | X114: 51142149 | Y114: 76.032.335-7 | Z114: Glucosa Solución Inyectable 50% - 100 ampolla Plástico - 20ml - Halex Istar- Vencimiento mayor a 12 meses- Importación por art 99 del producto. Fecha estimada de entrega segunda semana de Agosto de 2024.
A115: 1058012-4755-AG25 | B115: 45742 | C115: FARMACIA AMBULATORIA MARZO / FLECAINIDA 100 MG CM | D115: PEDIDO FARMACIA AMBULATORIA MARZO. ADQUISICIÓN VÍA COMPRA ÁGIL. DESPACHO 7 DÍAS SEGÚN COTIZACIÓN. ZGEN 100005331. REF 1058012-154-COT25. | E115: 261600 | F115: 0 | G115: 0 | H115: 49704 | I115: 311304 | J115: Fármarcos | K115: SCM PHARMA SPA | L115: 77.337.544-5 | M115: VENTA AL POR MAYOR DE PRODUCTOS FARMACEUTICOS Y MEDICINALES | N115: Mediana | O115: Región Metropolitana de Santiago | P115: 51121515 | Q115: FLECAINIDA 100 MG CM | R115: 300 | S115: Comprimido | T115: 872 | U115: 261600 | V115: 1058012-154-COT25 | W115: EL HOSPITAL CLÍNICO DE MAGALLANES REQUIERE FLECAINIDA 100 MG CM. INDICAR AL COTIZAR: VALOR UNITARIO TOTAL, PRESENTACIÓN (CM), FECHA VCTO, ADJUNTAR FICHA TÉCNICA Y/O REGISTRO ISP, TIPO DE TRASLADO (ESPECIFICAR, PARA ACORDAR RETIRO CARGO HOSPITAL DE SER NECESARIO), E INDICAR SI CUENTA CON STOCK PARA DESPACHO INMEDIATO. SE DECLARARÁ INADMISIBLE OFERTA QUE INDIQUE VALOR REFERENCIAL $0 o $1, U OMITAN INFORMACIÓN. | X115: 51121515 | Y115: 77.337.544-5 | Z115: Se adjunta cotización detallada, Contacto F. 225104550, contacto@scmpharma.cl, Despacho sin costo, Envio 7 dias- monto mínimo de despacho $ 100.000.- Cotización valida por 15 días.
A116: 1058012-1774-AG24 | B116: 45495 | C116: (FAR) COMPRA ALTERNATIVA CONTROLADOS JULIO / METILFENIDATO 36 MG CM LP | D116: COMPRA ALTERNATIVA POR FALTA DE STOCK EN PROVEEDOR OC N° 1058012-1536-SE24. ADQUISICIÓN VÍA COMPRA ÁGIL. FLETE 3 DÍAS HÁBILES SEGÚN COTIZACIÓN. ZGEN 100006139. REF 1058012-443-COT24. | E116: 255300 | F116: 0 | G116: 0 | H116: 48507 | I116: 303807 | J116: Fármarcos | K116: Exeltis Chile SpA | L116: 76.383.221-K | M116: Farmaceutico | N116: Grande | O116: Región Metropolitana de Santiago | P116: 51142618 | Q116: METILFENIDATO 36 MG CM | R116: 300 | S116: Comprimido | T116: 851 | U116: 255300 | V116: 1058012-443-COT24 | W116: EL HOSPITAL CLÍNICO DE MAGALLANES REQUIERE METILFENIDATO 36 MG CM. INDICAR AL COTIZAR: VALOR UNITARIO TOTAL, PRESENTACIÓN (ML), FECHA VCTO, ADJUNTAR FICHA TÉCNICA Y/O REGISTRO ISP, TIPO DE TRASLADO y ESPECIFICAR FECHA DE ENTREGA, INDICAR SI CUENTA CON STOCK PARA DESPACHO INMEDIATO. SE DESESTIMARÁ OFERTA QUE INDIQUE VALOR REFERENCIAL $0 o $1, U OMITAN INFORMACIÓN. | X116: 51142618 | Y116: 76.383.221-K | Z116: 236795 OSMETIL 36 mg Metilfenidato 36 mg Cada frasco contiene 30 comprimidos recubiertos de liberaci?n osm?tica prolongada. Entrega 3 d?as h?biles. Monto m?nimo de despacho y facturaci?n $100.000 Neto (Vence 31-jul.-2025
A117: 1058012-101-AG25 | B117: 45670 | C117: FARMACIA AMBULATORIA ENERO / EPLERENONA 50 MG CM | D117: PEDIDO FARMACIA AMBULATORIA ENERO. ADQUISICIÓN VÍA COMPRA ÁGIL. FLETE 7 DÍAS CARGO DEL PROVEEDOR. ZGEN 100005944. REF 1058012-7-COT25. | E117: 248400 | F117: 0 | G117: 0 | H117: 47196 | I117: 295596 | J117: Fármarcos | K117: SCM PHARMA SPA | L117: 77.337.544-5 | M117: VENTA AL POR MAYOR DE PRODUCTOS FARMACEUTICOS Y MEDICINALES | N117: Mediana | O117: Región Metropolitana de Santiago | P117: 85121902 | Q117: EPLERENONA 50 MG CM | R117: 300 | S117: Comprimido | T117: 828 | U117: 248400 | V117: 1058012-7-COT25 | W117: EL HOSPITAL CLÍNICO DE MAGALLANES REQUIERE EPLERENONA 50 MG CM. INDICAR AL COTIZAR: VALOR UNITARIO TOTAL, PRESENTACIÓN (CM), FECHA VCTO, ADJUNTAR FICHA TÉCNICA Y/O REGISTRO ISP, TIPO DE TRASLADO CARGO PROVEEDOR (ESPECIFICAR, PARA ACORDAR RETIRO CARGO HOSPITAL DE SER NECESARIO), E INDICAR SI CUENTA CON STOCK PARA DESPACHO INMEDIATO. SE DESESTIMARÁ OFERTA QUE INDIQUE VALOR REFERENCIAL $0 o $1, U OMITAN INFORMACIÓN Y DOCUMENTOS SOLICITADOS. | X117: 85121902 | Y117: 77.337.544-5 | Z117: Se adjunta cotización detallada, Contacto F. 225104550, contacto@scmpharma.cl, Despacho sin costo, Envio 7 dias- monto mínimo de despacho $ 100.000.- Cotización valida por 15 días.
A118: 1058012-1775-AG24 | B118: 45495 | C118: (FAR) COMPRA ALTERNATIVA CONTROLADOS JULIO / METILFENIDATO 27 MG CM LP | D118: COMPRA ALTERNATIVA POR FALTA DE STOCK EN PROVEEDOR OC N° 1058012-1535-SE24. ADQUISICIÓN VÍA COMPRA ÁGIL. FLETE 3 DÍAS HÁBILE SSEGÚN COTIZACIÓN. ZGEN 100006138. REF 1058012-444-COT24. | E118: 240600 | F118: 0 | G118: 0 | H118: 45714 | I118: 286314 | J118: Fármarcos | K118: Exeltis Chile SpA | L118: 76.383.221-K | M118: Farmaceutico | N118: Grande | O118: Región Metropolitana de Santiago | P118: 51142618 | Q118: METILFENIDATO 27 MG CM | R118: 300 | S118: Comprimido | T118: 802 | U118: 240600 | V118: 1058012-444-COT24 | W118: EL HOSPITAL CLÍNICO DE MAGALLANES REQUIERE METILFENIDATO 27 MG CM. INDICAR AL COTIZAR: VALOR UNITARIO TOTAL, PRESENTACIÓN (ML), FECHA VCTO, ADJUNTAR FICHA TÉCNICA Y/O REGISTRO ISP, TIPO DE TRASLADO y ESPECIFICAR FECHA DE ENTREGA, INDICAR SI CUENTA CON STOCK PARA DESPACHO INMEDIATO. SE DESESTIMARÁ OFERTA QUE INDIQUE VALOR REFERENCIAL $0 o $1, U OMITAN INFORMACIÓN. | X118: 51142618 | Y118: 76.383.221-K | Z118: 236794 OSMETIL 27 mg Metilfenidato 27 mg Cada frasco contiene 30 comprimidos recubiertos de liberaci?n osm?tica prolongada. Entrega 3 d?as h?biles. Monto m?nimo de despacho yfacturaci?n $100.000 Neto. (vence 30-nov.-2025
A119: 1058012-6756-AG25 | B119: 45934 | C119: PARTICULAR FARMACIA ABRIL / ESPIRONOLACTONA 100 MG CM | D119: PEDIDO PARTICULAR FARMACIA ABRIL. ADQUISICIÓN VÍA COMPRA ÁGIL. DESPACHO 13 A 20 DÍAS POSTERIOR A LA APROBACIÓN DE LOS DOCUMENTOS, CARGO DEL PROVEEDOR SEGÚN COTIZACIÓN. TRATAMIENTO PACIENTE P.D.A. DIAGNOSTICO SINDROME DE BARTTER Y SEGÚN RECETA INSTITUCIONAL N° 548090. REF 1058012-184-COT25 | E119: 320000 | F119: 0 | G119: 0 | H119: 60800 | I119: 380800 | J119: Fármarcos | K119: COMERCIALIZADORA DE ALIMENTOS ESPECIALIZADOS, MEDICAMENTOS Y DISPOSITI | L119: 77.145.531-K | M119: VENTA AL POR MAYOR DE PRODUCTOS FARMACEUTICOS Y MEDICINALES | N119: Mediana | O119: Región Metropolitana de Santiago | P119: 51191507 | Q119: ESPIRONOLACTONA 100 MG CM | R119: 400 | S119: Comprimido | T119: 800 | U119: 320000 | V119: 1058012-184-COT25 | W119: EL HOSPITAL CLÍNICO DE MAGALLANES REQUIEREESPIRONOLACTONA 100 MG CM. INDICAR AL COTIZAR: VALOR UNITARIO TOTAL, PRESENTACIÓN (CM), FECHA VCTO, ADJUNTAR FICHA TÉCNICA Y/O REGISTRO ISP, TIPO DE TRASLADO (ESPECIFICAR, PARA ACORDAR RETIRO CARGO HOSPITAL DE SER NECESARIO), E INDICAR SI CUENTA CON STOCK PARA DESPACHO INMEDIATO. SE DECLARARÁ INADMISIBLE OFERTA QUE INDIQUE VALOR REFERENCIAL $0 o $1, U OMITAN CUALQUIER INFORMACIÓN SOLICITADA PARA ESTA COTIZACIÓN. | X119: 51191507 | Y119: 77.145.531-K | Z119: Spironolactone 100mg (Espironolactona) frasco de 100 tabletas, plazo de entrega 13 a 20 días hábiles, una vez aprobados los documentos. Servicio importación medicamentos para uso personal, Art. N°24 del DTO, N°3 del MINSAL. ver documentos adjuntos.
A120: 1058012-1539-AG24 | B120: 45471 | C120: COMPRA ALTERNATIVA STOCK CRÍTICO FARMACIA AMBULATORIA JUNIO / CINACALCET 60 MG CM | D120: COMPRA ALTERNATIVA POR FALTA DE STOCK EN PROVEEDOR N° 1058012-1454-SE24. ADQUISICIÓN VÍA COMPRA ÁGIL. FLETE 3 DÍAS SEGÚN COTIZACIÓN. ZGEN 100003459. REF 1058012-436-COT24. | E120: 715500 | F120: 0 | G120: 0 | H120: 135945 | I120: 851445 | J120: Fármarcos | K120: EMCURE PHARMA CHILE SPA | L120: 77.240.238-4 | M120: FABRICACION DE PRODUCTOS FARMACEUTICOS, SUSTANCIAS QUIMICAS MEDICINALE | N120: Pequeña | O120: Región Metropolitana de Santiago | P120: 85121902 | Q120: CINACALCET 60 MG CM | R120: 900 | S120: Comprimido | T120: 795 | U120: 715500 | V120: 1058012-436-COT24 | W120: EL HOSPITAL CLÍNICO DE MAGALLANES REQUIERECINACALCET 60 MG CM. INDICAR AL COTIZAR: VALOR UNITARIO TOTAL, PRESENTACIÓN (CM), FECHA VCTO, ADJUNTAR FICHA TÉCNICA Y/O REGISTRO ISP, TIPO DE TRASLADO CARGO PROVEEDOR (ESPECIFICAR, PARA ACORDAR RETIRO CARGO HOSPITAL DE SER NECESARIO), E INDICAR SI CUENTA CON STOCK PARA DESPACHO INMEDIATO. SE DESESTIMARÁ OFERTA QUE INDIQUE VALOR REFERENCIAL $0 o $1, U OMITAN INFORMACIÓN. | X120: 85121902 | Y120: 77.240.238-4 | Z120: CINACALCET COMPRIMIDOS RECUBIERTOS 60 mg, Caja X 28 CM, Bioequivalente, Registro ISP F-27631, vencimiento 28-02-2027 Stock disponible, entrega en 3 días, despacho incluido. Datos de contacto en cotización adjunta.
A121: 1058012-2767-AG24 | B121: 45623 | C121: COMPRA ALTERNATIVA FALTA CENABAST OCTUBRE / CINACALCET 60 MG CM | D121: COMPRA ALTERNATIVA POR FALTA DE STOCK EN PROVEEDOR OC N° 1058012-2476-SE24. ADQUISICIÓN VÍA COMPRA ÁGIL. FLETE 3 DÍAS SEGÚN COTIZACIÓN. ZGEN 100003459. REF 1058012-640-COT24. | E121: 467460 | F121: 0 | G121: 0 | H121: 88817.4 | I121: 556277.4 | J121: Fármarcos | K121: EMCURE PHARMA CHILE SPA | L121: 77.240.238-4 | M121: FABRICACION DE PRODUCTOS FARMACEUTICOS, SUSTANCIAS QUIMICAS MEDICINALE | N121: Micro | O121: Región Metropolitana de Santiago | P121: 85121902 | Q121: CINACALCET 60 MG CM | R121: 588 | S121: Comprimido | T121: 795 | U121: 467460 | V121: 1058012-640-COT24 | W121: EL HOSPITAL CLÍNICO DE MAGALLANES REQUIERE CINACALCET 60 MG CM. INDICAR AL COTIZAR: VALOR UNITARIO TOTAL, PRESENTACIÓN (CM), FECHA VCTO, ADJUNTAR FICHA TÉCNICA Y/O REGISTRO ISP, TIPO DE TRASLADO CARGO PROVEEDOR (ESPECIFICAR, PARA ACORDAR RETIRO CARGO HOSPITAL DE SER NECESARIO), E INDICAR SI CUENTA CON STOCK PARA DESPACHO INMEDIATO. SE DESESTIMARÁ OFERTA QUE INDIQUE VALOR REFERENCIAL $0 o $1, U OMITAN INFORMACIÓN Y DOCUMENTOS SOLICITADOS. | X121: 85121902 | Y121: 77.240.238-4 | Z121: CINACALCET COMPRIMIDOS RECUBIERTOS 60 mg, Caja X 28 CM, Bioequivalente, Registro ISP F-27631, vencimiento 28-02-2027 Stock disponible, entrega en 3 días. Datos de contacto en cotización adjunta.
... A135: 1058012-1117-AG24 | B135: 45570 | C135: FARMACIA AMBULATORIA MAYO / DEFLAZACORT 6 MG CM | D135: PEDIDO FARMACIA AMBULATORIA MAYO. ADQUISICIÓN VÍA COMPRA ÁGIL. FLETE CARGO DEL PROVEEDOR. REF 1058012-323-COT24. | E135: 144000 | F135: 0 | G135: 0 | H135: 27360 | I135: 171360 | J135: Fármarcos | K135: MUNNICH PHARMA MEDICAL LIMITADA | L135: 80.447.400-5 | M135: VENTA AL POR MAYOR DE PRODUCTOS FARMACEUTICOS| VENTA AL POR MAYOR DE OTROS PRODUCTOS N.C.P. | N135: Grande | O135: Región Metropolitana de Santiago | P135: 51181718 | Q135: DEFLAZACORT 6 MG CM | R135: 300 | S135: Comprimido | T135: 480 | U135: 144000 | V135: 1058012-323-COT24 | W135: EL HOSPITAL CLÍNICO DE MAGALLANES REQUIERE DEFLAZACORT 6 MG CM. INDICAR AL COTIZAR: VALOR UNITARIO TOTAL, PRESENTACIÓN (CM), FECHA VCTO, ADJUNTAR FICHA TÉCNICA Y/O REGISTRO ISP, TIPO DE TRASLADO CARGO PROVEEDOR (ESPECIFICAR, PARA ACORDAR RETIRO CARGO HOSPITAL DE SER NECESARIO), E INDICAR SI CUENTA CON STOCK PARA DESPACHO INMEDIATO. SE DESESTIMARÁ OFERTA QUE INDIQUE VALOR REFERENCIAL $0 o $1, U OMITAN INFORMACIÓN. | X135: 51181718 | Y135: 80.447.400-5 | Z135: Se adjunta cotizacion formal. Se adjunta Ficha Tecnica para su evaluacion. Monto minimo de facturacion $50.000. Despacho en 24 a 72 hrs, sin costo. Zonas Extremas ( Sujeto a Evaluacion con Operador Logistico) Contacto: paloma.johnson@munnich.cl
A136: 1058012-2931-AG24 | B136: 45638 | C136: COMPRA ALTERNATIVA FARMACIA AMBULATORIA NOVIEMBRE / PROGESTERONA 100 MG CP | D136: COMPRA ALTERNATIVA POR FALTA DE STOCK EN PROVEEDOR OC N° 1058012-2772-AG24. ADQUISICIÓN VÍA COMPRA ÁGIL. FLETE 48 HORAS SEGÚN COTIZACIÓN. ZGEN 100003402. REF 1058012-670-COT24. | E136: 286200 | F136: 0 | G136: 0 | H136: 54378 | I136: 340578 | J136: Fármarcos | K136: SERVICIOS FARMACEUTICOS Y DE SALUD QAFARMA SPA | L136: 78.045.809-7 | N136: N/A | O136: Región Metropolitana de Santiago | P136: 51181818 | Q136: PROGESTERONA 100 MG CP | R136: 600 | S136: Cápsula | T136: 477 | U136: 286200 | V136: 1058012-670-COT24 | W136: EL HOSPITAL CLÍNICO DE MAGALLANES REQUIERE PROGESTERONA 100 MG CP. INDICAR AL COTIZAR: VALOR UNITARIO TOTAL, PRESENTACIÓN (CP), FECHA VCTO, ADJUNTAR FICHA TÉCNICA Y/O REGISTRO ISP, TIPO DE TRASLADO CARGO PROVEEDOR (ESPECIFICAR, PARA ACORDAR RETIRO CARGO HOSPITAL DE SER NECESARIO), E INDICAR SI CUENTA CON STOCK PARA DESPACHO INMEDIATO. SE DESESTIMARÁ OFERTA QUE INDIQUE VALOR REFERENCIAL $0 o $1, U OMITAN INFORMACIÓN Y DOCUMENTOS SOLICITADOS. | X136: 51181818 | Y136: 78.045.809-7 | Z136: Despacho costo 0, en 48 horas, contacto +56952396412, QA.farmavidda@gmail.com, PISV
A137: 1058012-7473-AG25 | B137: 45825 | C137: FARMACIA AMBULATORIA JUNIO / OLANZAPINA BUCODISPERSABLE 5 MG CM | D137: PEDIDO FARMACIA AMBULATORIA JUNIO. ADQUISICIÓN VÍA COMPRA ÁGIL. DESPACHO 3 DÍAS CARGO DEL PROVEEDOR SEGÚN COTIZACIÓN. ZGEN 100004891. REF 1058012-395-COT25. | E137: 572400 | F137: 0 | G137: 0 | H137: 108756 | I137: 681156 | J137: Fármarcos | K137: MEGALABS CHILE S.A | L137: 94.544.000-7 | M137: FABRICACION DE PRODUCTOS FARMACEUTICOS, SUSTANCIAS QUIMICAS MEDICINALE| VENTA AL POR MAYOR DE PRODUCTOS FARMACEUTICOS Y MEDICINALES| VENTA AL POR MAYOR DE OTROS TIPOS DE MAQUINARIA Y EQUIPO N.C.P. | N137: Grande | O137: Región Metropolitana de Santiago | P137: 51141703 | Q137: OLANZAPINA BUCODISPERSABLE 5 MG CM | R137: 1200 | S137: Comprimido | T137: 477 | U137: 572400 | V137: 1058012-395-COT25 | W137: EL HOSPITAL CLÍNICO DE MAGALLANES REQUIERE OLANZAPINA 5 MG CM. INDICAR AL COTIZAR: VALOR UNITARIO TOTAL, PRESENTACIÓN (CM), FECHA VCTO, ADJUNTAR FICHA TÉCNICA Y/O REGISTRO ISP, TIPO DE TRASLADO Y FECHA ESPECIFICA DE ENTREGA (ESPECIFICAR, PARA ACORDAR RETIRO CARGO HOSPITAL DE SER NECESARIO), E INDICAR SI CUENTA CON STOCK PARA DESPACHO INMEDIATO. SE DECLARARÁ INADMISIBLE OFERTA QUE INDIQUE VALOR REFERENCIAL $0 o $1, U OMITAN INFORMACIÓN Y DOCUMENTOS SOLICITADOS. | X137: 51141703 | Y137: 94.544.000-7 | Z137: 001-000-80618 OLIVIN DB 5 MG. X 30 COMP (BE) OLANZAPINA F-25360/25 LABORATORIOS LESVI S.L.-ESPAÑA EQUIV TERAPEUTICO VENCE: 30711/2026 MONTO MINIMO DE FACTURACION $ 100.000
A138: 1058012-7474-AG25 | B138: 45825 | C138: FALTA CENABAST FARMACIA AMBULATORIA JUNIO / FLECAINIDA 100 MG CM | D138: PEDIDO FALTA CENABAST FARMACIA AMBULATORIA JUNIO. ADQUISICIÓN VÍA COMPRA ÁGIL. DESPACHO 3 DÍAS CARGO DEL PROVEEDOR SEGÚN COTIZACIÓN. ZGEN 100005331. REF 1058012-409-COT25. | E138: 142500 | F138: 0 | G138: 0 | H138: 27075 | I138: 169575 | J138: Fármarcos | K138: EMCURE PHARMA CHILE SPA | L138: 77.240.238-4 | M138: FABRICACION DE PRODUCTOS FARMACEUTICOS, SUSTANCIAS QUIMICAS MEDICINALE | N138: Mediana | O138: Región Metropolitana de Santiago | P138: 51121504 | Q138: FLECAINIDA 100 MG CM | R138: 300 | S138: Comprimido | T138: 475 | U138: 142500 | V138: 1058012-409-COT25 | W138: EL HOSPITAL CLÍNICO DE MAGALLANES REQUIERE FLECAINIDA 100 MG CM. INDICAR AL COTIZAR: VALOR UNITARIO TOTAL, PRESENTACIÓN (CM), FECHA VCTO, ADJUNTAR FICHA TÉCNICA Y/O REGISTRO ISP, TIPO DE TRASLADO Y FECHA ESPECIFICA DE ENTREGA (ESPECIFICAR, PARA ACORDAR RETIRO CARGO HOSPITAL DE SER NECESARIO), E INDICAR SI CUENTA CON STOCK PARA DESPACHO INMEDIATO. SE DECLARARÁ INADMISIBLE OFERTA QUE INDIQUE VALOR REFERENCIAL $0 o $1, U OMITAN INFORMACIÓN Y DOCUMENTOS SOLICITADOS. | X138: 51121504 | Y138: 77.240.238-4 | Z138: CADENCE COMPRIMIDOS 100 mg (FLECAINIDA ACETATO), Bioequivalente, caja x50, Registro ISP: F-26177/21. Vencimiento: 30-04-2027. Stock disponible, entrega en 3 días - flete incluido. Datos de contacto en cotización adjunta.
A139: 1058012-62-AG24 | B139: 45627 | C139: COMITÉ FARMACIA N° 10 2023/ ALFACETOANALOGOS DE AMINOACIDOS | D139: PEDIDO COMITÉ FARMACIA N° 10 2023. COMPRA AGIL. FLETE AEREO CARGO DEL PROVEEDOR. 1058012-17-COT24 | E139: 1350000 | F139: 0 | G139: 0 | H139: 256500 | I139: 1606500 | J139: Fármarcos | K139: FRESENIUS KABI CHILE LIMITADA | L139: 77.478.120-k | M139: VENTA AL POR MAYOR DE PRODUCTOS FARMACEUTICOS| TRANSPORTE DE CARGA POR CARRETERA| EMPRESAS DE ASESORIA, CONSULTORIA FINANCIERA Y DE APOYO AL GIRO | N139: Grande | O139: Región Metropolitana de Santiago | P139: 51161812 | Q139: ALFACETOANALOGOS DE AMINOACIDOS | R139: 3000 | S139: Unidad | T139: 450 | U139: 1350000 | V139: 1058012-17-COT24 | W139: EL HOSPITAL CLÍNICO DE MAGALLANES REQUIERE ALFACETOANALOGOS DE AMINOACIDOS. INDICAR AL COTIZAR: VALOR UNITARIO TOTAL, PRESENTACIÓN (ML), FECHA VCTO, ADJUNTAR FICHA TÉCNICA Y/O REGISTRO ISP, TIPO DE TRASLADO (ESPECIFICAR, PARA ACORDAR RETIRO CARGO HOSPITAL DE SER NECESARIO), E INDICAR SI CUENTA CON STOCK PARA DESPACHO INMEDIATO. SE DESESTIMARÁ OFERTA QUE INDIQUE VALOR REFERENCIAL $0 o $1, U OMITAN INFORMACIÓN. | X139: 51161812 | Y139: 77.478.120-k | Z139: COTIZACION N° 20160500 Despacho en cajas cerradas, según factor de empaque.
A140: 1058012-4371-AG25 | B140: 45701 | C140: FARMACIA DOSIS UNITARIA FEBRERO / CLONIDINA 0,1 MG CM | D140: PEDIDO FARMACIA DOSIS UNITARIA FEBRERO. ADQUISICIÓN VÍA COMPRA ÁGIL. FLETE 14 A 26 DÍAS SEGÚN COTIZACIÓN. REF 1058012-93-COT25. | E140: 360000 | F140: 0 | G140: 0 | H140: 68400 | I140: 428400 | J140: Fármarcos | K140: COMERCIALIZADORA DE ALIMENTOS ESPECIALIZADOS, MEDICAMENTOS Y DISPOSITI | L140: 77.145.531-K | M140: VENTA AL POR MAYOR DE PRODUCTOS FARMACEUTICOS Y MEDICINALES | N140: Mediana | O140: Región Metropolitana de Santiago | P140: 51121718 | Q140: CLONIDINA 0,1 MG CM | R140: 800 | S140: Comprimido | T140: 450 | U140: 360000 | V140: 1058012-93-COT25 | W140: EL HOSPITAL CLÍNICO DE MAGALLANES REQUIERE CLONIDINA 0,1 mg cm INDICAR AL COTIZAR: VALOR UNITARIO TOTAL, PRESENTACIÓN (ML), FECHA VCTO, ADJUNTAR FICHA TÉCNICA Y/O REGISTRO ISP, TIPO DE TRASLADO (ESPECIFICAR, PARA ACORDAR RETIRO CARGO HOSPITAL DE SER NECESARIO), E INDICAR SI CUENTA CON STOCK PARA DESPACHO INMEDIATO. SE DESESTIMARÁ OFERTA QUE INDIQUE VALOR REFERENCIAL $0 o $1, U OMITAN INFORMACIÓN. | X140: 51121718 | Y140: 77.145.531-K | Z140: Clonidine 0,1mg (Clonidina HCl) frasco de 100 tabletas, plazo de entrega 14 a 26 días hábiles, una vez aprobados los documentos por Almedis. Servicio importación medicamentos para uso personal, según Art. N°24 del DTO, N°3 del MINSAL. ver condiciones adj.
...

Sheet medicamentos farmacia

Sheet CALCULOS TABLA
A7: Tabla analitica de ordenes de compra
L8: Total sin CENABAST | M8: Total sin farmacia ambulatoria | N8: Total stock critico + CENABAST | O8: Total dosis unitaria + comite farmacia | P8: Total farmacia ambulatoria
A9: Columna 1 | B9: Total stock critico | C9: Total CENABAST | D9: Total dosis unitaria | E9: Total farmacia ambulatoria | F9: Total comité farmacia | G9: Total controlados | H9: Total otros sin clasificar | I9: Total ordenes | L9: =TOTALES!C147 -> 149626460 | M9: =H10+G10+F10+D10+C10+B10 -> 140477859 | N9: =B10+C10 -> 49329647 | O9: =D10+F10 -> 54541587 | P9: 46137003
A10: Valor total con impuesto | B10: ='tabla dinamica total'!F17 -> 12341245 | C10: ='tabla dinamica total'!C47 -> 36988402 | D10: ='tabla dinamica total'!F72 -> 20394810 | E10: ='tabla dinamica total'!I58 -> 46137003 | F10: ='tabla dinamica total'!C74 -> 34146776 | G10: ='tabla dinamica total'!F24 -> 1837122 | H10: ='tabla dinamica total'!F50 -> 34769503 | I10: =SUM(B10:H10) -> 1.8661486e+08 | L10: =L9/I10 -> 0.80179284 | M10: =M9/I10 -> 0.75276887 | N10: =B11+C11 -> 0.26433933 | O10: =O9/I10 -> 0.29226818 | P10: 0.24723113
A11: Porcentaje de valor total | B11: =B10/$I$10 -> 0.066132165 | C11: =C10/$I$10 -> 0.19820716 | D11: =D10/$I$10 -> 0.10928824 | E11: =E10/$I$10 -> 0.24723113 | F11: =F10/$I$10 -> 0.18297994 | G11: =G10/$I$10 -> 0.0098444571 | H11: =H10/$I$10 -> 0.1863169
A12: Porcentaje acumulado | B12: =B11 -> 0.066132165 | C12: =B12+C11 -> 0.26433933 | D12: =C12+D11 -> 0.37362757 | E12: =D12+E11 -> 0.6208587 | F12: =E12+F11 -> 0.80383864 | G12: =F12+G11 -> 0.8136831 | H12: =G12+H11 -> 1
A13: Cantidad de datos | B13: ='tabla dinamica total'!E17 -> 15 | C13: ='tabla dinamica total'!B47 -> 46 | D13: ='tabla dinamica total'!E72 -> 20 | E13: ='tabla dinamica total'!H58 -> 56 | F13: ='tabla dinamica total'!B74 -> 25 | G13: ='tabla dinamica total'!E24 -> 5 | H13: ='tabla dinamica total'!E50 -> 26 | I13: =SUM(B13:H13) -> 193
A14: Porcentaje cantidad | B14: =B13/$I$13 -> 0.077720207 | C14: =C13/$I$13 -> 0.23834197 | D14: =D13/$I$13 -> 0.10362694 | E14: =E13/$I$13 -> 0.29015544 | F14: =F13/$I$13 -> 0.12953368 | G14: =G13/$I$13 -> 0.025906736 | H14: =H13/$I$13 -> 0.13471503 | I14: =I13/$I$13 -> 1
A15: Cantidad acumulada | B15: =B13 -> 15 | C15: =B15+C13 -> 61 | D15: =C15+D13 -> 81 | E15: =D15+E13 -> 137 | F15: =E15+F13 -> 162 | G15: =F15+G13 -> 167 | H15: =G15+H13 -> 193
A16: Porcentaje cantidad acumulada | B16: =B15/$I$13 -> 0.077720207 | C16: =C15/$I$13 -> 0.31606218 | D16: =D15/$I$13 -> 0.41968912 | E16: =E15/$I$13 -> 0.70984456 | F16: =F15/$I$13 -> 0.83937824 | G16: =G15/$I$13 -> 0.86528497 | H16: =H15/$I$13 -> 1
B17: farmacia amnbulatoria estaria gastando mas de 50 millones en 2 años si se suma el stock critico y el total cenabast, voy a hacer una suma tambien considernado solo el area de farmacia ambulatoria, que eran como 70 datos
A70: Periodo 2024-2025 | B70: Total stock critico | C70: Total CENABAST | D70: Total dosis unitaria | E70: Total farmacia ambulatoria | F70: Total comité farmacia | G70: Total controlados | H70: Total otros sin clasificar | I70: Total ordenes
A71: Valor total con impuesto | B71: 12341245 | C71: 36988402 | D71: 20394810 | E71: 46137003 | F71: 34146776 | G71: 1837122 | H71: 34769503 | I71: 1.8661486e+08
A72: Porcentaje de valor total | B72: 0.066132165 | C72: 0.19820716 | D72: 0.10928824 | E72: 0.24723113 | F72: 0.18297994 | G72: 0.0098444571 | H72: 0.1863169
A73: Porcentaje acumulado | B73: 0.066132165 | C73: 0.26433933 | D73: 0.37362757 | E73: 0.6208587 | F73: 0.80383864 | G73: 0.8136831 | H73: 1
A74: Cantidad de datos | B74: 15 | C74: 46 | D74: 20 | E74: 56 | F74: 25 | G74: 5 | H74: 26 | I74: 193
A75: Porcentaje cantidad | B75: 0.077720207 | C75: 0.23834197 | D75: 0.10362694 | E75: 0.29015544 | F75: 0.12953368 | G75: 0.025906736 | H75: 0.13471503 | I75: 1
A76: Cantidad acumulada | B76: 15 | C76: 61 | D76: 81 | E76: 137 | F76: 162 | G76: 167 | H76: 193
A77: Porcentaje cantidad acumulada | B77: 0.077720207 | C77: 0.31606218 | D77: 0.41968912 | E77: 0.70984456 | F77: 0.83937824 | G77: 0.86528497 | H77: 1
A79: 2024 | B79: Total stock critico | C79: Total CENABAST | D79: Total dosis unitaria | E79: Total farmacia ambulatoria | F79: Total comité farmacia | G79: Total controlados | H79: Total otros sin clasificar | I79: Total ordenes
A80: Valor total con impuesto | B80: ='Tabla dinámica 2024'!H10 -> 7776166.9 | C80: ='Tabla dinámica 2024'!D22 -> 8156588.4 | D80: ='Tabla dinámica 2024'!H45 -> 10531214 | E80: ='Tabla dinámica 2024'!L24 -> 15538045 | F80: ='Tabla dinámica 2024'!D42 -> 15318442 | G80: ='Tabla dinámica 2024'!H16 -> 848946 | H80: ='Tabla dinámica 2024'!H31 -> 18576543 | I80: =SUM(B80:H80) -> 76745945
A81: Porcentaje de valor total | B81: =B80/$I$80 -> 0.10132349 | C81: =C80/$I$80 -> 0.10628038 | D81: =D80/$I$80 -> 0.13722177 | E81: =E80/$I$80 -> 0.2024608 | F81: =F80/$I$80 -> 0.19959936 | G81: =G80/$I$80 -> 0.01106177 | H81: =H80/$I$80 -> 0.24205243 | I81: =I80/$I$80 -> 1
A82: Porcentaje acumulado | B82: =B81 -> 0.10132349 | C82: =B82+C81 -> 0.20760387 | D82: =C82+D81 -> 0.34482564 | E82: =D82+E81 -> 0.54728644 | F82: =E82+F81 -> 0.7468858 | G82: =F82+G81 -> 0.75794757 | H82: =G82+H81 -> 1
A83: Cantidad de datos | B83: ='Tabla dinámica 2024'!G10 -> 8 | C83: ='Tabla dinámica 2024'!C22 -> 20 | D83: ='Tabla dinámica 2024'!G45 -> 11 | E83: ='Tabla dinámica 2024'!K24 -> 22 | F83: ='Tabla dinámica 2024'!C42 -> 18 | G83: ='Tabla dinámica 2024'!G16 -> 3 | H83: ='Tabla dinámica 2024'!G31 -> 14 | I83: =SUM(B83:H83) -> 96 | L83: =I80+I89 -> 1.8661486e+08
A84: Porcentaje cantidad | B84: =B83/$I$83 -> 0.083333333 | C84: =C83/$I$83 -> 0.20833333 | D84: =D83/$I$83 -> 0.11458333 | E84: =E83/$I$83 -> 0.22916667 | F84: =F83/$I$83 -> 0.1875 | G84: =G83/$I$83 -> 0.03125 | H84: =H83/$I$83 -> 0.14583333 | I84: =SUM(B84:H84) -> 1 | L84: =I83+I92 -> 193
A85: Cantidad acumulada | B85: =B83 -> 8 | C85: =C83+B85 -> 28 | D85: =D83+C85 -> 39 | E85: =E83+D85 -> 61 | F85: =F83+E85 -> 79 | G85: =G83+F85 -> 82 | H85: =H83+G85 -> 96
A86: Porcentaje cantidad acumulada | B86: =B84 -> 0.083333333 | C86: =B86+C84 -> 0.29166667 | D86: =C86+D84 -> 0.40625 | E86: =D86+E84 -> 0.63541667 | F86: =E86+F84 -> 0.82291667 | G86: =F86+G84 -> 0.85416667 | H86: =G86+H84 -> 1
A88: 2025 | B88: Total stock critico | C88: Total CENABAST | D88: Total dosis unitaria | E88: Total farmacia ambulatoria | F88: Total comité farmacia | G88: Total controlados | H88: Total otros sin clasificar | I88: Total ordenes
A89: Valor total con impuesto | B89: ='tabla dinamica 2025'!H9 -> 4565078 | C89: ='tabla dinamica 2025'!D28 -> 28831814 | D89: ='tabla dinamica 2025'!H38 -> 9863595.8 | E89: ='tabla dinamica 2025'!L36 -> 30598958 | F89: ='tabla dinamica 2025'!D37 -> 18828335 | G89: ='tabla dinamica 2025'!H13 -> 988176 | H89: ='tabla dinamica 2025'!H27 -> 16192961 | I89: =SUM(B89:H89) -> 109868917
A90: Porcentaje de valor total | B90: =B89/$I$89 -> 0.041550223 | C90: =C89/$I$89 -> 0.26242012 | D90: =D89/$I$89 -> 0.089776036 | E90: =E89/$I$89 -> 0.27850423 | F90: =F89/$I$89 -> 0.1713709 | G90: =G89/$I$89 -> 0.0089941362 | H90: =H89/$I$89 -> 0.14738437
A91: Porcentaje acumulado | B91: =B90 -> 0.041550223 | C91: =B91+C90 -> 0.30397034 | D91: =C91+D90 -> 0.39374637 | E91: =D91+E90 -> 0.6722506 | F91: =E91+F90 -> 0.8436215 | G91: =F91+G90 -> 0.85261563 | H91: =G91+H90 -> 1
A92: Cantidad de datos | B92: ='tabla dinamica 2025'!G9 -> 7 | C92: ='tabla dinamica 2025'!C28 -> 26 | D92: ='tabla dinamica 2025'!G38 -> 9 | E92: ='tabla dinamica 2025'!K36 -> 34 | F92: ='tabla dinamica 2025'!C37 -> 7 | G92: ='tabla dinamica 2025'!G13 -> 2 | H92: ='tabla dinamica 2025'!G27 -> 12 | I92: =SUM(B92:H92) -> 97
A93: Porcentaje cantidad | B93: =B92/$I$92 -> 0.072164948 | C93: =C92/$I$92 -> 0.26804124 | D93: =D92/$I$92 -> 0.092783505 | E93: =E92/$I$92 -> 0.35051546 | F93: =F92/$I$92 -> 0.072164948 | G93: =G92/$I$92 -> 0.020618557 | H93: =H92/$I$92 -> 0.12371134
A94: Cantidad acumulada | B94: =B92 -> 7 | C94: =B94+C92 -> 33 | D94: =C94+D92 -> 42 | E94: =D94+E92 -> 76 | F94: =E94+F92 -> 83 | G94: =F94+G92 -> 85 | H94: =G94+H92 -> 97
A95: Porcentaje cantidad acumulada | B95: =B93 -> 0.072164948 | C95: =C93+B95 -> 0.34020619 | D95: =D93+C95 -> 0.43298969 | E95: =E93+D95 -> 0.78350515 | F95: =F93+E95 -> 0.8556701 | G95: =G93+F95 -> 0.87628866 | H95: =H93+G95 -> 1
A97: Valor total | B97: Stock critico | C97: CENABAST | D97: dosis unitaria | E97: farmacia ambulatoria | F97: comite farmacia | G97: controlados | H97: otros sin clasificar
A98: Diferencias entre años 2024-2025 | B98: =B90-B81 -> -0.059773265 | C98: =C90-C81 -> 0.15613973 | D98: =D90-D81 -> -0.047445733 | E98: =E90-E81 -> 0.076043429 | F98: =F90-F81 -> -0.028228465 | G98: =G90-G81 -> -0.0020676339 | H98: =H90-H81 -> -0.094668064

Sheet Tabla dinámica 2024
A78: =B47+B74+F72+F50+F24+F17+J58 -> #VALUE!

Sheet tabla dinamica 2025
A78: =B47+B74+F72+F50+F24+F17+J58 -> #VALUE!

Sheet tabla dinamica total
A78: =B47+B74+E72+E50+E24+E17+H58 -> 193

Sheet TOTALES

Sheet semestre1_2024

Sheet semestre2_2024

Sheet semestre1_2025

Sheet semestre2_2025

Sheet resumen OC
A6: Resumen 2024 | B6: Columna 1 | C6: Columna 2 | D6: Columna 3 | E6: Columna 4 | F6: Columna 5 | G6: Columna 6 | H6: Columna 7 | I6: Columna 8 | J6: Columna 9 | K6: Columna 10 | L6: Columna 11 | M6: Columna 12 | N6: Columna 13
B7: Enero | C7: Febrero | D7: Marzo | E7: Abril | F7: Mayo | G7: Junio | H7: julio | I7: agosto | J7: septiembre | K7: octubre | L7: noviembre | M7: diciembre | N7: Total ordenes
A8: Cantidad ordenes | B8: =semestre1_2024!D9 -> 7 | C8: =semestre1_2024!I8 -> 6 | D8: =semestre1_2024!N5 -> 3 | E8: =semestre1_2024!D16 -> 5 | F8: =semestre1_2024!I20 -> 10 | G8: =semestre1_2024!N17 -> 10 | H8: =semestre2_2024!D19 -> 17 | I8: =semestre2_2024!I12 -> 10 | J8: =semestre2_2024!N12 -> 10 | K8: =semestre2_2024!D24 -> 3 | L8: =semestre2_2024!I23 -> 9 | M8: =semestre2_2024!N20 -> 6 | N8: =SUM(B8:M8) -> 96
A9: Porcentaje ordenes | B9: =B8/$N$8 -> 0.072916667 | C9: =C8/$N$8 -> 0.0625 | D9: =D8/$N$8 -> 0.03125 | E9: =E8/$N$8 -> 0.052083333 | F9: =F8/$N$8 -> 0.10416667 | G9: =G8/$N$8 -> 0.10416667 | H9: =H8/$N$8 -> 0.17708333 | I9: =I8/$N$8 -> 0.10416667 | ... M9: =M8/$N$8 -> 0.0625 | N9: =SUM(B9:M9) -> 1
A10: Porcentaje acumulado | B10: =B9 -> 0.072916667 | C10: =B10+C9 -> 0.13541667 | D10: =C10+D9 -> 0.16666667 | E10: =D10+E9 -> 0.21875 | F10: =E10+F9 -> 0.32291667 | G10: =F10+G9 -> 0.42708333 | H10: =G10+H9 -> 0.60416667 | I10: =H10+I9 -> 0.70833333 | J10: =I10+J9 -> 0.8125 | ... M10: =L10+M9 -> 1
O12: =N8+N15 -> 193
A13: Resumen 2025 | B13: Columna 1 | C13: Columna 2 | D13: Columna 3 | E13: Columna 4 | F13: Columna 5 | G13: Columna 6 | H13: Columna 7 | I13: Columna 8 | J13: Columna 9 | K13: Columna 10 | L13: Columna 11 | M13: Columna 12 | N13: Columna 13
B14: Enero | C14: Febrero | D14: Marzo | E14: Abril | F14: Mayo | G14: Junio | H14: julio | I14: agosto | J14: septiembre | K14: octubre | L14: noviembre | M14: diciembre | N14: Total ordenes
A15: Cantidad ordenes | B15: =semestre1_2025!D8 -> 6 | C15: =semestre1_2025!H5 -> 3 | D15: =semestre1_2025!L8 -> 6 | E15: =semestre1_2025!C31 -> 21 | F15: =semestre1_2025!H11 -> 4 | G15: =semestre1_2025!L32 -> 14 | H15: =semestre2_2025!D15 -> 13 | I15: =semestre2_2025!H5 -> 3 | J15: =semestre2_2025!L15 -> 13 | K15: =semestre2_2025!C26 -> 9 | L15: =semestre2_2025!H9 -> 2 | M15: =semestre2_2025!L20 -> 3 | N15: =SUM(B15:M15) -> 97
A16: Porcentaje ordenes | B16: =B15/$N$15 -> 0.06185567 | C16: =C15/$N$15 -> 0.030927835 | D16: =D15/$N$15 -> 0.06185567 | E16: =E15/$N$15 -> 0.21649485 | F16: =F15/$N$15 -> 0.041237113 | G16: =G15/$N$15 -> 0.1443299 | H16: =H15/$N$15 -> 0.13402062 | I16: =I15/$N$15 -> 0.030927835 | ... N16: =N15/$N$15 -> 1
A17: Porcentaje acumulado | B17: =B16 -> 0.06185567 | C17: =B17+C16 -> 0.092783505 | D17: =C17+D16 -> 0.15463918 | E17: =D17+E16 -> 0.37113402 | F17: =E17+F16 -> 0.41237113 | G17: =F17+G16 -> 0.55670103 | H17: =G17+H16 -> 0.69072165 | I17: =H17+I16 -> 0.72164948 | J17: =I17+J16 -> 0.8556701 | ... M17: =L17+M16 -> 1
